Workbook

Sheet Sheet1
A1: Primary Variables | B1: Secondary Variables | C1: P1 | D1: P2 | E1: P3 | F1: P4 | G1: P5 | H1: P6 | I1: P7 | J1: P8 | K1: P9 | L1: P10 | M1: P11 | N1: P12 | O1: P13
A2: x1 | C2: 1 | D2: 1 | E2: 0 | F2: 0 | G2: 0 | H2: 1 | I2: 1 | J2: 0 | K2: 1 | L2: 1 | M2: 1 | N2: 1 | O2: 1
A3: x1 | C3: 1 | D3: 1 | E3: 1 | F3: 1 | G3: 1 | H3: 1 | I3: 1 | J3: 1 | K3: 1 | L3: 1 | M3: 1 | N3: 1 | O3: 1
A4: x1 | C4: 1 | D4: 1 | E4: 1 | F4: 1 | G4: 0 | H4: 1 | I4: 1 | J4: 1 | K4: 1 | L4: 1 | M4: 1 | N4: 1 | O4: 1
A5: x1 | C5: 1 | D5: 1 | E5: 1 | F5: 1 | G5: 1 | H5: 1 | I5: 1 | J5: 1 | K5: 1 | L5: 1 | M5: 1 | N5: 1 | O5: 1
A6: x1 | C6: 1 | D6: 0 | E6: 0 | F6: 1 | G6: 0 | H6: 1 | I6: 0 | J6: 1 | K6: 1 | L6: 1 | M6: 0 | N6: 0 | O6: 0
A7: x2 | C7: 1 | D7: 1 | E7: 1 | F7: 0 | G7: 0 | H7: 0 | I7: 0 | J7: 0 | K7: 0 | L7: 0 | M7: 0 | N7: 1 | O7: 0
A8: x2 | C8: 1 | D8: 1 | E8: 1 | F8: 0 | G8: 0 | H8: 0 | I8: 0 | J8: 1 | K8: 0 | L8: 0 | M8: 0 | N8: 1 | O8: 0
A9: x2 | C9: 1 | D9: 1 | E9: 1 | F9: 1 | G9: 1 | H9: 1 | I9: 1 | J9: 1 | K9: 1 | L9: 1 | M9: 1 | N9: 1 | O9: 1
A10: x3 | C10: 1 | D10: 1 | E10: 0 | F10: 1 | G10: 0 | H10: 1 | I10: 1 | J10: 1 | K10: 1 | L10: 1 | M10: 1 | N10: 0 | O10: 1
A11: x3 | C11: 0 | D11: 0 | E11: 1 | F11: 1 | G11: 1 | H11: 1 | I11: 1 | J11: 1 | K11: 1 | L11: 1 | M11: 1 | N11: 1 | O11: 1
A12: x4 | C12: 0 | D12: 1 | E12: 0 | F12: 0 | G12: 0 | H12: 0 | I12: 0 | J12: 0 | K12: 0 | L12: 0 | M12: 0 | N12: 0 | O12: 0
A13: x4 | C13: 1 | D13: 0 | E13: 1 | F13: 0 | G13: 0 | H13: 0 | I13: 0 | J13: 0 | K13: 0 | L13: 0 | M13: 0 | N13: 0 | O13: 0
... A34: x9 | C34: 1 | D34: 1 | E34: 1 | F34: 0 | G34: 0 | H34: 1 | I34: 1 | J34: 0 | K34: 1 | L34: 1 | M34: 1 | N34: 1 | O34: 0

Sheet cor
B1: p1 | C1: p2 | D1: p3 | E1: p4 | F1: p5 | G1: p6 | H1: p7 | I1: p8 | J1: p9 | K1: p10 | L1: p11 | M1: p12 | N1: p13
A2: p1 | B2: 1
A3: p2 | B3: 0.262 | C3: 1
A4: p3 | B4: 0.44 | C4: 0.0524 | D4: 1
A5: p4 | B5: 0.131 | C5: -0.0524 | D5: 0.05 | E5: 1
A6: p5 | B6: 0.0339 | C6: -0.0271 | D6: 0.336 | E6: 0.516 | F6: 1
A7: p6 | B7: 0.306 | C7: -0.0524 | D7: 0.1 | E7: 0.667 | F7: 0.516 | G7: 1
A8: p7 | B8: -0.019 | C8: 0.0151 | D8: 0.13 | E8: 0.577 | F8: 0.534 | G8: 0.593 | H8: 1
A9: p8 | B9: 0.105 | C9: 0.07 | D9: 0.0134 | E9: 0.668 | F9: 0.575 | G9: 0.46 | H9: 0.244 | I9: 1
A10: p9 | B10: 0.102 | C10: -0.0125 | D10: -0.0418 | E10: 0.598 | F10: 0.463 | G10: 0.896 | H10: 0.69 | I10: 0.383 | J10: 1
A11: p10 | B11: 0.223 | C11: -0.121 | D11: 0.175 | E11: 0.5 | F11: 0.478 | G11: 0.833 | H11: 0.606 | I11: 0.454 | J11: 0.747 | K11: 1
A12: p11 | B12: 0.223 | C12: 0.225 | D12: 0.175 | E12: 0.65 | F12: 0.478 | G12: 0.833 | H12: 0.606 | I12: 0.454 | J12: 0.747 | K12: 0.67 | L12: 1
A13: p12 | B13: -0.0429 | C13: 0.142 | D13: 0.242 | E13: 0.0933 | F13: 0.193 | G13: 0.202 | H13: 0.484 | I13: 0.0498 | J13: 0.273 | K13: 0.396 | L13: 0.242 | M13: 1
A14: p13 | B14: 0.0806 | C14: 0.189 | D14: -0.0219 | E14: 0.746 | F14: 0.509 | G14: 0.585 | H14: 0.62 | I14: 0.68 | J14: 0.524 | K14: 0.557 | L14: 0.702 | M14: 0.278 | N14: 1
A18: Means | B18: =AVERAGE(B3:B14,C4:C14,D5:D14,E6:E14,F7:F14,G8:G14,H9:H14,I10:I14,J11:J14,K12:K14,L13:L14,M14) -> 0.34616026
A19: Count | B19: =COUNT(B3:B14,C4:C14,D5:D14,E6:E14,F7:F14,G8:G14,H9:H14,I10:I14,J11:J14,K12:K14,L13:L14,M14) -> 78

Sheet 转置
A1: X1.1 | B1: X1.2 | C1: X1.3 | D1: X1.4 | E1: X1.5 | F1: X2.1 | G1: X2.2 | H1: X2.3 | I1: X3.1 | J1: X3.2 | K1: X4.1 | L1: X4.2 | M1: X4.3 | N1: X5.1 | O1: X5.2 | P1: X5.3 | Q1: X5.4 | R1: X5.5 | S1: X5.6 | T1: X6.1 | U1: X6.2 | V1: X7.1 | W1: X7.2 | X1: X7.3 | Y1: X7.4 | Z1: X8.1 | AA1: X8.2 | AB1: X8.3 | AC1: X8.4 | AD1: X9.1 | AE1: X9.2 | AF1: X9.3 | AG1: X9.4
A2: 1 | B2: 1 | C2: 1 | D2: 1 | E2: 1 | F2: 1 | G2: 1 | H2: 1 | I2: 1 | J2: 0 | K2: 0 | L2: 1 | M2: 0 | N2: 1 | O2: 1 | P2: 1 | Q2: 1 | R2: 1 | S2: 1 | T2: 1 | U2: 1 | V2: 1 | W2: 1 | X2: 0 | Y2: 1 | Z2: 1 | AA2: 1 | AB2: 1 | AC2: 1 | AD2: 1 | AE2: 1 | AF2: 1 | AG2: 1
A3: 1 | B3: 1 | C3: 1 | D3: 1 | E3: 0 | F3: 1 | G3: 1 | H3: 1 | I3: 1 | J3: 0 | K3: 1 | L3: 0 | M3: 0 | N3: 1 | O3: 1 | P3: 1 | Q3: 1 | R3: 1 | S3: 1 | T3: 1 | U3: 1 | V3: 1 | W3: 1 | X3: 1 | Y3: 1 | Z3: 0 | AA3: 1 | AB3: 0 | AC3: 0 | AD3: 1 | AE3: 1 | AF3: 1 | AG3: 1
A4: 0 | B4: 1 | C4: 1 | D4: 1 | E4: 0 | F4: 1 | G4: 1 | H4: 1 | I4: 0 | J4: 1 | K4: 0 | L4: 1 | M4: 0 | N4: 1 | O4: 1 | P4: 1 | Q4: 1 | R4: 0 | S4: 1 | T4: 1 | U4: 0 | V4: 1 | W4: 1 | X4: 0 | Y4: 1 | Z4: 1 | AA4: 1 | AB4: 1 | AC4: 1 | AD4: 1 | AE4: 1 | AF4: 1 | AG4: 1
A5: 0 | B5: 1 | C5: 1 | D5: 1 | E5: 1 | F5: 0 | G5: 0 | H5: 1 | I5: 1 | J5: 1 | K5: 0 | L5: 0 | M5: 1 | N5: 1 | O5: 1 | P5: 0 | Q5: 1 | R5: 1 | S5: 0 | T5: 0 | U5: 1 | V5: 1 | W5: 1 | X5: 0 | Y5: 1 | Z5: 1 | AA5: 1 | AB5: 0 | AC5: 1 | AD5: 1 | AE5: 1 | AF5: 1 | AG5: 0
A6: 0 | B6: 1 | C6: 0 | D6: 1 | E6: 0 | F6: 0 | G6: 0 | H6: 1 | I6: 0 | J6: 1 | K6: 0 | L6: 0 | M6: 1 | N6: 1 | O6: 1 | P6: 1 | Q6: 0 | R6: 0 | S6: 0 | T6: 0 | U6: 1 | V6: 1 | W6: 1 | X6: 0 | Y6: 1 | Z6: 1 | AA6: 1 | AB6: 1 | AC6: 0 | AD6: 1 | AE6: 1 | AF6: 1 | AG6: 0
A7: 1 | B7: 1 | C7: 1 | D7: 1 | E7: 1 | F7: 0 | G7: 0 | H7: 1 | I7: 1 | J7: 1 | K7: 0 | L7: 0 | M7: 1 | N7: 1 | O7: 1 | P7: 1 | Q7: 1 | R7: 1 | S7: 1 | T7: 0 | U7: 1 | V7: 1 | W7: 1 | X7: 0 | Y7: 1 | Z7: 1 | AA7: 1 | AB7: 1 | AC7: 1 | AD7: 1 | AE7: 1 | AF7: 1 | AG7: 1
A8: 1 | B8: 1 | C8: 1 | D8: 1 | E8: 0 | F8: 0 | G8: 0 | H8: 1 | I8: 1 | J8: 1 | K8: 0 | L8: 0 | M8: 1 | N8: 1 | O8: 1 | P8: 0 | Q8: 1 | R8: 0 | S8: 0 | T8: 0 | U8: 1 | V8: 1 | W8: 1 | X8: 1 | Y8: 1 | Z8: 1 | AA8: 1 | AB8: 1 | AC8: 1 | AD8: 1 | AE8: 1 | AF8: 1 | AG8: 1
A9: 0 | B9: 1 | C9: 1 | D9: 1 | E9: 1 | F9: 0 | G9: 1 | H9: 1 | I9: 1 | J9: 1 | K9: 0 | L9: 0 | M9: 1 | N9: 1 | O9: 1 | P9: 1 | Q9: 0 | R9: 1 | S9: 0 | T9: 0 | U9: 1 | V9: 1 | W9: 1 | X9: 0 | Y9: 1 | Z9: 1 | AA9: 0 | AB9: 0 | AC9: 0 | AD9: 1 | AE9: 1 | AF9: 1 | AG9: 0
A10: 1 | B10: 1 | C10: 1 | D10: 1 | E10: 1 | F10: 0 | G10: 0 | H10: 1 | I10: 1 | J10: 1 | K10: 0 | L10: 0 | M10: 1 | N10: 1 | O10: 1 | P10: 1 | Q10: 1 | R10: 1 | S10: 1 | T10: 0 | U10: 1 | V10: 1 | W10: 1 | X10: 1 | Y10: 1 | Z10: 1 | AA10: 1 | AB10: 1 | AC10: 1 | AD10: 1 | AE10: 1 | AF10: 1 | AG10: 1
A11: 1 | B11: 1 | C11: 1 | D11: 1 | E11: 1 | F11: 0 | G11: 0 | H11: 1 | I11: 1 | J11: 1 | K11: 0 | L11: 0 | M11: 1 | N11: 1 | O11: 1 | P11: 1 | Q11: 1 | R11: 0 | S11: 1 | T11: 0 | U11: 1 | V11: 1 | W11: 1 | X11: 0 | Y11: 1 | Z11: 1 | AA11: 0 | AB11: 1 | AC11: 1 | AD11: 1 | AE11: 1 | AF11: 1 | AG11: 1
A12: 1 | B12: 1 | C12: 1 | D12: 1 | E12: 0 | F12: 0 | G12: 0 | H12: 1 | I12: 1 | J12: 1 | K12: 0 | L12: 0 | M12: 1 | N12: 1 | O12: 1 | P12: 1 | Q12: 1 | R12: 1 | S12: 1 | T12: 0 | U12: 1 | V12: 1 | W12: 1 | X12: 0 | Y12: 1 | Z12: 1 | AA12: 1 | AB12: 0 | AC12: 1 | AD12: 1 | AE12: 1 | AF12: 1 | AG12: 1
A13: 1 | B13: 1 | C13: 1 | D13: 1 | E13: 0 | F13: 1 | G13: 1 | H13: 1 | I13: 0 | J13: 1 | K13: 0 | L13: 0 | M13: 1 | N13: 1 | O13: 0 | P13: 0 | Q13: 1 | R13: 0 | S13: 1 | T13: 0 | U13: 1 | V13: 1 | W13: 1 | X13: 1 | Y13: 1 | Z13: 0 | AA13: 0 | AB13: 1 | AC13: 1 | AD13: 1 | AE13: 1 | AF13: 1 | AG13: 1
A14: 1 | B14: 1 | C14: 1 | D14: 1 | E14: 0 | F14: 0 | G14: 0 | H14: 1 | I14: 1 | J14: 1 | K14: 0 | L14: 0 | M14: 1 | N14: 1 | O14: 1 | P14: 0 | Q14: 1 | R14: 1 | S14: 0 | T14: 0 | U14: 1 | V14: 1 | W14: 1 | X14: 0 | Y14: 1 | Z14: 1 | AA14: 0 | AB14: 0 | AC14: 0 | AD14: 1 | AE14: 1 | AF14: 1 | AG14: 0

Sheet Sheet2
A1: Paper_11 | B1: Paper_12 | C1: Paper_13
A2: 0.86 | B2: 0.83 | C2: 1
A3: 0.83 | B3: 0.62 | C3: 0.62
A4: 0.5 | B4: 1 | C4: 1

Sheet Sheet3
A1: Paper_11 | B1: Paper_12 | C1: Paper_13
A2: 0.86 | B2: 1 | C2: 1
A3: 0.83 | B3: 0.62 | C3: 0.62
A4: 0.5 | B4: 0.4 | C4: 1

Sheet Sheet4
A1: Paper_11 | B1: Paper_12 | C1: Paper_13
A2: 0.86 | B2: 1 | C2: 0.3
A3: 1 | B3: 0.62 | C3: 1
A4: 0.5 | B4: 1 | C4: 1

Sheet Sheet5
A1: Paper_11 | B1: Paper_12 | C1: Paper_13
A2: 1 | B2: 1 | C2: 1
A3: 1 | B3: 0.8 | C3: 1
A4: 0.8 | B4: 1 | C4: 1

Sheet 测试
A2: 主要变量 | B2: P1 | C2: P2 | D2: P3 | E2: P4 | F2: P5 | G2: P6 | H2: P7 | I2: P8 | J2: P9 | K2: P10 | L2: P11 | M2: P12 | N2: 平均的
A4: X 1 | B4: 0.8 | C4: 0.8 | D4: 0.8 | E4: 0.8 | F4: 1 | G4: 1 | H4: 0.8 | I4: 0.8 | J4: 0.8 | K4: 1 | L4: 1 | M4: 0.8 | N4: 0.87
A5: X 2 | B5: 0.5 | C5: 0.5 | D5: 0.25 | E5: 0.25 | F5: 0.25 | G5: 0.25 | H5: 0.5 | I5: 0.75 | J5: 0.25 | K5: 0.5 | L5: 0.5 | M5: 0.25 | N5: 0.4
A6: X 3 | B6: 0.67 | C6: 1 | D6: 1 | E6: 1 | F6: 0.67 | G6: 1 | H6: 1 | I6: 1 | J6: 1 | K6: 1 | L6: 1 | M6: 0.67 | N6: 0.92
A7: X 4 | B7: 0.75 | C7: 0.5 | D7: 0.75 | E7: 0 | F7: 0.25 | G7: 0.5 | H7: 0.5 | I7: 0.5 | J7: 0.5 | K7: 0.75 | L7: 0.5 | M7: 0.25 | N7: 0.48
A8: X 5 | B8: 1 | C8: 1 | D8: 1 | E8: 1 | F8: 0.83 | G8: 1 | H8: 1 | I8: 1 | J8: 1 | K8: 1 | L8: 1 | M8: 0.83 | N8: 0.97
A9: X 6 | B9: 1 | C9: 1 | D9: 1 | E9: 1 | F9: 0.75 | G9: 1 | H9: 1 | I9: 1 | J9: 1 | K9: 1 | L9: 1 | M9: 0.75 | N9: 0.96
A10: X 7 | B10: 0.6 | C10: 0.8 | D10: 1 | E10: 0.6 | F10: 0.8 | G10: 1 | H10: 0.8 | I10: 1 | J10: 1 | K10: 1 | L10: 1 | M10: 0.8 | N10: 0.87
A11: X 8 | B11: 1 | C11: 1 | D11: 1 | E11: 1 | F11: 0.75 | G11: 1 | H11: 0.75 | I11: 0.75 | J11: 1 | K11: 1 | L11: 1 | M11: 1 | N11: 0.94
A12: X 9 | B12: 0.67 | C12: 0.67 | D12: 0.67 | E12: 0.67 | F12: 0.67 | G12: 0.67 | H12: 0.67 | I12: 1 | J12: 0.67 | K12: 0.67 | L12: 0.67 | M12: 0.67 | N12: 0.7
A13: X 10 | B13: 1 | C13: 1 | D13: 1 | E13: 1 | F13: 1 | G13: 1 | H13: 1 | I13: 1 | J13: 1 | K13: 1 | L13: 1 | M13: 1 | N13: 1
A14: 总得分 | B14: 7.99 | C14: 8.27 | D14: 8.47 | E14: 7.32 | F14: 6.97 | G14: 8.42 | H14: 8.02 | I14: 8.8 | J14: 8.22 | K14: 8.92 | L14: 8.67 | M14: 7.02 | N14: 8.09
A15: 排行 | B15: 9 | C15: 6 | D15: 4 | E15: 10 | F15: 12 | G15: 5 | H15: 8 | I15: 2 | J15: 7 | K15: 1 | L15: 3 | M15: 11 | N15: —
A16: 等级 | B16: 好的 | C16: 好的 | D16: 好的 | E16: 好的 | F16: 可以接受 | G16: 好的 | H16: 好的 | I16: 好的 | J16: 好的 | K16: 好的 | L16: 好的 | M16: 好的 | N16: —
B22: =B4 -> 0.8 | C22: =B7 -> 0.75 | D22: =B10 -> 0.6
B23: =B5 -> 0.5 | C23: =B8 -> 1 | D23: =B11 -> 1
B24: =B6 -> 0.67 | C24: =B9 -> 1 | D24: =B12 -> 0.67

Sheet Evaluation
A1: Section 1
A2: 1 | B2: Supervision Objects
B3: Development Enterprises
B4: Compliance with fund use regulations
B5: Transparent reporting and documentation
B6: Municipal and County Construction Departments
B7: Regular inspections and audits
B8: Enforcement of compliance
B9: Commercial Banks
B10: Accurate management of supervision accounts
B11: Timely and correct fund disbursement
A12: 2 | B12: Developer Responsibilities
B13: Apply for pre-sale permits
B14: Establish supervision accounts
B15: Sign supervision agreements
B16: Comply with fund use nodes
B17: Guaranteeing the delivery of housing
A18: 3 | B18: Construction Departments' Responsibilities
B19: Select commercial banks through bidding
B20: Formulate supervision implementation rules
B21: Determine supervision quotas
B22: Supervise fund use
B23: Handle illegal behaviors
A24: 4 | B24: Coordination Mechanism
B25: Determine the service bank through bidding
B26: Guaranteeing the delivery of housing
A27: 5 | B27: Commercial Banks' Responsibilities
B28: Manage supervision accounts
B29: Monitor and allocate funds
B30: Conduct regular reconciliation
A31: 6 | B31: Supervision policy Period
B32: From the issuance of the "Commercial Housing Pre-sale Permit"
B33: To the first registration of property rights aŌ er project completion
A34: 7 | B34: Types of Funds
B35: Deposit
B36: Down Payment
B37: Housing Provident Fund Loans
B38: Mortgage Loans
B39: Other Forms of House Purchase Payments
B40: Any additional payments related to the purchase
A41: 8 | B41: Supervision Content
B42: Storage
B43: Use
B44: Presale funds
A45: 9 | B45: Supervision Principles
B46: Dedicated Account Storage
B47: Exclusive Fund Use
B48: Full-Process Supervision
B49: Node Control
B50: Multi-Party Supervision
A51: 10 | B51: Policy Issuing Authorities
B52: Provincial
B53: Municipal
B54: Country
A55: Section 2
A56: 1 | B56: Policy Goals
B57: Ensure Project Completion and Delivery
B58: Protect Buyers' Rights
B59: Promote Stable Real Estate Market Development
A60: 2 | B60: Supervision Fcous
B61: Exclusive Use of Funds
B62: Prioritize Payments for Construction Costs
A63: 3 | B63: Fund use Nodes
B64: Completion of Underground Structure
B65: Structural Division Inspection
B66: Scaffold Removal
B67: Completion Acceptance Filing
B68: Joint Acceptance
B69: First Property Registration
A70: 4 | B70: Approval Process
B71: Verification Process
B72: Timely Approval
A73: 5 | B73: Disbursement Conditions
B74: Developers' Application Submission of detailed applications for fund use
B75: Verification and Approval Municipal and county departments verify progress and approve disbursement
A76: 6 | B76: Excess Fund Usage
B77: Usage of Excess Funds
B78: Flexible Fund Management
A79: 7 | B79: Bank Responsibilities
B80: Accurate Fund Disbursement
B81: Timely Execution
A82: 8 | B82: Suspension Conditions
B83: Construction Suspension
B84: Quality Issues
B85: Delayed Delivery
B86: illegal Construction and Sales
B87: Serious Debt and Labor Disputes
A88: 9 | B88: Information Sharing
B89: Integration of Systems
B90: Enhanced Monitoring
A91: 10 | B91: Legal Responsibilities
B92: Accountability Measures
B93: Strict Enforcement
A94: Section 3
A95: 1 | B95: Policy Issuing Authorities | D95: 1. X1 | H95: Policy Issuing Agency
B96: Provinces | D96: 1.1
B97: Cities | D97: 1.2
B98: Country-level Cities | D98: 1.3
B99: Level Unknown | D99: 1.4
A100: 2 | B100: Credit Grade Classification | D100: 2. X10
...

Sheet Evaluation-transfer
B1: X1 | E1: X2 | I1: X3 | L1: X4 | N1: X5 | S1: X6 | V1: X7 | AA1: X8 | AC1: X9 | AL1: Original Column | AM1: New Column
B2: X1: 1 | C2: X1: 2 | D2: X1: 3 | E2: X2: 1 | F2: X2: 2 | G2: X2: 3 | H2: X2: 4 | I2: X3: 1 | J2: X3: 2 | K2: X3: 3 | L2: X4: 1 | M2: X4: 2 | N2: X5: 1 | O2: X5: 2 | P2: X5: 3 | Q2: X5: 4 | R2: X5: 5 | S2: X6: 1 | T2: X6: 2 | U2: X6: 3 | V2: X7: 1 | W2: X7: 2 | X2: X7: 3 | Y2: X7: 4 | Z2: X7: 5 | AA2: X8: 1 | AB2: X8: 2 | AC2: X9: 1 | AD2: X9: 2 | AE2: X9: 3 | AF2: X9: 4 | AG2: X9: 5 | AH2: X10 | AL2: Main Indicators and Variables | AM2: Main Indicators and Variables
A3: P1 | B3: 0 | C3: 0 | D3: 1 | E3: 0 | F3: 0 | G3: 0 | H3: 0 | I3: 0 | J3: 0 | K3: 1 | L3: 1 | M3: 0 | N3: 1 | O3: 1 | P3: 1 | Q3: 0 | R3: 1 | S3: 1 | T3: 1 | U3: 0 | V3: 0 | W3: 0 | X3: 0 | Y3: 0 | Z3: 0 | AA3: 0 | AB3: 0 | AC3: 1 | AD3: 0 | AE3: 1 | AF3: 0 | AG3: 0 | AH3: 0 | AL3: Sub Indicators and Variables | AM3: Sub Indicators and Variables
A4: P2 | B4: 0 | C4: 1 | D4: 0 | E4: 0 | F4: 0 | G4: 0 | H4: 1 | I4: 0 | J4: 0 | K4: 0 | L4: 1 | M4: 0 | N4: 1 | O4: 1 | P4: 1 | Q4: 1 | R4: 1 | S4: 1 | T4: 0 | U4: 0 | V4: 1 | W4: 1 | X4: 1 | Y4: 0 | Z4: 1 | AA4: 0 | AB4: 0 | AC4: 0 | AD4: 0 | AE4: 1 | AF4: 0 | AG4: 0 | AH4: 0 | AL4: Chinese cities' name | AM4: English cities' name | AN4: # | AO4: Chinese cities' name | AP4: English cities' name | AQ4: # | AR4: Chinese cities' name | AS4: English cities' name | AT4: #
A5: P3 | B5: 1 | C5: 0 | D5: 0 | E5: 0 | F5: 0 | G5: 1 | H5: 0 | I5: 0 | J5: 3 | K5: 1 | L5: 1 | M5: 0 | N5: 2 | O5: 2 | P5: 1 | Q5: 2 | R5: 1 | S5: 1 | T5: 1 | U5: 1 | V5: 1 | W5: 2 | X5: 0 | Y5: 1 | Z5: 0 | AA5: 1 | AB5: 0 | AC5: 2 | AD5: 0 | AE5: 1 | AF5: 0 | AG5: 0 | AH5: 0 | AL5: 白沙县 | AM5: Baisha County | AN5: P1 | AO5: 九江市 | AP5: Jiujiang City | AQ5: P15 | AR5: 韶关 | AS5: Shaoguan | AT5: P29
A6: P4 | B6: 0 | C6: 0 | D6: 1 | E6: 0 | F6: 0 | G6: 0 | H6: 1 | I6: 0 | J6: 1 | K6: 0 | L6: 1 | M6: 0 | N6: 0 | O6: 1 | P6: 0 | Q6: 1 | R6: 2 | S6: 2 | T6: 1 | U6: 1 | V6: 1 | W6: 0 | X6: 0 | Y6: 0 | Z6: 0 | AA6: 0 | AB6: 0 | AC6: 1 | AD6: 0 | AE6: 1 | AF6: 1 | AG6: 0 | AH6: 0 | AL6: 北海市 | AM6: Beihai City | AN6: P2 | AO6: 兰州 | AP6: Lanzhou | AQ6: P16 | AR6: 深圳市 | AS6: Shenzhen | AT6: P30
A7: P5 | B7: 0 | C7: 1 | D7: 0 | E7: 1 | F7: 0 | G7: 0 | H7: 0 | I7: 0 | J7: 1 | K7: 0 | L7: 1 | M7: 0 | N7: 0 | O7: 1 | P7: 0 | Q7: 1 | R7: 2 | S7: 2 | T7: 2 | U7: 0 | V7: 1 | W7: 0 | X7: 0 | Y7: 0 | Z7: 0 | AA7: 0 | AB7: 0 | AC7: 0 | AD7: 0 | AE7: 0 | AF7: 0 | AG7: 0 | AH7: 0 | AL7: 北京市 | AM7: Beijing | AN7: P3 | AO7: 乐东县 | AP7: Ledong County | AQ7: P17 | AR7: 万宁市 | AS7: Wanning City | AT7: P31
A8: P6 | B8: 1 | C8: 0 | D8: 0 | E8: 0 | F8: 0 | G8: 0 | H8: 1 | I8: 0 | J8: 0 | K8: 0 | L8: 1 | M8: 0 | N8: 0 | O8: 0 | P8: 0 | Q8: 0 | R8: 0 | S8: 2 | T8: 0 | U8: 0 | V8: 1 | W8: 0 | X8: 1 | Y8: 1 | Z8: 1 | AA8: 0 | AB8: 1 | AC8: 1 | AD8: 0 | AE8: 1 | AF8: 0 | AG8: 0 | AH8: 0 | AL8: 澄迈县 | AM8: Chengmai County | AN8: P4 | AO8: 乐山市 | AP8: Leshan City | AQ8: P18 | AR8: 文昌市 | AS8: Wenchang City | AT8: P32
A9: P7 | B9: 0 | C9: 0 | D9: 1 | E9: 0 | F9: 1 | G9: 0 | H9: 0 | I9: 0 | J9: 0 | K9: 0 | L9: 1 | M9: 0 | N9: 0 | O9: 2 | P9: 2 | Q9: 2 | R9: 2 | S9: 2 | T9: 2 | U9: 0 | V9: 0 | W9: 0 | X9: 0 | Y9: 0 | Z9: 0 | AA9: 0 | AB9: 0 | AC9: 0 | AD9: 0 | AE9: 0 | AF9: 0 | AG9: 0 | AH9: 0 | AL9: 儋州市 | AM9: Danzhou City | AN9: P5 | AO9: 丽水市 | AP9: Lishui City | AQ9: P19 | AR9: 五指山 | AS9: Wuzhishan | AT9: P33
A10: P8 | B10: 0 | C10: 1 | D10: 0 | E10: 0 | F10: 1 | G10: 0 | H10: 0 | I10: 0 | J10: 1 | K10: 3 | L10: 1 | M10: 0 | N10: 0 | O10: 2 | P10: 1 | Q10: 1 | R10: 1 | S10: 4 | T10: 3 | U10: 0 | V10: 3 | W10: 1 | X10: 1 | Y10: 1 | Z10: 1 | AA10: 1 | AB10: 0 | AC10: 0 | AD10: 1 | AE10: 1 | AF10: 0 | AG10: 0 | AH10: 1 | AL10: 定安县 | AM10: Ding'an County | AN10: P6 | AO10: 临高 | AP10: Lingao | AQ10: P20 | AR10: 信阳市 | AS10: Xinyang City | AT10: P34
A11: P9 | B11: 0 | C11: 1 | D11: 0 | E11: 0 | F11: 1 | G11: 0 | H11: 0 | I11: 0 | J11: 1 | K11: 2 | L11: 1 | M11: 0 | N11: 1 | O11: 2 | P11: 2 | Q11: 2 | R11: 2 | S11: 1 | T11: 0 | U11: 0 | V11: 1 | W11: 1 | X11: 0 | Y11: 1 | Z11: 0 | AA11: 1 | AB11: 0 | AC11: 0 | AD11: 0 | AE11: 0 | AF11: 0 | AG11: 0 | AH11: 1 | AL11: 东方市 | AM11: Dongfang City | AN11: P7 | AO11: 陵水 | AP11: Lingshui | AQ11: P21 | AR11: 义乌 | AS11: Yiwu | AT11: P35
A12: P10 | B12: 0 | C12: 1 | D12: 0 | E12: 0 | F12: 1 | G12: 0 | H12: 0 | I12: 0 | J12: 1 | K12: 0 | L12: 2 | M12: 0 | N12: 1 | O12: 2 | P12: 2 | Q12: 2 | R12: 1 | S12: 1 | T12: 1 | U12: 0 | V12: 0 | W12: 1 | X12: 0 | Y12: 0 | Z12: 0 | AA12: 0 | AB12: 0 | AC12: 1 | AD12: 0 | AE12: 0 | AF12: 0 | AG12: 0 | AH12: 2 | AL12: 东莞 | AM12: Dongguan | AN12: P8 | AO12: 六安 | AP12: Lu'an | AQ12: P22 | AR12: 肇庆市 | AS12: Zhaoqing City | AT12: P36
A13: P11 | B13: 0 | C13: 1 | D13: 0 | E13: 0 | F13: 0 | G13: 0 | H13: 1 | I13: 0 | J13: 0 | K13: 0 | L13: 0 | M13: 1 | N13: 0 | O13: 1 | P13: 1 | Q13: 1 | R13: 0 | S13: 1 | T13: 2 | U13: 0 | V13: 1 | W13: 1 | X13: 0 | Y13: 0 | Z13: 0 | AA13: 0 | AB13: 0 | AC13: 0 | AD13: 0 | AE13: 0 | AF13: 0 | AG13: 0 | AH13: 0 | AL13: 东营市 | AM13: Dongying City | AN13: P9 | AO13: 清远市 | AP13: Qingyuan City | AQ13: P23 | AR13: 中山 | AS13: Zhongshan | AT13: P37
A14: P12 | B14: 0 | C14: 0 | D14: 0 | E14: 0 | F14: 0 | G14: 0 | H14: 0 | I14: 0 | J14: 1 | K14: 0 | L14: 0 | M14: 0 | N14: 1 | O14: 1 | P14: 1 | Q14: 1 | R14: 1 | S14: 2 | T14: 1 | U14: 0 | V14: 1 | W14: 1 | X14: 0 | Y14: 0 | Z14: 0 | AA14: 0 | AB14: 0 | AC14: 0 | AD14: 0 | AE14: 0 | AF14: 0 | AG14: 0 | AH14: 0 | AL14: 佛山市 | AM14: Foshan City | AN14: P10 | AO14: 琼海市 | AP14: Qionghai City | AQ14: P24 | AR14: 中卫 | AS14: Zhongwei | AT14: P38
A15: P13 | B15: 0 | C15: 1 | D15: 0 | E15: 2 | F15: 0 | G15: 0 | H15: 0 | I15: 0 | J15: 2 | K15: 1 | L15: 0 | M15: 1 | N15: 1 | O15: 1 | P15: 1 | Q15: 1 | R15: 0 | S15: 1 | T15: 1 | U15: 0 | V15: 0 | W15: 1 | X15: 0 | Y15: 0 | Z15: 0 | AA15: 0 | AB15: 0 | AC15: 0 | AD15: 0 | AE15: 0 | AF15: 0 | AG15: 0 | AH15: 0 | AL15: 广州市 | AM15: Guangzhou | AN15: P11 | AO15: 琼中县 | AP15: Qiongzhong County | AQ15: P25 | AR15: 珠海市 | AS15: Zhuhai City | AT15: P39
... A17: P15 | B17: 0 | C17: 1 | D17: 0 | E17: 0 | F17: 0 | G17: 0 | H17: 1 | I17: 0 | J17: 3 | K17: 1 | L17: 1 | M17: 0 | N17: 2 | O17: 1 | P17: 1 | Q17: 3 | R17: 1 | S17: 4 | T17: 1 | U17: 0 | V17: 3 | W17: 2 | X17: 0 | Y17: 0 | Z17: 0 | AA17: 0 | AB17: 0 | AC17: 0 | AD17: 0 | AE17: 0 | AF17: 0 | AG17: 0 | AH17: 0 | AL17: 合肥市 | AM17: Hefei | AN17: P13 | AO17: 上海 | AP17: Shanghai | AQ17: P27 | AR17: 昌江县 | AS17: Changjiang County | AT17: P41
A18: P16 | B18: 0 | C18: 1 | D18: 0 | E18: 0 | F18: 1 | G18: 0 | H18: 0 | I18: 0 | J18: 1 | K18: 0 | L18: 1 | M18: 0 | N18: 2 | O18: 2 | P18: 2 | Q18: 2 | R18: 2 | S18: 1 | T18: 2 | U18: 0 | V18: 1 | W18: 1 | X18: 0 | Y18: 0 | Z18: 0 | AA18: 0 | AB18: 0 | AC18: 1 | AD18: 0 | AE18: 1 | AF18: 0 | AG18: 0 | AH18: 1 | AL18: 惠州 | AM18: Huizhou | AN18: P14 | AO18: 上饶 | AP18: Shangrao | AQ18: P28
A19: P17 | B19: 0 | C19: 0 | D19: 1 | E19: 0 | F19: 0 | G19: 0 | H19: 1 | I19: 0 | J19: 0 | K19: 0 | L19: 1 | M19: 0 | N19: 0 | O19: 1 | P19: 1 | Q19: 1 | R19: 1 | S19: 1 | T19: 0 | U19: 0 | V19: 0 | W19: 0 | X19: 0 | Y19: 0 | Z19: 0 | AA19: 0 | AB19: 0 | AC19: 0 | AD19: 0 | AE19: 0 | AF19: 0 | AG19: 0 | AH19: 0
A20: P18 | B20: 0 | C20: 1 | D20: 0 | E20: 0 | F20: 0 | G20: 1 | H20: 0 | I20: 1 | J20: 0 | K20: 0 | L20: 1 | M20: 0 | N20: 1 | O20: 1 | P20: 1 | Q20: 1 | R20: 1 | S20: 2 | T20: 0 | U20: 0 | V20: 1 | W20: 2 | X20: 0 | Y20: 0 | Z20: 0 | AA20: 0 | AB20: 0 | AC20: 1 | AD20: 0 | AE20: 1 | AF20: 0 | AG20: 0 | AH20: 1
A21: P19 | B21: 1 | C21: 0 | D21: 0 | E21: 0 | F21: 0 | G21: 0 | H21: 1 | I21: 0 | J21: 1 | K21: 0 | L21: 1 | M21: 0 | N21: 0 | O21: 0 | P21: 1 | Q21: 2 | R21: 2 | S21: 1 | T21: 1 | U21: 0 | V21: 0 | W21: 0 | X21: 0 | Y21: 0 | Z21: 0 | AA21: 0 | AB21: 0 | AC21: 0 | AD21: 0 | AE21: 0 | AF21: 0 | AG21: 0 | AH21: 0
A22: P20 | B22: 1 | C22: 0 | D22: 0 | E22: 0 | F22: 0 | G22: 0 | H22: 1 | I22: 0 | J22: 2 | K22: 0 | L22: 1 | M22: 0 | N22: 0 | O22: 0 | P22: 0 | Q22: 0 | R22: 0 | S22: 3 | T22: 1 | U22: 0 | V22: 1 | W22: 0 | X22: 1 | Y22: 0 | Z22: 1 | AA22: 0 | AB22: 0 | AC22: 1 | AD22: 0 | AE22: 1 | AF22: 0 | AG22: 0 | AH22: 0
A23: P21 | B23: 1 | C23: 1 | D23: 0 | E23: 0 | F23: 0 | G23: 0 | H23: 1 | I23: 0 | J23: 0 | K23: 0 | L23: 1 | M23: 0 | N23: 0 | O23: 0 | P23: 0 | Q23: 0 | R23: 0 | S23: 2 | T23: 0 | U23: 0 | V23: 1 | W23: 0 | X23: 1 | Y23: 1 | Z23: 1 | AA23: 0 | AB23: 1 | AC23: 1 | AD23: 0 | AE23: 1 | AF23: 0 | AG23: 0 | AH23: 0
A24: P22 | B24: 0 | C24: 1 | D24: 0 | E24: 0 | F24: 0 | G24: 0 | H24: 1 | I24: 0 | J24: 2 | K24: 1 | L24: 1 | M24: 0 | N24: 1 | O24: 1 | P24: 1 | Q24: 1 | R24: 0 | S24: 2 | T24: 0 | U24: 0 | V24: 1 | W24: 1 | X24: 0 | Y24: 0 | Z24: 0 | AA24: 0 | AB24: 0 | AC24: 0 | AD24: 0 | AE24: 2 | AF24: 0 | AG24: 0 | AH24: 0
A25: P23 | B25: 0 | C25: 1 | D25: 0 | E25: 0 | F25: 1 | G25: 0 | H25: 0 | I25: 1 | J25: 3 | K25: 0 | L25: 0 | M25: 0 | N25: 0 | O25: 1 | P25: 1 | Q25: 2 | R25: 0 | S25: 2 | T25: 1 | U25: 0 | V25: 1 | W25: 1 | X25: 1 | Y25: 0 | Z25: 1 | AA25: 0 | AB25: 0 | AC25: 1 | AD25: 0 | AE25: 2 | AF25: 0 | AG25: 0 | AH25: 1
A26: P24 | B26: 0 | C26: 1 | D26: 0 | E26: 0 | F26: 0 | G26: 0 | H26: 1 | I26: 0 | J26: 1 | K26: 0 | L26: 1 | M26: 0 | N26: 0 | O26: 0 | P26: 1 | Q26: 1 | R26: 1 | S26: 1 | T26: 1 | U26: 0 | V26: 0 | W26: 0 | X26: 0 | Y26: 0 | Z26: 0 | AA26: 0 | AB26: 0 | AC26: 0 | AD26: 0 | AE26: 0 | AF26: 0 | AG26: 0 | AH26: 0
A27: P25 | B27: 0 | C27: 0 | D27: 1 | E27: 1 | F27: 0 | G27: 0 | H27: 0 | I27: 0 | J27: 1 | K27: 1 | L27: 1 | M27: 0 | N27: 1 | O27: 1 | P27: 1 | Q27: 0 | R27: 1 | S27: 2 | T27: 0 | U27: 0 | V27: 2 | W27: 2 | X27: 1 | Y27: 0 | Z27: 1 | AA27: 0 | AB27: 0 | AC27: 1 | AD27: 0 | AE27: 1 | AF27: 0 | AG27: 0 | AH27: 0
A28: P26 | B28: 0 | C28: 1 | D28: 0 | E28: 1 | F28: 0 | G28: 0 | H28: 0 | I28: 2 | J28: 2 | K28: 0 | L28: 0 | M28: 0 | N28: 1 | O28: 1 | P28: 1 | Q28: 1 | R28: 1 | S28: 2 | T28: 1 | U28: 1 | V28: 3 | W28: 0 | X28: 0 | Y28: 0 | Z28: 0 | AA28: 0 | AB28: 0 | AC28: 1 | AD28: 0 | AE28: 1 | AF28: 0 | AG28: 0 | AH28: 0
A29: P27 | B29: 0 | C29: 1 | D29: 0 | E29: 0 | F29: 0 | G29: 1 | H29: 0 | I29: 0 | J29: 0 | K29: 0 | L29: 0 | M29: 1 | N29: 1 | O29: 1 | P29: 1 | Q29: 1 | R29: 0 | S29: 2 | T29: 1 | U29: 1 | V29: 0 | W29: 0 | X29: 0 | Y29: 0 | Z29: 0 | AA29: 0 | AB29: 0 | AC29: 0 | AD29: 0 | AE29: 0 | AF29: 1 | AG29: 0 | AH29: 0
A30: P28 | B30: 0 | C30: 1 | D30: 0 | E30: 0 | F30: 0 | G30: 0 | H30: 1 | I30: 0 | J30: 3 | K30: 2 | L30: 0 | M30: 1 | N30: 0 | O30: 0 | P30: 0 | Q30: 1 | R30: 2 | S30: 0 | T30: 0 | U30: 0 | V30: 1 | W30: 2 | X30: 0 | Y30: 1 | Z30: 0 | AA30: 0 | AB30: 1 | AC30: 0 | AD30: 0 | AE30: 1 | AF30: 0 | AG30: 0 | AH30: 0
... A43: P41 | B43: 1 | C43: 0 | D43: 0 | E43: 0 | F43: 0 | G43: 0 | H43: 1 | I43: 0 | J43: 0 | K43: 1 | L43: 1 | M43: 0 | N43: 0 | O43: 0 | P43: 0 | Q43: 1 | R43: 0 | S43: 3 | T43: 0 | U43: 1 | V43: 1 | W43: 0 | X43: 1 | Y43: 0 | Z43: 1 | AA43: 0 | AB43: 1 | AC43: 1 | AD43: 0 | AE43: 1 | AF43: 0 | AG43: 0 | AH43: 0
B45: =B1 -> X1 | C45: =C1 -> 0 | D45: =D1 -> 0 | E45: =E1 -> X2 | F45: =F1 -> 0 | G45: =G1 -> 0 | H45: =H1 -> 0 | I45: =I1 -> X3 | ... AG45: =AG1 -> 0 | AH45: =AH2 -> X10
A46: =A3 -> P1 | B46: =B3/COUNT($B3:$D3) -> 0 | C46: =C3/COUNT($B3:$D3) -> 0 | D46: =D3/COUNT($B3:$D3) -> 0.33333333 | E46: =E3/COUNT($E3:$H3) -> 0 | F46: =F3/COUNT($E3:$H3) -> 0 | G46: =G3/COUNT($E3:$H3) -> 0 | H46: =H3/COUNT($E3:$H3) -> 0 | I46: =I3/COUNT($I3:$K3) -> 0 | J46: =J3/COUNT($I3:$K3) -> 0 | K46: =K3/COUNT($I3:$K3) -> 0.33333333 | L46: =L3/COUNT($L3:$M3) -> 0.5 | M46: =M3/COUNT($L3:$M3) -> 0 | N46: =N3/COUNT($N3:$R3) -> 0.2 | O46: =O3/COUNT($N3:$R3) -> 0.2 | P46: =P3/COUNT($N3:$R3) -> 0.2 | Q46: =Q3/COUNT($N3:$R3) -> 0 | R46: =R3/COUNT($N3:$R3) -> 0.2 | S46: =S3/COUNT($S3:$U3) -> 0.33333333 | T46: =T3/COUNT($S3:$U3) -> 0.33333333 | U46: =U3/COUNT($S3:$U3) -> 0 | V46: =V3/COUNT($V3:$Z3) -> 0 | W46: =W3/COUNT($V3:$Z3) -> 0 | X46: =X3/COUNT($V3:$Z3) -> 0 | Y46: =Y3/COUNT($V3:$Z3) -> 0 | Z46: =Z3/COUNT($V3:$Z3) -> 0 | AA46: =AA3/COUNT($AA3:$AB3) -> 0 | AB46: =AB3/COUNT($AA3:$AB3) -> 0 | AC46: =AC3/COUNT($AC3:$AG3) -> 0.2 | AD46: =AD3/COUNT($AC3:$AG3) -> 0 | AE46: =AE3/COUNT($AC3:$AG3) -> 0.2 | AF46: =AF3/COUNT($AC3:$AG3) -> 0 | AG46: =AG3/COUNT($AC3:$AG3) -> 0 | AH46: =AH3 -> 0
A47: =A4 -> P2 | B47: =B4/COUNT($B4:$D4) -> 0 | C47: =C4/COUNT($B4:$D4) -> 0.33333333 | D47: =D4/COUNT($B4:$D4) -> 0 | E47: =E4/COUNT($E4:$H4) -> 0 | F47: =F4/COUNT($E4:$H4) -> 0 | G47: =G4/COUNT($E4:$H4) -> 0 | H47: =H4/COUNT($E4:$H4) -> 0.25 | I47: =I4/COUNT($I4:$K4) -> 0 | J47: =J4/COUNT($I4:$K4) -> 0 | K47: =K4/COUNT($I4:$K4) -> 0 | L47: =L4/COUNT($L4:$M4) -> 0.5 | M47: =M4/COUNT($L4:$M4) -> 0 | N47: =N4/COUNT($N4:$R4) -> 0.2 | O47: =O4/COUNT($N4:$R4) -> 0.2 | P47: =P4/COUNT($N4:$R4) -> 0.2 | Q47: =Q4/COUNT($N4:$R4) -> 0.2 | R47: =R4/COUNT($N4:$R4) -> 0.2 | S47: =S4/COUNT($S4:$U4) -> 0.33333333 | T47: =T4/COUNT($S4:$U4) -> 0 | U47: =U4/COUNT($S4:$U4) -> 0 | V47: =V4/COUNT($V4:$Z4) -> 0.2 | W47: =W4/COUNT($V4:$Z4) -> 0.2 | X47: =X4/COUNT($V4:$Z4) -> 0.2 | Y47: =Y4/COUNT($V4:$Z4) -> 0 | Z47: =Z4/COUNT($V4:$Z4) -> 0.2 | AA47: =AA4/COUNT($AA4:$AB4) -> 0 | AB47: =AB4/COUNT($AA4:$AB4) -> 0 | AC47: =AC4/COUNT($AC4:$AG4) -> 0 | AD47: =AD4/COUNT($AC4:$AG4) -> 0 | AE47: =AE4/COUNT($AC4:$AG4) -> 0.2 | AF47: =AF4/COUNT($AC4:$AG4) -> 0 | AG47: =AG4/COUNT($AC4:$AG4) -> 0 | AH47: =AH4 -> 0
A48: =A5 -> P3 | B48: =B5/COUNT($B5:$D5) -> 0.33333333 | C48: =C5/COUNT($B5:$D5) -> 0 | D48: =D5/COUNT($B5:$D5) -> 0 | E48: =E5/COUNT($E5:$H5) -> 0 | F48: =F5/COUNT($E5:$H5) -> 0 | G48: =G5/COUNT($E5:$H5) -> 0.25 | H48: =H5/COUNT($E5:$H5) -> 0 | I48: =I5/COUNT($I5:$K5) -> 0 | J48: =J5/COUNT($I5:$K5) -> 1 | K48: =K5/COUNT($I5:$K5) -> 0.33333333 | L48: =L5/COUNT($L5:$M5) -> 0.5 | M48: =M5/COUNT($L5:$M5) -> 0 | N48: =N5/COUNT($N5:$R5) -> 0.4 | O48: =O5/COUNT($N5:$R5) -> 0.4 | P48: =P5/COUNT($N5:$R5) -> 0.2 | Q48: =Q5/COUNT($N5:$R5) -> 0.4 | R48: =R5/COUNT($N5:$R5) -> 0.2 | S48: =S5/COUNT($S5:$U5) -> 0.33333333 | T48: =T5/COUNT($S5:$U5) -> 0.33333333 | U48: =U5/COUNT($S5:$U5) -> 0.33333333 | V48: =V5/COUNT($V5:$Z5) -> 0.2 | W48: =W5/COUNT($V5:$Z5) -> 0.4 | X48: =X5/COUNT($V5:$Z5) -> 0 | Y48: =Y5/COUNT($V5:$Z5) -> 0.2 | Z48: =Z5/COUNT($V5:$Z5) -> 0 | AA48: =AA5/COUNT($AA5:$AB5) -> 0.5 | AB48: =AB5/COUNT($AA5:$AB5) -> 0 | AC48: =AC5/COUNT($AC5:$AG5) -> 0.4 | AD48: =AD5/COUNT($AC5:$AG5) -> 0 | AE48: =AE5/COUNT($AC5:$AG5) -> 0.2 | AF48: =AF5/COUNT($AC5:$AG5) -> 0 | AG48: =AG5/COUNT($AC5:$AG5) -> 0 | AH48: =AH5 -> 0
A49: =A6 -> P4 | B49: =B6/COUNT($B6:$D6) -> 0 | C49: =C6/COUNT($B6:$D6) -> 0 | D49: =D6/COUNT($B6:$D6) -> 0.33333333 | E49: =E6/COUNT($E6:$H6) -> 0 | F49: =F6/COUNT($E6:$H6) -> 0 | G49: =G6/COUNT($E6:$H6) -> 0 | H49: =H6/COUNT($E6:$H6) -> 0.25 | I49: =I6/COUNT($I6:$K6) -> 0 | J49: =J6/COUNT($I6:$K6) -> 0.33333333 | K49: =K6/COUNT($I6:$K6) -> 0 | L49: =L6/COUNT($L6:$M6) -> 0.5 | M49: =M6/COUNT($L6:$M6) -> 0 | N49: =N6/COUNT($N6:$R6) -> 0 | O49: =O6/COUNT($N6:$R6) -> 0.2 | P49: =P6/COUNT($N6:$R6) -> 0 | Q49: =Q6/COUNT($N6:$R6) -> 0.2 | R49: =R6/COUNT($N6:$R6) -> 0.4 | S49: =S6/COUNT($S6:$U6) -> 0.66666667 | T49: =T6/COUNT($S6:$U6) -> 0.33333333 | U49: =U6/COUNT($S6:$U6) -> 0.33333333 | V49: =V6/COUNT($V6:$Z6) -> 0.2 | W49: =W6/COUNT($V6:$Z6) -> 0 | X49: =X6/COUNT($V6:$Z6) -> 0 | Y49: =Y6/COUNT($V6:$Z6) -> 0 | Z49: =Z6/COUNT($V6:$Z6) -> 0 | AA49: =AA6/COUNT($AA6:$AB6) -> 0 | AB49: =AB6/COUNT($AA6:$AB6) -> 0 | AC49: =AC6/COUNT($AC6:$AG6) -> 0.2 | AD49: =AD6/COUNT($AC6:$AG6) -> 0 | AE49: =AE6/COUNT($AC6:$AG6) -> 0.2 | AF49: =AF6/COUNT($AC6:$AG6) -> 0.2 | AG49: =AG6/COUNT($AC6:$AG6) -> 0 | AH49: =AH6 -> 0
A50: =A7 -> P5 | B50: =B7/COUNT($B7:$D7) -> 0 | C50: =C7/COUNT($B7:$D7) -> 0.33333333 | D50: =D7/COUNT($B7:$D7) -> 0 | E50: =E7/COUNT($E7:$H7) -> 0.25 | F50: =F7/COUNT($E7:$H7) -> 0 | G50: =G7/COUNT($E7:$H7) -> 0 | H50: =H7/COUNT($E7:$H7) -> 0 | I50: =I7/COUNT($I7:$K7) -> 0 | J50: =J7/COUNT($I7:$K7) -> 0.33333333 | K50: =K7/COUNT($I7:$K7) -> 0 | L50: =L7/COUNT($L7:$M7) -> 0.5 | M50: =M7/COUNT($L7:$M7) -> 0 | N50: =N7/COUNT($N7:$R7) -> 0 | O50: =O7/COUNT($N7:$R7) -> 0.2 | P50: =P7/COUNT($N7:$R7) -> 0 | Q50: =Q7/COUNT($N7:$R7) -> 0.2 | R50: =R7/COUNT($N7:$R7) -> 0.4 | S50: =S7/COUNT($S7:$U7) -> 0.66666667 | T50: =T7/COUNT($S7:$U7) -> 0.66666667 | U50: =U7/COUNT($S7:$U7) -> 0 | V50: =V7/COUNT($V7:$Z7) -> 0.2 | W50: =W7/COUNT($V7:$Z7) -> 0 | X50: =X7/COUNT($V7:$Z7) -> 0 | Y50: =Y7/COUNT($V7:$Z7) -> 0 | Z50: =Z7/COUNT($V7:$Z7) -> 0 | AA50: =AA7/COUNT($AA7:$AB7) -> 0 | AB50: =AB7/COUNT($AA7:$AB7) -> 0 | AC50: =AC7/COUNT($AC7:$AG7) -> 0 | AD50: =AD7/COUNT($AC7:$AG7) -> 0 | AE50: =AE7/COUNT($AC7:$AG7) -> 0 | AF50: =AF7/COUNT($AC7:$AG7) -> 0 | AG50: =AG7/COUNT($AC7:$AG7) -> 0 | AH50: =AH7 -> 0
A51: =A8 -> P6 | B51: =B8/COUNT($B8:$D8) -> 0.33333333 | C51: =C8/COUNT($B8:$D8) -> 0 | D51: =D8/COUNT($B8:$D8) -> 0 | E51: =E8/COUNT($E8:$H8) -> 0 | F51: =F8/COUNT($E8:$H8) -> 0 | G51: =G8/COUNT($E8:$H8) -> 0 | H51: =H8/COUNT($E8:$H8) -> 0.25 | I51: =I8/COUNT($I8:$K8) -> 0 | J51: =J8/COUNT($I8:$K8) -> 0 | K51: =K8/COUNT($I8:$K8) -> 0 | L51: =L8/COUNT($L8:$M8) -> 0.5 | M51: =M8/COUNT($L8:$M8) -> 0 | N51: =N8/COUNT($N8:$R8) -> 0 | O51: =O8/COUNT($N8:$R8) -> 0 | P51: =P8/COUNT($N8:$R8) -> 0 | Q51: =Q8/COUNT($N8:$R8) -> 0 | R51: =R8/COUNT($N8:$R8) -> 0 | S51: =S8/COUNT($S8:$U8) -> 0.66666667 | T51: =T8/COUNT($S8:$U8) -> 0 | U51: =U8/COUNT($S8:$U8) -> 0 | V51: =V8/COUNT($V8:$Z8) -> 0.2 | W51: =W8/COUNT($V8:$Z8) -> 0 | X51: =X8/COUNT($V8:$Z8) -> 0.2 | Y51: =Y8/COUNT($V8:$Z8) -> 0.2 | Z51: =Z8/COUNT($V8:$Z8) -> 0.2 | AA51: =AA8/COUNT($AA8:$AB8) -> 0 | AB51: =AB8/COUNT($AA8:$AB8) -> 0.5 | AC51: =AC8/COUNT($AC8:$AG8) -> 0.2 | AD51: =AD8/COUNT($AC8:$AG8) -> 0 | AE51: =AE8/COUNT($AC8:$AG8) -> 0.2 | AF51: =AF8/COUNT($AC8:$AG8) -> 0 | AG51: =AG8/COUNT($AC8:$AG8) -> 0 | AH51: =AH8 -> 0
A52: =A9 -> P7 | B52: =B9/COUNT($B9:$D9) -> 0 | C52: =C9/COUNT($B9:$D9) -> 0 | D52: =D9/COUNT($B9:$D9) -> 0.33333333 | E52: =E9/COUNT($E9:$H9) -> 0 | F52: =F9/COUNT($E9:$H9) -> 0.25 | G52: =G9/COUNT($E9:$H9) -> 0 | H52: =H9/COUNT($E9:$H9) -> 0 | I52: =I9/COUNT($I9:$K9) -> 0 | J52: =J9/COUNT($I9:$K9) -> 0 | K52: =K9/COUNT($I9:$K9) -> 0 | L52: =L9/COUNT($L9:$M9) -> 0.5 | M52: =M9/COUNT($L9:$M9) -> 0 | N52: =N9/COUNT($N9:$R9) -> 0 | O52: =O9/COUNT($N9:$R9) -> 0.4 | P52: =P9/COUNT($N9:$R9) -> 0.4 | Q52: =Q9/COUNT($N9:$R9) -> 0.4 | R52: =R9/COUNT($N9:$R9) -> 0.4 | S52: =S9/COUNT($S9:$U9) -> 0.66666667 | T52: =T9/COUNT($S9:$U9) -> 0.66666667 | U52: =U9/COUNT($S9:$U9) -> 0 | V52: =V9/COUNT($V9:$Z9) -> 0 | W52: =W9/COUNT($V9:$Z9) -> 0 | X52: =X9/COUNT($V9:$Z9) -> 0 | Y52: =Y9/COUNT($V9:$Z9) -> 0 | Z52: =Z9/COUNT($V9:$Z9) -> 0 | AA52: =AA9/COUNT($AA9:$AB9) -> 0 | AB52: =AB9/COUNT($AA9:$AB9) -> 0 | AC52: =AC9/COUNT($AC9:$AG9) -> 0 | AD52: =AD9/COUNT($AC9:$AG9) -> 0 | AE52: =AE9/COUNT($AC9:$AG9) -> 0 | AF52: =AF9/COUNT($AC9:$AG9) -> 0 | AG52: =AG9/COUNT($AC9:$AG9) -> 0 | AH52: =AH9 -> 0
A53: =A10 -> P8 | B53: =B10/COUNT($B10:$D10) -> 0 | C53: =C10/COUNT($B10:$D10) -> 0.33333333 | D53: =D10/COUNT($B10:$D10) -> 0 | E53: =E10/COUNT($E10:$H10) -> 0 | F53: =F10/COUNT($E10:$H10) -> 0.25 | G53: =G10/COUNT($E10:$H10) -> 0 | H53: =H10/COUNT($E10:$H10) -> 0 | I53: =I10/COUNT($I10:$K10) -> 0 | J53: =J10/COUNT($I10:$K10) -> 0.33333333 | K53: =K10/COUNT($I10:$K10) -> 1 | L53: =L10/COUNT($L10:$M10) -> 0.5 | M53: =M10/COUNT($L10:$M10) -> 0 | N53: =N10/COUNT($N10:$R10) -> 0 | O53: =O10/COUNT($N10:$R10) -> 0.4 | P53: =P10/COUNT($N10:$R10) -> 0.2 | Q53: =Q10/COUNT($N10:$R10) -> 0.2 | R53: =R10/COUNT($N10:$R10) -> 0.2 | S53: =S10/COUNT($S10:$U10) -> 1.3333333 | T53: =T10/COUNT($S10:$U10) -> 1 | U53: =U10/COUNT($S10:$U10) -> 0 | V53: =V10/COUNT($V10:$Z10) -> 0.6 | W53: =W10/COUNT($V10:$Z10) -> 0.2 | X53: =X10/COUNT($V10:$Z10) -> 0.2 | Y53: =Y10/COUNT($V10:$Z10) -> 0.2 | Z53: =Z10/COUNT($V10:$Z10) -> 0.2 | AA53: =AA10/COUNT($AA10:$AB10) -> 0.5 | AB53: =AB10/COUNT($AA10:$AB10) -> 0 | AC53: =AC10/COUNT($AC10:$AG10) -> 0 | AD53: =AD10/COUNT($AC10:$AG10) -> 0.2 | AE53: =AE10/COUNT($AC10:$AG10) -> 0.2 | AF53: =AF10/COUNT($AC10:$AG10) -> 0 | AG53: =AG10/COUNT($AC10:$AG10) -> 0 | AH53: =AH10 -> 1
A54: =A11 -> P9 | B54: =B11/COUNT($B11:$D11) -> 0 | C54: =C11/COUNT($B11:$D11) -> 0.33333333 | D54: =D11/COUNT($B11:$D11) -> 0 | E54: =E11/COUNT($E11:$H11) -> 0 | F54: =F11/COUNT($E11:$H11) -> 0.25 | G54: =G11/COUNT($E11:$H11) -> 0 | H54: =H11/COUNT($E11:$H11) -> 0 | I54: =I11/COUNT($I11:$K11) -> 0 | J54: =J11/COUNT($I11:$K11) -> 0.33333333 | K54: =K11/COUNT($I11:$K11) -> 0.66666667 | L54: =L11/COUNT($L11:$M11) -> 0.5 | M54: =M11/COUNT($L11:$M11) -> 0 | N54: =N11/COUNT($N11:$R11) -> 0.2 | O54: =O11/COUNT($N11:$R11) -> 0.4 | P54: =P11/COUNT($N11:$R11) -> 0.4 | Q54: =Q11/COUNT($N11:$R11) -> 0.4 | R54: =R11/COUNT($N11:$R11) -> 0.4 | S54: =S11/COUNT($S11:$U11) -> 0.33333333 | T54: =T11/COUNT($S11:$U11) -> 0 | U54: =U11/COUNT($S11:$U11) -> 0 | V54: =V11/COUNT($V11:$Z11) -> 0.2 | W54: =W11/COUNT($V11:$Z11) -> 0.2 | X54: =X11/COUNT($V11:$Z11) -> 0 | Y54: =Y11/COUNT($V11:$Z11) -> 0.2 | Z54: =Z11/COUNT($V11:$Z11) -> 0 | AA54: =AA11/COUNT($AA11:$AB11) -> 0.5 | AB54: =AB11/COUNT($AA11:$AB11) -> 0 | AC54: =AC11/COUNT($AC11:$AG11) -> 0 | AD54: =AD11/COUNT($AC11:$AG11) -> 0 | AE54: =AE11/COUNT($AC11:$AG11) -> 0 | AF54: =AF11/COUNT($AC11:$AG11) -> 0 | AG54: =AG11/COUNT($AC11:$AG11) -> 0 | AH54: =AH11 -> 1
A55: =A12 -> P10 | B55: =B12/COUNT($B12:$D12) -> 0 | C55: =C12/COUNT($B12:$D12) -> 0.33333333 | D55: =D12/COUNT($B12:$D12) -> 0 | E55: =E12/COUNT($E12:$H12) -> 0 | F55: =F12/COUNT($E12:$H12) -> 0.25 | G55: =G12/COUNT($E12:$H12) -> 0 | H55: =H12/COUNT($E12:$H12) -> 0 | I55: =I12/COUNT($I12:$K12) -> 0 | J55: =J12/COUNT($I12:$K12) -> 0.33333333 | K55: =K12/COUNT($I12:$K12) -> 0 | L55: =L12/COUNT($L12:$M12) -> 1 | M55: =M12/COUNT($L12:$M12) -> 0 | N55: =N12/COUNT($N12:$R12) -> 0.2 | O55: =O12/COUNT($N12:$R12) -> 0.4 | P55: =P12/COUNT($N12:$R12) -> 0.4 | Q55: =Q12/COUNT($N12:$R12) -> 0.4 | R55: =R12/COUNT($N12:$R12) -> 0.2 | S55: =S12/COUNT($S12:$U12) -> 0.33333333 | T55: =T12/COUNT($S12:$U12) -> 0.33333333 | U55: =U12/COUNT($S12:$U12) -> 0 | V55: =V12/COUNT($V12:$Z12) -> 0 | W55: =W12/COUNT($V12:$Z12) -> 0.2 | X55: =X12/COUNT($V12:$Z12) -> 0 | Y55: =Y12/COUNT($V12:$Z12) -> 0 | Z55: =Z12/COUNT($V12:$Z12) -> 0 | AA55: =AA12/COUNT($AA12:$AB12) -> 0 | AB55: =AB12/COUNT($AA12:$AB12) -> 0 | AC55: =AC12/COUNT($AC12:$AG12) -> 0.2 | AD55: =AD12/COUNT($AC12:$AG12) -> 0 | AE55: =AE12/COUNT($AC12:$AG12) -> 0 | AF55: =AF12/COUNT($AC12:$AG12) -> 0 | AG55: =AG12/COUNT($AC12:$AG12) -> 0 | AH55: =AH12 -> 2
A56: =A13 -> P11 | B56: =B13/COUNT($B13:$D13) -> 0 | C56: =C13/COUNT($B13:$D13) -> 0.33333333 | D56: =D13/COUNT($B13:$D13) -> 0 | E56: =E13/COUNT($E13:$H13) -> 0 | F56: =F13/COUNT($E13:$H13) -> 0 | G56: =G13/COUNT($E13:$H13) -> 0 | H56: =H13/COUNT($E13:$H13) -> 0.25 | I56: =I13/COUNT($I13:$K13) -> 0 | J56: =J13/COUNT($I13:$K13) -> 0 | K56: =K13/COUNT($I13:$K13) -> 0 | L56: =L13/COUNT($L13:$M13) -> 0 | M56: =M13/COUNT($L13:$M13) -> 0.5 | N56: =N13/COUNT($N13:$R13) -> 0 | O56: =O13/COUNT($N13:$R13) -> 0.2 | P56: =P13/COUNT($N13:$R13) -> 0.2 | Q56: =Q13/COUNT($N13:$R13) -> 0.2 | R56: =R13/COUNT($N13:$R13) -> 0 | S56: =S13/COUNT($S13:$U13) -> 0.33333333 | T56: =T13/COUNT($S13:$U13) -> 0.66666667 | U56: =U13/COUNT($S13:$U13) -> 0 | V56: =V13/COUNT($V13:$Z13) -> 0.2 | W56: =W13/COUNT($V13:$Z13) -> 0.2 | X56: =X13/COUNT($V13:$Z13) -> 0 | Y56: =Y13/COUNT($V13:$Z13) -> 0 | Z56: =Z13/COUNT($V13:$Z13) -> 0 | AA56: =AA13/COUNT($AA13:$AB13) -> 0 | AB56: =AB13/COUNT($AA13:$AB13) -> 0 | AC56: =AC13/COUNT($AC13:$AG13) -> 0 | AD56: =AD13/COUNT($AC13:$AG13) -> 0 | AE56: =AE13/COUNT($AC13:$AG13) -> 0 | AF56: =AF13/COUNT($AC13:$AG13) -> 0 | AG56: =AG13/COUNT($AC13:$AG13) -> 0 | AH56: =AH13 -> 0
A57: =A14 -> P12 | B57: =B14/COUNT($B14:$D14) -> 0 | C57: =C14/COUNT($B14:$D14) -> 0 | D57: =D14/COUNT($B14:$D14) -> 0 | E57: =E14/COUNT($E14:$H14) -> 0 | F57: =F14/COUNT($E14:$H14) -> 0 | G57: =G14/COUNT($E14:$H14) -> 0 | H57: =H14/COUNT($E14:$H14) -> 0 | I57: =I14/COUNT($I14:$K14) -> 0 | J57: =J14/COUNT($I14:$K14) -> 0.33333333 | K57: =K14/COUNT($I14:$K14) -> 0 | L57: =L14/COUNT($L14:$M14) -> 0 | M57: =M14/COUNT($L14:$M14) -> 0 | N57: =N14/COUNT($N14:$R14) -> 0.2 | O57: =O14/COUNT($N14:$R14) -> 0.2 | P57: =P14/COUNT($N14:$R14) -> 0.2 | Q57: =Q14/COUNT($N14:$R14) -> 0.2 | R57: =R14/COUNT($N14:$R14) -> 0.2 | S57: =S14/COUNT($S14:$U14) -> 0.66666667 | T57: =T14/COUNT($S14:$U14) -> 0.33333333 | U57: =U14/COUNT($S14:$U14) -> 0 | V57: =V14/COUNT($V14:$Z14) -> 0.2 | W57: =W14/COUNT($V14:$Z14) -> 0.2 | X57: =X14/COUNT($V14:$Z14) -> 0 | Y57: =Y14/COUNT($V14:$Z14) -> 0 | Z57: =Z14/COUNT($V14:$Z14) -> 0 | AA57: =AA14/COUNT($AA14:$AB14) -> 0 | AB57: =AB14/COUNT($AA14:$AB14) -> 0 | AC57: =AC14/COUNT($AC14:$AG14) -> 0 | AD57: =AD14/COUNT($AC14:$AG14) -> 0 | AE57: =AE14/COUNT($AC14:$AG14) -> 0 | AF57: =AF14/COUNT($AC14:$AG14) -> 0 | AG57: =AG14/COUNT($AC14:$AG14) -> 0 | AH57: =AH14 -> 0
... A86: =A43 -> P41 | B86: =B43/COUNT($B43:$D43) -> 0.33333333 | C86: =C43/COUNT($B43:$D43) -> 0 | D86: =D43/COUNT($B43:$D43) -> 0 | E86: =E43/COUNT($E43:$H43) -> 0 | F86: =F43/COUNT($E43:$H43) -> 0 | G86: =G43/COUNT($E43:$H43) -> 0 | H86: =H43/COUNT($E43:$H43) -> 0.25 | I86: =I43/COUNT($I43:$K43) -> 0 | J86: =J43/COUNT($I43:$K43) -> 0 | K86: =K43/COUNT($I43:$K43) -> 0.33333333 | L86: =L43/COUNT($L43:$M43) -> 0.5 | M86: =M43/COUNT($L43:$M43) -> 0 | N86: =N43/COUNT($N43:$R43) -> 0 | O86: =O43/COUNT($N43:$R43) -> 0 | P86: =P43/COUNT($N43:$R43) -> 0 | Q86: =Q43/COUNT($N43:$R43) -> 0.2 | R86: =R43/COUNT($N43:$R43) -> 0 | S86: =S43/COUNT($S43:$U43) -> 1 | T86: =T43/COUNT($S43:$U43) -> 0 | U86: =U43/COUNT($S43:$U43) -> 0.33333333 | V86: =V43/COUNT($V43:$Z43) -> 0.2 | W86: =W43/COUNT($V43:$Z43) -> 0 | X86: =X43/COUNT($V43:$Z43) -> 0.2 | Y86: =Y43/COUNT($V43:$Z43) -> 0 | Z86: =Z43/COUNT($V43:$Z43) -> 0.2 | AA86: =AA43/COUNT($AA43:$AB43) -> 0 | AB86: =AB43/COUNT($AA43:$AB43) -> 0.5 | AC86: =AC43/COUNT($AC43:$AG43) -> 0.2 | AD86: =AD43/COUNT($AC43:$AG43) -> 0 | AE86: =AE43/COUNT($AC43:$AG43) -> 0.2 | AF86: =AF43/COUNT($AC43:$AG43) -> 0 | AG86: =AG43/COUNT($AC43:$AG43) -> 0 | AH86: =AH43 -> 0
B88: =B45 -> X1 | C88: =C45 -> 0 | D88: =D45 -> 0 | E88: =E45 -> X2 | F88: =F45 -> 0 | G88: =G45 -> 0 | H88: =H45 -> 0 | I88: =I45 -> X3 | ... AH88: =AH45 -> X10 | AI88: PMC-I
A89: =A46 -> P1 | B89: =SUM(B46:D46) -> 0.33333333 | E89: =SUM(E46:H46) -> 0 | I89: =SUM(I46:K46) -> 0.33333333 | L89: =SUM(L46:M46) -> 0.5 | N89: =SUM(N46:R46) -> 0.8 | S89: =SUM(S46:U46) -> 0.66666667 | V89: =SUM(V46:Z46) -> 0 | AA89: =SUM(AA46:AB46) -> 0 | AC89: =SUM(AC46:AG46) -> 0.4 | AH89: =AH46 -> 0 | AI89: =SUM(B89:AH89) -> 3.0333333
A90: =A47 -> P2 | B90: =SUM(B47:D47) -> 0.33333333 | E90: =SUM(E47:H47) -> 0.25 | I90: =SUM(I47:K47) -> 0 | L90: =SUM(L47:M47) -> 0.5 | N90: =SUM(N47:R47) -> 1 | S90: =SUM(S47:U47) -> 0.33333333 | V90: =SUM(V47:Z47) -> 0.8 | AA90: =SUM(AA47:AB47) -> 0 | AC90: =SUM(AC47:AG47) -> 0.2 | AH90: =AH47 -> 0 | AI90: =SUM(B90:AH90) -> 3.4166667
A91: =A48 -> P3 | B91: =SUM(B48:D48) -> 0.33333333 | E91: =SUM(E48:H48) -> 0.25 | I91: =SUM(I48:K48) -> 1.3333333 | L91: =SUM(L48:M48) -> 0.5 | N91: =SUM(N48:R48) -> 1.6 | S91: =SUM(S48:U48) -> 1 | V91: =SUM(V48:Z48) -> 0.8 | AA91: =SUM(AA48:AB48) -> 0.5 | AC91: =SUM(AC48:AG48) -> 0.6 | AH91: =AH48 -> 0 | AI91: =SUM(B91:AH91) -> 6.9166667
A92: =A49 -> P4 | B92: =SUM(B49:D49) -> 0.33333333 | E92: =SUM(E49:H49) -> 0.25 | I92: =SUM(I49:K49) -> 0.33333333 | L92: =SUM(L49:M49) -> 0.5 | N92: =SUM(N49:R49) -> 0.8 | S92: =SUM(S49:U49) -> 1.3333333 | V92: =SUM(V49:Z49) -> 0.2 | AA92: =SUM(AA49:AB49) -> 0 | AC92: =SUM(AC49:AG49) -> 0.6 | AH92: =AH49 -> 0 | AI92: =SUM(B92:AH92) -> 4.35
A93: =A50 -> P5 | B93: =SUM(B50:D50) -> 0.33333333 | E93: =SUM(E50:H50) -> 0.25 | I93: =SUM(I50:K50) -> 0.33333333 | L93: =SUM(L50:M50) -> 0.5 | N93: =SUM(N50:R50) -> 0.8 | S93: =SUM(S50:U50) -> 1.3333333 | V93: =SUM(V50:Z50) -> 0.2 | AA93: =SUM(AA50:AB50) -> 0 | AC93: =SUM(AC50:AG50) -> 0 | AH93: =AH50 -> 0 | AI93: =SUM(B93:AH93) -> 3.75
A94: =A51 -> P6 | B94: =SUM(B51:D51) -> 0.33333333 | E94: =SUM(E51:H51) -> 0.25 | I94: =SUM(I51:K51) -> 0 | L94: =SUM(L51:M51) -> 0.5 | N94: =SUM(N51:R51) -> 0 | S94: =SUM(S51:U51) -> 0.66666667 | V94: =SUM(V51:Z51) -> 0.8 | AA94: =SUM(AA51:AB51) -> 0.5 | AC94: =SUM(AC51:AG51) -> 0.4 | AH94: =AH51 -> 0 | AI94: =SUM(B94:AH94) -> 3.45
A95: =A52 -> P7 | B95: =SUM(B52:D52) -> 0.33333333 | E95: =SUM(E52:H52) -> 0.25 | I95: =SUM(I52:K52) -> 0 | L95: =SUM(L52:M52) -> 0.5 | N95: =SUM(N52:R52) -> 1.6 | S95: =SUM(S52:U52) -> 1.3333333 | V95: =SUM(V52:Z52) -> 0 | AA95: =SUM(AA52:AB52) -> 0 | AC95: =SUM(AC52:AG52) -> 0 | AH95: =AH52 -> 0 | AI95: =SUM(B95:AH95) -> 4.0166667
A96: =A53 -> P8 | B96: =SUM(B53:D53) -> 0.33333333 | E96: =SUM(E53:H53) -> 0.25 | I96: =SUM(I53:K53) -> 1.3333333 | L96: =SUM(L53:M53) -> 0.5 | N96: =SUM(N53:R53) -> 1 | S96: =SUM(S53:U53) -> 2.3333333 | V96: =SUM(V53:Z53) -> 1.4 | AA96: =SUM(AA53:AB53) -> 0.5 | AC96: =SUM(AC53:AG53) -> 0.4 | AH96: =AH53 -> 1 | AI96: =SUM(B96:AH96) -> 9.05
A97: =A54 -> P9 | B97: =SUM(B54:D54) -> 0.33333333 | E97: =SUM(E54:H54) -> 0.25 | I97: =SUM(I54:K54) -> 1 | L97: =SUM(L54:M54) -> 0.5 | N97: =SUM(N54:R54) -> 1.8 | S97: =SUM(S54:U54) -> 0.33333333 | V97: =SUM(V54:Z54) -> 0.6 | AA97: =SUM(AA54:AB54) -> 0.5 | AC97: =SUM(AC54:AG54) -> 0 | AH97: =AH54 -> 1 | AI97: =SUM(B97:AH97) -> 6.3166667
A98: =A55 -> P10 | B98: =SUM(B55:D55) -> 0.33333333 | E98: =SUM(E55:H55) -> 0.25 | I98: =SUM(I55:K55) -> 0.33333333 | L98: =SUM(L55:M55) -> 1 | N98: =SUM(N55:R55) -> 1.6 | S98: =SUM(S55:U55) -> 0.66666667 | V98: =SUM(V55:Z55) -> 0.2 | AA98: =SUM(AA55:AB55) -> 0 | AC98: =SUM(AC55:AG55) -> 0.2 | AH98: =AH55 -> 2 | AI98: =SUM(B98:AH98) -> 6.5833333
A99: =A56 -> P11 | B99: =SUM(B56:D56) -> 0.33333333 | E99: =SUM(E56:H56) -> 0.25 | I99: =SUM(I56:K56) -> 0 | L99: =SUM(L56:M56) -> 0.5 | N99: =SUM(N56:R56) -> 0.6 | S99: =SUM(S56:U56) -> 1 | V99: =SUM(V56:Z56) -> 0.4 | AA99: =SUM(AA56:AB56) -> 0 | AC99: =SUM(AC56:AG56) -> 0 | AH99: =AH56 -> 0 | AI99: =SUM(B99:AH99) -> 3.0833333
A100: =A57 -> P12 | B100: =SUM(B57:D57) -> 0 | E100: =SUM(E57:H57) -> 0 | I100: =SUM(I57:K57) -> 0.33333333 | L100: =SUM(L57:M57) -> 0 | N100: =SUM(N57:R57) -> 1 | S100: =SUM(S57:U57) -> 1 | V100: =SUM(V57:Z57) -> 0.4 | AA100: =SUM(AA57:AB57) -> 0 | AC100: =SUM(AC57:AG57) -> 0 | AH100: =AH57 -> 0 | AI100: =SUM(B100:AH100) -> 2.7333333
... A129: =A86 -> P41 | B129: =SUM(B86:D86) -> 0.33333333 | E129: =SUM(E86:H86) -> 0.25 | I129: =SUM(I86:K86) -> 0.33333333 | L129: =SUM(L86:M86) -> 0.5 | N129: =SUM(N86:R86) -> 0.2 | S129: =SUM(S86:U86) -> 1.3333333 | V129: =SUM(V86:Z86) -> 0.6 | AA129: =SUM(AA86:AB86) -> 0.5 | AC129: =SUM(AC86:AG86) -> 0.4 | AH129: =AH86 -> 0 | AI129: =SUM(B129:AH129) -> 4.45
A130: Mean | B130: =AVERAGE(B89:B129) -> 0.33333333 | E130: =AVERAGE(E89:E129) -> 0.25 | I130: =AVERAGE(I89:I129) -> 0.4796748 | L130: =AVERAGE(L89:L129) -> 0.47560976 | N130: =AVERAGE(N89:N129) -> 0.86341463 | S130: =AVERAGE(S89:S129) -> 0.93495935 | V130: =AVERAGE(V89:V129) -> 0.55609756 | AA130: =AVERAGE(AA89:AA129) -> 0.12195122 | AC130: =AVERAGE(AC89:AC129) -> 0.23414634 | AH130: =AVERAGE(AH89:AH129) -> 0.26829268 | AI130: =AVERAGE(AI89:AI129) -> 4.5174797
A136: 传统[0, 1]
B137: X1 | E137: X2 | I137: X3 | L137: X4 | N137: X5 | S137: X6 | V137: X7 | AA137: X8 | AC137: X9
B138: X1: 1 | C138: X1: 2 | D138: X1: 3 | E138: X2: 1 | F138: X2: 2 | G138: X2: 3 | H138: X2: 4 | I138: X3: 1 | J138: X3: 2 | K138: X3: 3 | L138: X4: 1 | M138: X4: 2 | N138: X5: 1 | O138: X5: 2 | P138: X5: 3 | Q138: X5: 4 | R138: X5: 5 | S138: X6: 1 | T138: X6: 2 | U138: X6: 3 | V138: X7: 1 | W138: X7: 2 | X138: X7: 3 | Y138: X7: 4 | Z138: X7: 5 | AA138: X8: 1 | AB138: X8: 2 | AC138: X9: 1 | AD138: X9: 2 | AE138: X9: 3 | AF138: X9: 4 | AG138: X9: 5 | AH138: X10
A139: P1 | B139: 0 | C139: 0 | D139: 1 | E139: 0 | F139: 0 | G139: 0 | H139: 0 | I139: 0 | J139: 0 | K139: 1 | L139: 1 | M139: 0 | N139: 1 | O139: 1 | P139: 1 | Q139: 0 | R139: 1 | S139: 1 | T139: 1 | U139: 0 | V139: 0 | W139: 0 | X139: 0 | Y139: 0 | Z139: 0 | AA139: 0 | AB139: 0 | AC139: 1 | AD139: 0 | AE139: 1 | AF139: 0 | AG139: 0 | AH139: 0
A140: P2 | B140: 0 | C140: 1 | D140: 0 | E140: 0 | F140: 0 | G140: 0 | H140: 1 | I140: 0 | J140: 0 | K140: 0 | L140: 1 | M140: 0 | N140: 1 | O140: 1 | P140: 1 | Q140: 1 | R140: 1 | S140: 1 | T140: 0 | U140: 0 | V140: 1 | W140: 1 | X140: 1 | Y140: 0 | Z140: 1 | AA140: 0 | AB140: 0 | AC140: 0 | AD140: 0 | AE140: 1 | AF140: 0 | AG140: 0 | AH140: 0
A141: P3 | B141: 1 | C141: 0 | D141: 0 | E141: 0 | F141: 0 | G141: 1 | H141: 0 | I141: 0 | J141: 1 | K141: 1 | L141: 1 | M141: 0 | N141: 1 | O141: 1 | P141: 1 | Q141: 1 | R141: 1 | S141: 1 | T141: 1 | U141: 1 | V141: 1 | W141: 1 | X141: 0 | Y141: 1 | Z141: 0 | AA141: 1 | AB141: 0 | AC141: 1 | AD141: 0 | AE141: 1 | AF141: 0 | AG141: 0 | AH141: 0
A142: P4 | B142: 0 | C142: 0 | D142: 1 | E142: 0 | F142: 0 | G142: 0 | H142: 1 | I142: 0 | J142: 1 | K142: 0 | L142: 1 | M142: 0 | N142: 0 | O142: 1 | P142: 0 | Q142: 1 | R142: 1 | S142: 1 | T142: 1 | U142: 1 | V142: 1 | W142: 0 | X142: 0 | Y142: 0 | Z142: 0 | AA142: 0 | AB142: 0 | AC142: 1 | AD142: 0 | AE142: 1 | AF142: 1 | AG142: 0 | AH142: 0
A143: P5 | B143: 0 | C143: 1 | D143: 0 | E143: 1 | F143: 0 | G143: 0 | H143: 0 | I143: 0 | J143: 1 | K143: 0 | L143: 1 | M143: 0 | N143: 0 | O143: 1 | P143: 0 | Q143: 1 | R143: 1 | S143: 1 | T143: 1 | U143: 0 | V143: 1 | W143: 0 | X143: 0 | Y143: 0 | Z143: 0 | AA143: 0 | AB143: 0 | AC143: 0 | AD143: 0 | AE143: 0 | AF143: 0 | AG143: 0 | AH143: 0
A144: P6 | B144: 1 | C144: 0 | D144: 0 | E144: 0 | F144: 0 | G144: 0 | H144: 1 | I144: 0 | J144: 0 | K144: 0 | L144: 1 | M144: 0 | N144: 0 | O144: 0 | P144: 0 | Q144: 0 | R144: 0 | S144: 1 | T144: 0 | U144: 0 | V144: 1 | W144: 0 | X144: 1 | Y144: 1 | Z144: 1 | AA144: 0 | AB144: 1 | AC144: 1 | AD144: 0 | AE144: 1 | AF144: 0 | AG144: 0 | AH144: 0
A145: P7 | B145: 0 | C145: 0 | D145: 1 | E145: 0 | F145: 1 | G145: 0 | H145: 0 | I145: 0 | J145: 0 | K145: 0 | L145: 1 | M145: 0 | N145: 0 | O145: 1 | P145: 1 | Q145: 1 | R145: 1 | S145: 1 | T145: 1 | U145: 0 | V145: 0 | W145: 0 | X145: 0 | Y145: 0 | Z145: 0 | AA145: 0 | AB145: 0 | AC145: 0 | AD145: 0 | AE145: 0 | AF145: 0 | AG145: 0 | AH145: 0
A146: P8 | B146: 0 | C146: 1 | D146: 0 | E146: 0 | F146: 1 | G146: 0 | H146: 0 | I146: 0 | J146: 1 | K146: 1 | L146: 1 | M146: 0 | N146: 0 | O146: 1 | P146: 1 | Q146: 1 | R146: 1 | S146: 1 | T146: 1 | U146: 0 | V146: 1 | W146: 1 | X146: 1 | Y146: 1 | Z146: 1 | AA146: 1 | AB146: 0 | AC146: 0 | AD146: 1 | AE146: 1 | AF146: 0 | AG146: 0 | AH146: 1
A147: P9 | B147: 0 | C147: 1 | D147: 0 | E147: 0 | F147: 1 | G147: 0 | H147: 0 | I147: 0 | J147: 1 | K147: 1 | L147: 1 | M147: 0 | N147: 1 | O147: 1 | P147: 1 | Q147: 1 | R147: 1 | S147: 1 | T147: 0 | U147: 0 | V147: 1 | W147: 1 | X147: 0 | Y147: 1 | Z147: 0 | AA147: 1 | AB147: 0 | AC147: 0 | AD147: 0 | AE147: 0 | AF147: 0 | AG147: 0 | AH147: 1
A148: P10 | B148: 0 | C148: 1 | D148: 0 | E148: 0 | F148: 1 | G148: 0 | H148: 0 | I148: 0 | J148: 1 | K148: 0 | L148: 1 | M148: 0 | N148: 1 | O148: 1 | P148: 1 | Q148: 1 | R148: 1 | S148: 1 | T148: 1 | U148: 0 | V148: 0 | W148: 1 | X148: 0 | Y148: 0 | Z148: 0 | AA148: 0 | AB148: 0 | AC148: 1 | AD148: 0 | AE148: 0 | AF148: 0 | AG148: 0 | AH148: 1
A149: P11 | B149: 0 | C149: 1 | D149: 0 | E149: 0 | F149: 0 | G149: 0 | H149: 1 | I149: 0 | J149: 0 | K149: 0 | L149: 0 | M149: 1 | N149: 0 | O149: 1 | P149: 1 | Q149: 1 | R149: 0 | S149: 1 | T149: 1 | U149: 0 | V149: 1 | W149: 1 | X149: 0 | Y149: 0 | Z149: 0 | AA149: 0 | AB149: 0 | AC149: 0 | AD149: 0 | AE149: 0 | AF149: 0 | AG149: 0 | AH149: 0
A150: P12 | B150: 0 | C150: 0 | D150: 0 | E150: 0 | F150: 0 | G150: 0 | H150: 0 | I150: 0 | J150: 1 | K150: 0 | L150: 0 | M150: 0 | N150: 1 | O150: 1 | P150: 1 | Q150: 1 | R150: 1 | S150: 1 | T150: 1 | U150: 0 | V150: 1 | W150: 1 | X150: 0 | Y150: 0 | Z150: 0 | AA150: 0 | AB150: 0 | AC150: 0 | AD150: 0 | AE150: 0 | AF150: 0 | AG150: 0 | AH150: 0
... A179: P41 | B179: 1 | C179: 0 | D179: 0 | E179: 0 | F179: 0 | G179: 0 | H179: 1 | I179: 0 | J179: 0 | K179: 1 | L179: 1 | M179: 0 | N179: 0 | O179: 0 | P179: 0 | Q179: 1 | R179: 0 | S179: 1 | T179: 0 | U179: 1 | V179: 1 | W179: 0 | X179: 1 | Y179: 0 | Z179: 1 | AA179: 0 | AB179: 1 | AC179: 1 | AD179: 0 | AE179: 1 | AF179: 0 | AG179: 0 | AH179: 0
B181: =B137 -> X1 | C181: =C137 -> 0 | D181: =D137 -> 0 | E181: =E137 -> X2 | F181: =F137 -> 0 | G181: =G137 -> 0 | H181: =H137 -> 0 | I181: =I137 -> X3 | ... AG181: =AG137 -> 0 | AH181: =AH138 -> X10
A182: =A139 -> P1 | B182: =B139/COUNT($B139:$D139) -> 0 | C182: =C139/COUNT($B139:$D139) -> 0 | D182: =D139/COUNT($B139:$D139) -> 0.33333333 | E182: =E139/COUNT($E139:$H139) -> 0 | F182: =F139/COUNT($E139:$H139) -> 0 | G182: =G139/COUNT($E139:$H139) -> 0 | H182: =H139/COUNT($E139:$H139) -> 0 | I182: =I139/COUNT($I139:$K139) -> 0 | J182: =J139/COUNT($I139:$K139) -> 0 | K182: =K139/COUNT($I139:$K139) -> 0.33333333 | L182: =L139/COUNT($L139:$M139) -> 0.5 | M182: =M139/COUNT($L139:$M139) -> 0 | N182: =N139/COUNT($N139:$R139) -> 0.2 | O182: =O139/COUNT($N139:$R139) -> 0.2 | P182: =P139/COUNT($N139:$R139) -> 0.2 | Q182: =Q139/COUNT($N139:$R139) -> 0 | R182: =R139/COUNT($N139:$R139) -> 0.2 | S182: =S139/COUNT($S139:$U139) -> 0.33333333 | T182: =T139/COUNT($S139:$U139) -> 0.33333333 | U182: =U139/COUNT($S139:$U139) -> 0 | V182: =V139/COUNT($V139:$Z139) -> 0 | W182: =W139/COUNT($V139:$Z139) -> 0 | X182: =X139/COUNT($V139:$Z139) -> 0 | Y182: =Y139/COUNT($V139:$Z139) -> 0 | Z182: =Z139/COUNT($V139:$Z139) -> 0 | AA182: =AA139/COUNT($AA139:$AB139) -> 0 | AB182: =AB139/COUNT($AA139:$AB139) -> 0 | AC182: =AC139/COUNT($AC139:$AG139) -> 0.2 | AD182: =AD139/COUNT($AC139:$AG139) -> 0 | AE182: =AE139/COUNT($AC139:$AG139) -> 0.2 | AF182: =AF139/COUNT($AC139:$AG139) -> 0 | AG182: =AG139/COUNT($AC139:$AG139) -> 0 | AH182: =AH139 -> 0
A183: =A140 -> P2 | B183: =B140/COUNT($B140:$D140) -> 0 | C183: =C140/COUNT($B140:$D140) -> 0.33333333 | D183: =D140/COUNT($B140:$D140) -> 0 | E183: =E140/COUNT($E140:$H140) -> 0 | F183: =F140/COUNT($E140:$H140) -> 0 | G183: =G140/COUNT($E140:$H140) -> 0 | H183: =H140/COUNT($E140:$H140) -> 0.25 | I183: =I140/COUNT($I140:$K140) -> 0 | J183: =J140/COUNT($I140:$K140) -> 0 | K183: =K140/COUNT($I140:$K140) -> 0 | L183: =L140/COUNT($L140:$M140) -> 0.5 | M183: =M140/COUNT($L140:$M140) -> 0 | N183: =N140/COUNT($N140:$R140) -> 0.2 | O183: =O140/COUNT($N140:$R140) -> 0.2 | P183: =P140/COUNT($N140:$R140) -> 0.2 | Q183: =Q140/COUNT($N140:$R140) -> 0.2 | R183: =R140/COUNT($N140:$R140) -> 0.2 | S183: =S140/COUNT($S140:$U140) -> 0.33333333 | T183: =T140/COUNT($S140:$U140) -> 0 | U183: =U140/COUNT($S140:$U140) -> 0 | V183: =V140/COUNT($V140:$Z140) -> 0.2 | W183: =W140/COUNT($V140:$Z140) -> 0.2 | X183: =X140/COUNT($V140:$Z140) -> 0.2 | Y183: =Y140/COUNT($V140:$Z140) -> 0 | Z183: =Z140/COUNT($V140:$Z140) -> 0.2 | AA183: =AA140/COUNT($AA140:$AB140) -> 0 | AB183: =AB140/COUNT($AA140:$AB140) -> 0 | AC183: =AC140/COUNT($AC140:$AG140) -> 0 | AD183: =AD140/COUNT($AC140:$AG140) -> 0 | AE183: =AE140/COUNT($AC140:$AG140) -> 0.2 | AF183: =AF140/COUNT($AC140:$AG140) -> 0 | AG183: =AG140/COUNT($AC140:$AG140) -> 0 | AH183: =AH140 -> 0
A184: =A141 -> P3 | B184: =B141/COUNT($B141:$D141) -> 0.33333333 | C184: =C141/COUNT($B141:$D141) -> 0 | D184: =D141/COUNT($B141:$D141) -> 0 | E184: =E141/COUNT($E141:$H141) -> 0 | F184: =F141/COUNT($E141:$H141) -> 0 | G184: =G141/COUNT($E141:$H141) -> 0.25 | H184: =H141/COUNT($E141:$H141) -> 0 | I184: =I141/COUNT($I141:$K141) -> 0 | J184: =J141/COUNT($I141:$K141) -> 0.33333333 | K184: =K141/COUNT($I141:$K141) -> 0.33333333 | L184: =L141/COUNT($L141:$M141) -> 0.5 | M184: =M141/COUNT($L141:$M141) -> 0 | N184: =N141/COUNT($N141:$R141) -> 0.2 | O184: =O141/COUNT($N141:$R141) -> 0.2 | P184: =P141/COUNT($N141:$R141) -> 0.2 | Q184: =Q141/COUNT($N141:$R141) -> 0.2 | R184: =R141/COUNT($N141:$R141) -> 0.2 | S184: =S141/COUNT($S141:$U141) -> 0.33333333 | T184: =T141/COUNT($S141:$U141) -> 0.33333333 | U184: =U141/COUNT($S141:$U141) -> 0.33333333 | V184: =V141/COUNT($V141:$Z141) -> 0.2 | W184: =W141/COUNT($V141:$Z141) -> 0.2 | X184: =X141/COUNT($V141:$Z141) -> 0 | Y184: =Y141/COUNT($V141:$Z141) -> 0.2 | Z184: =Z141/COUNT($V141:$Z141) -> 0 | AA184: =AA141/COUNT($AA141:$AB141) -> 0.5 | AB184: =AB141/COUNT($AA141:$AB141) -> 0 | AC184: =AC141/COUNT($AC141:$AG141) -> 0.2 | AD184: =AD141/COUNT($AC141:$AG141) -> 0 | AE184: =AE141/COUNT($AC141:$AG141) -> 0.2 | AF184: =AF141/COUNT($AC141:$AG141) -> 0 | AG184: =AG141/COUNT($AC141:$AG141) -> 0 | AH184: =AH141 -> 0
A185: =A142 -> P4 | B185: =B142/COUNT($B142:$D142) -> 0 | C185: =C142/COUNT($B142:$D142) -> 0 | D185: =D142/COUNT($B142:$D142) -> 0.33333333 | E185: =E142/COUNT($E142:$H142) -> 0 | F185: =F142/COUNT($E142:$H142) -> 0 | G185: =G142/COUNT($E142:$H142) -> 0 | H185: =H142/COUNT($E142:$H142) -> 0.25 | I185: =I142/COUNT($I142:$K142) -> 0 | J185: =J142/COUNT($I142:$K142) -> 0.33333333 | K185: =K142/COUNT($I142:$K142) -> 0 | L185: =L142/COUNT($L142:$M142) -> 0.5 | M185: =M142/COUNT($L142:$M142) -> 0 | N185: =N142/COUNT($N142:$R142) -> 0 | O185: =O142/COUNT($N142:$R142) -> 0.2 | P185: =P142/COUNT($N142:$R142) -> 0 | Q185: =Q142/COUNT($N142:$R142) -> 0.2 | R185: =R142/COUNT($N142:$R142) -> 0.2 | S185: =S142/COUNT($S142:$U142) -> 0.33333333 | T185: =T142/COUNT($S142:$U142) -> 0.33333333 | U185: =U142/COUNT($S142:$U142) -> 0.33333333 | V185: =V142/COUNT($V142:$Z142) -> 0.2 | W185: =W142/COUNT($V142:$Z142) -> 0 | X185: =X142/COUNT($V142:$Z142) -> 0 | Y185: =Y142/COUNT($V142:$Z142) -> 0 | Z185: =Z142/COUNT($V142:$Z142) -> 0 | AA185: =AA142/COUNT($AA142:$AB142) -> 0 | AB185: =AB142/COUNT($AA142:$AB142) -> 0 | AC185: =AC142/COUNT($AC142:$AG142) -> 0.2 | AD185: =AD142/COUNT($AC142:$AG142) -> 0 | AE185: =AE142/COUNT($AC142:$AG142) -> 0.2 | AF185: =AF142/COUNT($AC142:$AG142) -> 0.2 | AG185: =AG142/COUNT($AC142:$AG142) -> 0 | AH185: =AH142 -> 0
A186: =A143 -> P5 | B186: =B143/COUNT($B143:$D143) -> 0 | C186: =C143/COUNT($B143:$D143) -> 0.33333333 | D186: =D143/COUNT($B143:$D143) -> 0 | E186: =E143/COUNT($E143:$H143) -> 0.25 | F186: =F143/COUNT($E143:$H143) -> 0 | G186: =G143/COUNT($E143:$H143) -> 0 | H186: =H143/COUNT($E143:$H143) -> 0 | I186: =I143/COUNT($I143:$K143) -> 0 | J186: =J143/COUNT($I143:$K143) -> 0.33333333 | K186: =K143/COUNT($I143:$K143) -> 0 | L186: =L143/COUNT($L143:$M143) -> 0.5 | M186: =M143/COUNT($L143:$M143) -> 0 | N186: =N143/COUNT($N143:$R143) -> 0 | O186: =O143/COUNT($N143:$R143) -> 0.2 | P186: =P143/COUNT($N143:$R143) -> 0 | Q186: =Q143/COUNT($N143:$R143) -> 0.2 | R186: =R143/COUNT($N143:$R143) -> 0.2 | S186: =S143/COUNT($S143:$U143) -> 0.33333333 | T186: =T143/COUNT($S143:$U143) -> 0.33333333 | U186: =U143/COUNT($S143:$U143) -> 0 | V186: =V143/COUNT($V143:$Z143) -> 0.2 | W186: =W143/COUNT($V143:$Z143) -> 0 | X186: =X143/COUNT($V143:$Z143) -> 0 | Y186: =Y143/COUNT($V143:$Z143) -> 0 | Z186: =Z143/COUNT($V143:$Z143) -> 0 | AA186: =AA143/COUNT($AA143:$AB143) -> 0 | AB186: =AB143/COUNT($AA143:$AB143) -> 0 | AC186: =AC143/COUNT($AC143:$AG143) -> 0 | AD186: =AD143/COUNT($AC143:$AG143) -> 0 | AE186: =AE143/COUNT($AC143:$AG143) -> 0 | AF186: =AF143/COUNT($AC143:$AG143) -> 0 | AG186: =AG143/COUNT($AC143:$AG143) -> 0 | AH186: =AH143 -> 0
A187: =A144 -> P6 | B187: =B144/COUNT($B144:$D144) -> 0.33333333 | C187: =C144/COUNT($B144:$D144) -> 0 | D187: =D144/COUNT($B144:$D144) -> 0 | E187: =E144/COUNT($E144:$H144) -> 0 | F187: =F144/COUNT($E144:$H144) -> 0 | G187: =G144/COUNT($E144:$H144) -> 0 | H187: =H144/COUNT($E144:$H144) -> 0.25 | I187: =I144/COUNT($I144:$K144) -> 0 | J187: =J144/COUNT($I144:$K144) -> 0 | K187: =K144/COUNT($I144:$K144) -> 0 | L187: =L144/COUNT($L144:$M144) -> 0.5 | M187: =M144/COUNT($L144:$M144) -> 0 | N187: =N144/COUNT($N144:$R144) -> 0 | O187: =O144/COUNT($N144:$R144) -> 0 | P187: =P144/COUNT($N144:$R144) -> 0 | Q187: =Q144/COUNT($N144:$R144) -> 0 | R187: =R144/COUNT($N144:$R144) -> 0 | S187: =S144/COUNT($S144:$U144) -> 0.33333333 | T187: =T144/COUNT($S144:$U144) -> 0 | U187: =U144/COUNT($S144:$U144) -> 0 | V187: =V144/COUNT($V144:$Z144) -> 0.2 | W187: =W144/COUNT($V144:$Z144) -> 0 | X187: =X144/COUNT($V144:$Z144) -> 0.2 | Y187: =Y144/COUNT($V144:$Z144) -> 0.2 | Z187: =Z144/COUNT($V144:$Z144) -> 0.2 | AA187: =AA144/COUNT($AA144:$AB144) -> 0 | AB187: =AB144/COUNT($AA144:$AB144) -> 0.5 | AC187: =AC144/COUNT($AC144:$AG144) -> 0.2 | AD187: =AD144/COUNT($AC144:$AG144) -> 0 | AE187: =AE144/COUNT($AC144:$AG144) -> 0.2 | AF187: =AF144/COUNT($AC144:$AG144) -> 0 | AG187: =AG144/COUNT($AC144:$AG144) -> 0 | AH187: =AH144 -> 0
A188: =A145 -> P7 | B188: =B145/COUNT($B145:$D145) -> 0 | C188: =C145/COUNT($B145:$D145) -> 0 | D188: =D145/COUNT($B145:$D145) -> 0.33333333 | E188: =E145/COUNT($E145:$H145) -> 0 | F188: =F145/COUNT($E145:$H145) -> 0.25 | G188: =G145/COUNT($E145:$H145) -> 0 | H188: =H145/COUNT($E145:$H145) -> 0 | I188: =I145/COUNT($I145:$K145) -> 0 | J188: =J145/COUNT($I145:$K145) -> 0 | K188: =K145/COUNT($I145:$K145) -> 0 | L188: =L145/COUNT($L145:$M145) -> 0.5 | M188: =M145/COUNT($L145:$M145) -> 0 | N188: =N145/COUNT($N145:$R145) -> 0 | O188: =O145/COUNT($N145:$R145) -> 0.2 | P188: =P145/COUNT($N145:$R145) -> 0.2 | Q188: =Q145/COUNT($N145:$R145) -> 0.2 | R188: =R145/COUNT($N145:$R145) -> 0.2 | S188: =S145/COUNT($S145:$U145) -> 0.33333333 | T188: =T145/COUNT($S145:$U145) -> 0.33333333 | U188: =U145/COUNT($S145:$U145) -> 0 | V188: =V145/COUNT($V145:$Z145) -> 0 | W188: =W145/COUNT($V145:$Z145) -> 0 | X188: =X145/COUNT($V145:$Z145) -> 0 | Y188: =Y145/COUNT($V145:$Z145) -> 0 | Z188: =Z145/COUNT($V145:$Z145) -> 0 | AA188: =AA145/COUNT($AA145:$AB145) -> 0 | AB188: =AB145/COUNT($AA145:$AB145) -> 0 | AC188: =AC145/COUNT($AC145:$AG145) -> 0 | AD188: =AD145/COUNT($AC145:$AG145) -> 0 | AE188: =AE145/COUNT($AC145:$AG145) -> 0 | AF188: =AF145/COUNT($AC145:$AG145) -> 0 | AG188: =AG145/COUNT($AC145:$AG145) -> 0 | AH188: =AH145 -> 0
A189: =A146 -> P8 | B189: =B146/COUNT($B146:$D146) -> 0 | C189: =C146/COUNT($B146:$D146) -> 0.33333333 | D189: =D146/COUNT($B146:$D146) -> 0 | E189: =E146/COUNT($E146:$H146) -> 0 | F189: =F146/COUNT($E146:$H146) -> 0.25 | G189: =G146/COUNT($E146:$H146) -> 0 | H189: =H146/COUNT($E146:$H146) -> 0 | I189: =I146/COUNT($I146:$K146) -> 0 | J189: =J146/COUNT($I146:$K146) -> 0.33333333 | K189: =K146/COUNT($I146:$K146) -> 0.33333333 | L189: =L146/COUNT($L146:$M146) -> 0.5 | M189: =M146/COUNT($L146:$M146) -> 0 | N189: =N146/COUNT($N146:$R146) -> 0 | O189: =O146/COUNT($N146:$R146) -> 0.2 | P189: =P146/COUNT($N146:$R146) -> 0.2 | Q189: =Q146/COUNT($N146:$R146) -> 0.2 | R189: =R146/COUNT($N146:$R146) -> 0.2 | S189: =S146/COUNT($S146:$U146) -> 0.33333333 | T189: =T146/COUNT($S146:$U146) -> 0.33333333 | U189: =U146/COUNT($S146:$U146) -> 0 | V189: =V146/COUNT($V146:$Z146) -> 0.2 | W189: =W146/COUNT($V146:$Z146) -> 0.2 | X189: =X146/COUNT($V146:$Z146) -> 0.2 | Y189: =Y146/COUNT($V146:$Z146) -> 0.2 | Z189: =Z146/COUNT($V146:$Z146) -> 0.2 | AA189: =AA146/COUNT($AA146:$AB146) -> 0.5 | AB189: =AB146/COUNT($AA146:$AB146) -> 0 | AC189: =AC146/COUNT($AC146:$AG146) -> 0 | AD189: =AD146/COUNT($AC146:$AG146) -> 0.2 | AE189: =AE146/COUNT($AC146:$AG146) -> 0.2 | AF189: =AF146/COUNT($AC146:$AG146) -> 0 | AG189: =AG146/COUNT($AC146:$AG146) -> 0 | AH189: =AH146 -> 1
A190: =A147 -> P9 | B190: =B147/COUNT($B147:$D147) -> 0 | C190: =C147/COUNT($B147:$D147) -> 0.33333333 | D190: =D147/COUNT($B147:$D147) -> 0 | E190: =E147/COUNT($E147:$H147) -> 0 | F190: =F147/COUNT($E147:$H147) -> 0.25 | G190: =G147/COUNT($E147:$H147) -> 0 | H190: =H147/COUNT($E147:$H147) -> 0 | I190: =I147/COUNT($I147:$K147) -> 0 | J190: =J147/COUNT($I147:$K147) -> 0.33333333 | K190: =K147/COUNT($I147:$K147) -> 0.33333333 | L190: =L147/COUNT($L147:$M147) -> 0.5 | M190: =M147/COUNT($L147:$M147) -> 0 | N190: =N147/COUNT($N147:$R147) -> 0.2 | O190: =O147/COUNT($N147:$R147) -> 0.2 | P190: =P147/COUNT($N147:$R147) -> 0.2 | Q190: =Q147/COUNT($N147:$R147) -> 0.2 | R190: =R147/COUNT($N147:$R147) -> 0.2 | S190: =S147/COUNT($S147:$U147) -> 0.33333333 | T190: =T147/COUNT($S147:$U147) -> 0 | U190: =U147/COUNT($S147:$U147) -> 0 | V190: =V147/COUNT($V147:$Z147) -> 0.2 | W190: =W147/COUNT($V147:$Z147) -> 0.2 | X190: =X147/COUNT($V147:$Z147) -> 0 | Y190: =Y147/COUNT($V147:$Z147) -> 0.2 | Z190: =Z147/COUNT($V147:$Z147) -> 0 | AA190: =AA147/COUNT($AA147:$AB147) -> 0.5 | AB190: =AB147/COUNT($AA147:$AB147) -> 0 | AC190: =AC147/COUNT($AC147:$AG147) -> 0 | AD190: =AD147/COUNT($AC147:$AG147) -> 0 | AE190: =AE147/COUNT($AC147:$AG147) -> 0 | AF190: =AF147/COUNT($AC147:$AG147) -> 0 | AG190: =AG147/COUNT($AC147:$AG147) -> 0 | AH190: =AH147 -> 1
A191: =A148 -> P10 | B191: =B148/COUNT($B148:$D148) -> 0 | C191: =C148/COUNT($B148:$D148) -> 0.33333333 | D191: =D148/COUNT($B148:$D148) -> 0 | E191: =E148/COUNT($E148:$H148) -> 0 | F191: =F148/COUNT($E148:$H148) -> 0.25 | G191: =G148/COUNT($E148:$H148) -> 0 | H191: =H148/COUNT($E148:$H148) -> 0 | I191: =I148/COUNT($I148:$K148) -> 0 | J191: =J148/COUNT($I148:$K148) -> 0.33333333 | K191: =K148/COUNT($I148:$K148) -> 0 | L191: =L148/COUNT($L148:$M148) -> 0.5 | M191: =M148/COUNT($L148:$M148) -> 0 | N191: =N148/COUNT($N148:$R148) -> 0.2 | O191: =O148/COUNT($N148:$R148) -> 0.2 | P191: =P148/COUNT($N148:$R148) -> 0.2 | Q191: =Q148/COUNT($N148:$R148) -> 0.2 | R191: =R148/COUNT($N148:$R148) -> 0.2 | S191: =S148/COUNT($S148:$U148) -> 0.33333333 | T191: =T148/COUNT($S148:$U148) -> 0.33333333 | U191: =U148/COUNT($S148:$U148) -> 0 | V191: =V148/COUNT($V148:$Z148) -> 0 | W191: =W148/COUNT($V148:$Z148) -> 0.2 | X191: =X148/COUNT($V148:$Z148) -> 0 | Y191: =Y148/COUNT($V148:$Z148) -> 0 | Z191: =Z148/COUNT($V148:$Z148) -> 0 | AA191: =AA148/COUNT($AA148:$AB148) -> 0 | AB191: =AB148/COUNT($AA148:$AB148) -> 0 | AC191: =AC148/COUNT($AC148:$AG148) -> 0.2 | AD191: =AD148/COUNT($AC148:$AG148) -> 0 | AE191: =AE148/COUNT($AC148:$AG148) -> 0 | AF191: =AF148/COUNT($AC148:$AG148) -> 0 | AG191: =AG148/COUNT($AC148:$AG148) -> 0 | AH191: =AH148 -> 1
A192: =A149 -> P11 | B192: =B149/COUNT($B149:$D149) -> 0 | C192: =C149/COUNT($B149:$D149) -> 0.33333333 | D192: =D149/COUNT($B149:$D149) -> 0 | E192: =E149/COUNT($E149:$H149) -> 0 | F192: =F149/COUNT($E149:$H149) -> 0 | G192: =G149/COUNT($E149:$H149) -> 0 | H192: =H149/COUNT($E149:$H149) -> 0.25 | I192: =I149/COUNT($I149:$K149) -> 0 | J192: =J149/COUNT($I149:$K149) -> 0 | K192: =K149/COUNT($I149:$K149) -> 0 | L192: =L149/COUNT($L149:$M149) -> 0 | M192: =M149/COUNT($L149:$M149) -> 0.5 | N192: =N149/COUNT($N149:$R149) -> 0 | O192: =O149/COUNT($N149:$R149) -> 0.2 | P192: =P149/COUNT($N149:$R149) -> 0.2 | Q192: =Q149/COUNT($N149:$R149) -> 0.2 | R192: =R149/COUNT($N149:$R149) -> 0 | S192: =S149/COUNT($S149:$U149) -> 0.33333333 | T192: =T149/COUNT($S149:$U149) -> 0.33333333 | U192: =U149/COUNT($S149:$U149) -> 0 | V192: =V149/COUNT($V149:$Z149) -> 0.2 | W192: =W149/COUNT($V149:$Z149) -> 0.2 | X192: =X149/COUNT($V149:$Z149) -> 0 | Y192: =Y149/COUNT($V149:$Z149) -> 0 | Z192: =Z149/COUNT($V149:$Z149) -> 0 | AA192: =AA149/COUNT($AA149:$AB149) -> 0 | AB192: =AB149/COUNT($AA149:$AB149) -> 0 | AC192: =AC149/COUNT($AC149:$AG149) -> 0 | AD192: =AD149/COUNT($AC149:$AG149) -> 0 | AE192: =AE149/COUNT($AC149:$AG149) -> 0 | AF192: =AF149/COUNT($AC149:$AG149) -> 0 | AG192: =AG149/COUNT($AC149:$AG149) -> 0 | AH192: =AH149 -> 0
A193: =A150 -> P12 | B193: =B150/COUNT($B150:$D150) -> 0 | C193: =C150/COUNT($B150:$D150) -> 0 | D193: =D150/COUNT($B150:$D150) -> 0 | E193: =E150/COUNT($E150:$H150) -> 0 | F193: =F150/COUNT($E150:$H150) -> 0 | G193: =G150/COUNT($E150:$H150) -> 0 | H193: =H150/COUNT($E150:$H150) -> 0 | I193: =I150/COUNT($I150:$K150) -> 0 | J193: =J150/COUNT($I150:$K150) -> 0.33333333 | K193: =K150/COUNT($I150:$K150) -> 0 | L193: =L150/COUNT($L150:$M150) -> 0 | M193: =M150/COUNT($L150:$M150) -> 0 | N193: =N150/COUNT($N150:$R150) -> 0.2 | O193: =O150/COUNT($N150:$R150) -> 0.2 | P193: =P150/COUNT($N150:$R150) -> 0.2 | Q193: =Q150/COUNT($N150:$R150) -> 0.2 | R193: =R150/COUNT($N150:$R150) -> 0.2 | S193: =S150/COUNT($S150:$U150) -> 0.33333333 | T193: =T150/COUNT($S150:$U150) -> 0.33333333 | U193: =U150/COUNT($S150:$U150) -> 0 | V193: =V150/COUNT($V150:$Z150) -> 0.2 | W193: =W150/COUNT($V150:$Z150) -> 0.2 | X193: =X150/COUNT($V150:$Z150) -> 0 | Y193: =Y150/COUNT($V150:$Z150) -> 0 | Z193: =Z150/COUNT($V150:$Z150) -> 0 | AA193: =AA150/COUNT($AA150:$AB150) -> 0 | AB193: =AB150/COUNT($AA150:$AB150) -> 0 | AC193: =AC150/COUNT($AC150:$AG150) -> 0 | AD193: =AD150/COUNT($AC150:$AG150) -> 0 | AE193: =AE150/COUNT($AC150:$AG150) -> 0 | AF193: =AF150/COUNT($AC150:$AG150) -> 0 | AG193: =AG150/COUNT($AC150:$AG150) -> 0 | AH193: =AH150 -> 0
... A222: =A179 -> P41 | B222: =B179/COUNT($B179:$D179) -> 0.33333333 | C222: =C179/COUNT($B179:$D179) -> 0 | D222: =D179/COUNT($B179:$D179) -> 0 | E222: =E179/COUNT($E179:$H179) -> 0 | F222: =F179/COUNT($E179:$H179) -> 0 | G222: =G179/COUNT($E179:$H179) -> 0 | H222: =H179/COUNT($E179:$H179) -> 0.25 | I222: =I179/COUNT($I179:$K179) -> 0 | J222: =J179/COUNT($I179:$K179) -> 0 | K222: =K179/COUNT($I179:$K179) -> 0.33333333 | L222: =L179/COUNT($L179:$M179) -> 0.5 | M222: =M179/COUNT($L179:$M179) -> 0 | N222: =N179/COUNT($N179:$R179) -> 0 | O222: =O179/COUNT($N179:$R179) -> 0 | P222: =P179/COUNT($N179:$R179) -> 0 | Q222: =Q179/COUNT($N179:$R179) -> 0.2 | R222: =R179/COUNT($N179:$R179) -> 0 | S222: =S179/COUNT($S179:$U179) -> 0.33333333 | T222: =T179/COUNT($S179:$U179) -> 0 | U222: =U179/COUNT($S179:$U179) -> 0.33333333 | V222: =V179/COUNT($V179:$Z179) -> 0.2 | W222: =W179/COUNT($V179:$Z179) -> 0 | X222: =X179/COUNT($V179:$Z179) -> 0.2 | Y222: =Y179/COUNT($V179:$Z179) -> 0 | Z222: =Z179/COUNT($V179:$Z179) -> 0.2 | AA222: =AA179/COUNT($AA179:$AB179) -> 0 | AB222: =AB179/COUNT($AA179:$AB179) -> 0.5 | AC222: =AC179/COUNT($AC179:$AG179) -> 0.2 | AD222: =AD179/COUNT($AC179:$AG179) -> 0 | AE222: =AE179/COUNT($AC179:$AG179) -> 0.2 | AF222: =AF179/COUNT($AC179:$AG179) -> 0 | AG222: =AG179/COUNT($AC179:$AG179) -> 0 | AH222: =AH179 -> 0
B224: =B181 -> X1 | C224: =C181 -> 0 | D224: =D181 -> 0 | E224: =E181 -> X2 | F224: =F181 -> 0 | G224: =G181 -> 0 | H224: =H181 -> 0 | I224: =I181 -> X3 | ... AH224: =AH181 -> X10 | AI224: PMC-T
A225: =A182 -> P1 | B225: =SUM(B182:D182) -> 0.33333333 | E225: =SUM(E182:H182) -> 0 | I225: =SUM(I182:K182) -> 0.33333333 | L225: =SUM(L182:M182) -> 0.5 | N225: =SUM(N182:R182) -> 0.8 | S225: =SUM(S182:U182) -> 0.66666667 | V225: =SUM(V182:Z182) -> 0 | AA225: =SUM(AA182:AB182) -> 0 | AC225: =SUM(AC182:AG182) -> 0.4 | AH225: =AH182 -> 0 | AI225: =SUM(B225:AH225) -> 3.0333333
A226: =A183 -> P2 | B226: =SUM(B183:D183) -> 0.33333333 | E226: =SUM(E183:H183) -> 0.25 | I226: =SUM(I183:K183) -> 0 | L226: =SUM(L183:M183) -> 0.5 | N226: =SUM(N183:R183) -> 1 | S226: =SUM(S183:U183) -> 0.33333333 | V226: =SUM(V183:Z183) -> 0.8 | AA226: =SUM(AA183:AB183) -> 0 | AC226: =SUM(AC183:AG183) -> 0.2 | AH226: =AH183 -> 0 | AI226: =SUM(B226:AH226) -> 3.4166667
A227: =A184 -> P3 | B227: =SUM(B184:D184) -> 0.33333333 | E227: =SUM(E184:H184) -> 0.25 | I227: =SUM(I184:K184) -> 0.66666667 | L227: =SUM(L184:M184) -> 0.5 | N227: =SUM(N184:R184) -> 1 | S227: =SUM(S184:U184) -> 1 | V227: =SUM(V184:Z184) -> 0.6 | AA227: =SUM(AA184:AB184) -> 0.5 | AC227: =SUM(AC184:AG184) -> 0.4 | AH227: =AH184 -> 0 | AI227: =SUM(B227:AH227) -> 5.25
A228: =A185 -> P4 | B228: =SUM(B185:D185) -> 0.33333333 | E228: =SUM(E185:H185) -> 0.25 | I228: =SUM(I185:K185) -> 0.33333333 | L228: =SUM(L185:M185) -> 0.5 | N228: =SUM(N185:R185) -> 0.6 | S228: =SUM(S185:U185) -> 1 | V228: =SUM(V185:Z185) -> 0.2 | AA228: =SUM(AA185:AB185) -> 0 | AC228: =SUM(AC185:AG185) -> 0.6 | AH228: =AH185 -> 0 | AI228: =SUM(B228:AH228) -> 3.8166667
A229: =A186 -> P5 | B229: =SUM(B186:D186) -> 0.33333333 | E229: =SUM(E186:H186) -> 0.25 | I229: =SUM(I186:K186) -> 0.33333333 | L229: =SUM(L186:M186) -> 0.5 | N229: =SUM(N186:R186) -> 0.6 | S229: =SUM(S186:U186) -> 0.66666667 | V229: =SUM(V186:Z186) -> 0.2 | AA229: =SUM(AA186:AB186) -> 0 | AC229: =SUM(AC186:AG186) -> 0 | AH229: =AH186 -> 0 | AI229: =SUM(B229:AH229) -> 2.8833333
A230: =A187 -> P6 | B230: =SUM(B187:D187) -> 0.33333333 | E230: =SUM(E187:H187) -> 0.25 | I230: =SUM(I187:K187) -> 0 | L230: =SUM(L187:M187) -> 0.5 | N230: =SUM(N187:R187) -> 0 | S230: =SUM(S187:U187) -> 0.33333333 | V230: =SUM(V187:Z187) -> 0.8 | AA230: =SUM(AA187:AB187) -> 0.5 | AC230: =SUM(AC187:AG187) -> 0.4 | AH230: =AH187 -> 0 | AI230: =SUM(B230:AH230) -> 3.1166667
A231: =A188 -> P7 | B231: =SUM(B188:D188) -> 0.33333333 | E231: =SUM(E188:H188) -> 0.25 | I231: =SUM(I188:K188) -> 0 | L231: =SUM(L188:M188) -> 0.5 | N231: =SUM(N188:R188) -> 0.8 | S231: =SUM(S188:U188) -> 0.66666667 | V231: =SUM(V188:Z188) -> 0 | AA231: =SUM(AA188:AB188) -> 0 | AC231: =SUM(AC188:AG188) -> 0 | AH231: =AH188 -> 0 | AI231: =SUM(B231:AH231) -> 2.55
A232: =A189 -> P8 | B232: =SUM(B189:D189) -> 0.33333333 | E232: =SUM(E189:H189) -> 0.25 | I232: =SUM(I189:K189) -> 0.66666667 | L232: =SUM(L189:M189) -> 0.5 | N232: =SUM(N189:R189) -> 0.8 | S232: =SUM(S189:U189) -> 0.66666667 | V232: =SUM(V189:Z189) -> 1 | AA232: =SUM(AA189:AB189) -> 0.5 | AC232: =SUM(AC189:AG189) -> 0.4 | AH232: =AH189 -> 1 | AI232: =SUM(B232:AH232) -> 6.1166667
A233: =A190 -> P9 | B233: =SUM(B190:D190) -> 0.33333333 | E233: =SUM(E190:H190) -> 0.25 | I233: =SUM(I190:K190) -> 0.66666667 | L233: =SUM(L190:M190) -> 0.5 | N233: =SUM(N190:R190) -> 1 | S233: =SUM(S190:U190) -> 0.33333333 | V233: =SUM(V190:Z190) -> 0.6 | AA233: =SUM(AA190:AB190) -> 0.5 | AC233: =SUM(AC190:AG190) -> 0 | AH233: =AH190 -> 1 | AI233: =SUM(B233:AH233) -> 5.1833333
A234: =A191 -> P10 | B234: =SUM(B191:D191) -> 0.33333333 | E234: =SUM(E191:H191) -> 0.25 | I234: =SUM(I191:K191) -> 0.33333333 | L234: =SUM(L191:M191) -> 0.5 | N234: =SUM(N191:R191) -> 1 | S234: =SUM(S191:U191) -> 0.66666667 | V234: =SUM(V191:Z191) -> 0.2 | AA234: =SUM(AA191:AB191) -> 0 | AC234: =SUM(AC191:AG191) -> 0.2 | AH234: =AH191 -> 1 | AI234: =SUM(B234:AH234) -> 4.4833333
...

Sheet machine_learning
G1: CNY Yuan per square meter | H1: Months | I1: Months | J1: CNY Yuan per square meter | K1: CNY Yuan per square meter | L1: % | M1: % | S1: Months
B2: 城市 | C2: PMCcode | D2: City | E2: Tier System | F2: Province | G2: City average price | H2: Sales absorption period | I2: Standard construction duration | J2: Peak occupancy cost | K2: Opportunity cost | L2: Opportunity cost as a percentage of average sales price | M2: Peak occupancy costs as a percentage of sales price | N2: ='Evaluation-transfer'!AI88 -> PMC-I | O2: ='Evaluation-transfer'!AI224 -> PMC-T | S2: Standard construction duration
B3: 白沙 | C3: P1 | D3: Baisha | E3: Third Tier | F3: Hainan | G3: 7850 | H3: 109.1 | I3: 27.141667 | J3: 3500 | K3: 44.559244 | L3: 0.0056763368 | M3: 0.44585987 | N3: ='Evaluation-transfer'!AI89 -> 3.0333333 | O3: ='Evaluation-transfer'!AI225 -> 3.0333333 | S3: 27.141667 | T3: 26.5
B4: 北海 | C4: P2 | D4: Beihai | E4: Third Tier | F4: Guangxi | G4: 6800 | H4: 11.524897 | I4: 27.141667 | J4: 2560.1079 | K4: 315.86099 | L4: 0.046450146 | M4: 0.37648646 | N4: ='Evaluation-transfer'!AI90 -> 3.4166667 | O4: ='Evaluation-transfer'!AI226 -> 3.4166667 | S4: 27.141667 | T4: 27.141667
B5: 北京 | C5: P3 | D5: Beijing | E5: First Tier | F5: Beijing | G5: 40094 | H5: 19 | I5: 28.008333 | J5: 5000 | K5: 1175.8517 | L5: 0.029327373 | M5: 0.12470694 | N5: ='Evaluation-transfer'!AI91 -> 6.9166667 | O5: ='Evaluation-transfer'!AI227 -> 5.25 | S5: 28.008333 | T5: 27.1
B6: 澄迈 | C6: P4 | D6: Chengmai | E6: Third Tier | F6: Hainan | G6: 11522 | H6: 54.5 | I6: 27.141667 | J6: 3500 | K6: 498.09375 | L6: 0.0432298 | M6: 0.30376671 | N6: ='Evaluation-transfer'!AI92 -> 4.35 | O6: ='Evaluation-transfer'!AI228 -> 3.8166667 | S6: 27.141667 | T6: 26.5
B7: 儋州 | C7: P5 | D7: Danzhou | E7: Third Tier | F7: Hainan | G7: 10533 | H7: 82.5 | I7: 27.141667 | J7: 1798.1091 | K7: 84.611564 | L7: 0.0080329976 | M7: 0.17071196 | N7: ='Evaluation-transfer'!AI93 -> 3.75 | O7: ='Evaluation-transfer'!AI229 -> 2.8833333 | S7: 27.141667 | T7: 26.5
B8: 定安 | C8: P6 | D8: Dingwan | E8: Third Tier | F8: Hainan | G8: 8030 | H8: 41.5 | I8: 27.141667 | J8: 1315.759 | K8: 67.589864 | L8: 0.0084171687 | M8: 0.16385542 | N8: ='Evaluation-transfer'!AI94 -> 3.45 | O8: ='Evaluation-transfer'!AI230 -> 3.1166667 | S8: 27.141667 | T8: 26.5
B9: 东方 | C9: P7 | D9: Dongfang | E9: Third Tier | F9: Hainan | G9: 12405 | H9: 61.7 | I9: 27.141667 | J9: 1256.5843 | K9: 71.444356 | L9: 0.0057593193 | M9: 0.1012966 | N9: ='Evaluation-transfer'!AI95 -> 4.0166667 | O9: ='Evaluation-transfer'!AI231 -> 2.55 | S9: 27.141667 | T9: 26.5
B10: 东莞 | C10: P8 | D10: Dongguan | E10: Second Tier | F10: Guangdong | G10: 36305 | H10: 25.6 | I10: 27.141667 | J10: 14819.814 | K10: 999.32703 | L10: 0.027525879 | M10: 0.40820312 | N10: ='Evaluation-transfer'!AI96 -> 9.05 | O10: ='Evaluation-transfer'!AI232 -> 6.1166667 | S10: 27.141667 | T10: 27.141667
B11: 东营 | C11: P9 | D11: Dongying | E11: Third Tier | F11: Shandong | G11: 8079 | H11: 52.3 | I11: 28.008333 | J11: 1668.3212 | K11: 133.50045 | L11: 0.016524379 | M11: 0.20650096 | N11: ='Evaluation-transfer'!AI97 -> 6.3166667 | O11: ='Evaluation-transfer'!AI233 -> 5.1833333 | S11: 28.008333 | T11: 28.008333
B12: 佛山 | C12: P10 | D12: Foshan | E12: Second Tier | F12: Guangdong | G12: 18333 | H12: 19.9 | I12: 27.141667 | J12: 1372.6719 | K12: 66.268267 | L12: 0.0036146985 | M12: 0.074874372 | N12: ='Evaluation-transfer'!AI98 -> 6.5833333 | O12: ='Evaluation-transfer'!AI234 -> 4.4833333 | S12: 27.141667 | T12: 25
B13: 广州 | C13: P11 | D13: Guangzhou | E13: First Tier | F13: Guangdong | G13: 37881 | H13: 17.6 | I13: 27.141667 | J13: 6177.1858 | K13: 809.7548 | L13: 0.021376278 | M13: 0.16306818 | N13: ='Evaluation-transfer'!AI99 -> 3.0833333 | O13: ='Evaluation-transfer'!AI235 -> 2.75 | S13: 27.141667 | T13: 24
B14: 海口 | C14: P12 | D14: Haikou | E14: Second Tier | F14: Hainan | G14: 18307 | H14: 19.4 | I14: 27.141667 | J14: 5000 | K14: 427.89905 | L14: 0.023373521 | M14: 0.27311957 | N14: ='Evaluation-transfer'!AI100 -> 2.7333333 | O14: ='Evaluation-transfer'!AI236 -> 2.4 | S14: 27.141667 | T14: 26.5
... B43: 昌江 | C43: P41 | D43: Changjiang | E43: Third Tier | F43: Hainan | G43: 6880 | H43: 18.1 | I43: 27.141667 | J43: 2508.7293 | K43: 131.79381 | L43: 0.019156077 | M43: 0.36464088 | N43: ='Evaluation-transfer'!AI129 -> 4.45 | O43: ='Evaluation-transfer'!AI265 -> 3.7833333 | S43: 27.141667 | T43: 26.5
E50: Total Number | F50: Mean | G50: Standard deviation | H50: Variance | I50: Skewness | J50: Min. value | K50: Q1 | L50: Median | M50: Q3 | N50: Max. value | O50: Range | AB50: Value)
E51: 总数N | F51: 均值 | G51: 标准差 | H51: 方差 | I51: 偏度 | J51: 最小值 | K51: 第一个四分位数(Q1) | L51: 中位数 | M51: 第三个四分位数(Q3) | N51: 最大值 | O51: 极差(最大值-最小值)
B52: Sales absorption period | D52: Third Tier | E52: 24 | F52: 69.94644 | G52: 66.83779 | H52: 4467.2903 | I52: 2.40026 | J52: 6.4 | K52: 21.55 | L52: 54.8 | M52: 95.8 | N52: 318.7 | O52: 312.3
D53: First Tier | E53: 4 | F53: 21.625 | G53: 4.05822 | H53: 16.46917 | I53: 0.32088 | J53: 17.6 | K53: 18.3 | L53: 21.25 | M53: 24.95 | N53: 26.4 | O53: 8.8
D54: Second Tier | E54: 13 | F54: 27.75385 | G54: 14.67904 | H54: 215.47436 | I54: 0.81471 | J54: 7.1 | K54: 19.9 | L54: 22.6 | M54: 34.1 | N54: 55.7 | O54: 48.6
B55: City average sales price | D55: Third Tier | E55: 24 | F55: 9798.625 | G55: 3612.628 | H55: 13051100 | I55: 1.05376 | J55: 4898 | K55: 7012.5 | L55: 8237 | M55: 12144.5 | N55: 19437 | O55: 14539
D56: First Tier | E56: 4 | F56: 52036 | G56: 15137.982 | H56: 229158000 | I56: 0.01147 | J56: 37881 | K56: 38987.5 | L56: 51884.5 | M56: 65084.5 | N56: 66494 | O56: 28613
D57: Second Tier | E57: 13 | F57: 17425.462 | G57: 9032.453 | H57: 81585200 | I57: 0.89379 | J57: 5911 | K57: 10711 | L57: 13988 | M57: 21353 | N57: 36305 | O57: 30394
B58: Standard construction duration | D58: Third Tier | E58: 24 | F58: 27.25 | G58: 0.29279 | H58: 0.08572 | I58: 2.42186 | J58: 27.14167 | K58: 27.14167 | L58: 27.14167 | M58: 27.14167 | N58: 28.00833 | O58: 0.86667
D59: First Tier | E59: 4 | F59: 27.35833 | G59: 0.43333 | H59: 0.18778 | I59: 2 | J59: 27.14167 | K59: 27.14167 | L59: 27.14167 | M59: 27.575 | N59: 28.00833 | O59: 0.86667
D60: Second Tier | E60: 13 | F60: 27.20833 | G60: 0.24037 | H60: 0.05778 | I60: 3.60555 | J60: 27.14167 | K60: 27.14167 | L60: 27.14167 | M60: 27.14167 | N60: 28.00833 | O60: 0.86667

Sheet Randa plot
A2: =machine_learning!C2 -> PMCcode | B2: =machine_learning!E2 -> Tier System | C2: ='Evaluation-transfer'!N271 -> X1 | D2: ='Evaluation-transfer'!O271 -> X2 | E2: ='Evaluation-transfer'!P271 -> X3 | F2: ='Evaluation-transfer'!Q271 -> X4 | G2: ='Evaluation-transfer'!R271 -> X5 | H2: ='Evaluation-transfer'!S271 -> X6 | I2: ='Evaluation-transfer'!T271 -> X7 | J2: ='Evaluation-transfer'!U271 -> X8 | ... M2: ='Evaluation-transfer'!X271 -> PMC-T | O2: =A2 -> PMCcode | P2: =B2 -> Tier System | Q2: ='Evaluation-transfer'!AC271 -> X1 | R2: ='Evaluation-transfer'!AD271 -> X2 | S2: ='Evaluation-transfer'!AE271 -> X3 | T2: ='Evaluation-transfer'!AF271 -> X4 | U2: ='Evaluation-transfer'!AG271 -> X5 | V2: ='Evaluation-transfer'!AH271 -> X6 | W2: ='Evaluation-transfer'!AI271 -> X7 | X2: ='Evaluation-transfer'!AJ271 -> X8 | ... AA2: ='Evaluation-transfer'!AM271 -> PMC-I
A3: =machine_learning!C3 -> P1 | B3: =machine_learning!E3 -> Third Tier | C3: ='Evaluation-transfer'!N272 -> 0.33333333 | D3: ='Evaluation-transfer'!O272 -> 0 | E3: ='Evaluation-transfer'!P272 -> 0.33333333 | F3: ='Evaluation-transfer'!Q272 -> 0.5 | G3: ='Evaluation-transfer'!R272 -> 0.8 | H3: ='Evaluation-transfer'!S272 -> 0.66666667 | I3: ='Evaluation-transfer'!T272 -> 0 | J3: ='Evaluation-transfer'!U272 -> 0 | ... M3: ='Evaluation-transfer'!X272 -> 3.0333333 | O3: =A3 -> P1 | P3: =B3 -> Third Tier | Q3: ='Evaluation-transfer'!AC272 -> 0.33333333 | R3: ='Evaluation-transfer'!AD272 -> 0 | S3: ='Evaluation-transfer'!AE272 -> 0.33333333 | T3: ='Evaluation-transfer'!AF272 -> 0.5 | U3: ='Evaluation-transfer'!AG272 -> 0.8 | V3: ='Evaluation-transfer'!AH272 -> 0.66666667 | W3: ='Evaluation-transfer'!AI272 -> 0 | X3: ='Evaluation-transfer'!AJ272 -> 0 | ... AA3: ='Evaluation-transfer'!AM272 -> 3.0333333
A4: =machine_learning!C4 -> P2 | B4: =machine_learning!E4 -> Third Tier | C4: ='Evaluation-transfer'!N273 -> 0.33333333 | D4: ='Evaluation-transfer'!O273 -> 0.25 | E4: ='Evaluation-transfer'!P273 -> 0 | F4: ='Evaluation-transfer'!Q273 -> 0.5 | G4: ='Evaluation-transfer'!R273 -> 1 | H4: ='Evaluation-transfer'!S273 -> 0.33333333 | I4: ='Evaluation-transfer'!T273 -> 0.8 | J4: ='Evaluation-transfer'!U273 -> 0 | ... M4: ='Evaluation-transfer'!X273 -> 3.4166667 | O4: =A4 -> P2 | P4: =B4 -> Third Tier | Q4: ='Evaluation-transfer'!AC273 -> 0.33333333 | R4: ='Evaluation-transfer'!AD273 -> 0.25 | S4: ='Evaluation-transfer'!AE273 -> 0 | T4: ='Evaluation-transfer'!AF273 -> 0.5 | U4: ='Evaluation-transfer'!AG273 -> 1 | V4: ='Evaluation-transfer'!AH273 -> 0.33333333 | W4: ='Evaluation-transfer'!AI273 -> 0.8 | X4: ='Evaluation-transfer'!AJ273 -> 0 | ... AA4: ='Evaluation-transfer'!AM273 -> 3.4166667
A5: =machine_learning!C5 -> P3 | B5: =machine_learning!E5 -> First Tier | C5: ='Evaluation-transfer'!N274 -> 0.33333333 | D5: ='Evaluation-transfer'!O274 -> 0.25 | E5: ='Evaluation-transfer'!P274 -> 0.66666667 | F5: ='Evaluation-transfer'!Q274 -> 0.5 | G5: ='Evaluation-transfer'!R274 -> 1 | H5: ='Evaluation-transfer'!S274 -> 1 | I5: ='Evaluation-transfer'!T274 -> 0.6 | J5: ='Evaluation-transfer'!U274 -> 0.5 | ... M5: ='Evaluation-transfer'!X274 -> 5.25 | O5: =A5 -> P3 | P5: =B5 -> First Tier | Q5: ='Evaluation-transfer'!AC274 -> 0.33333333 | R5: ='Evaluation-transfer'!AD274 -> 0.25 | S5: ='Evaluation-transfer'!AE274 -> 1.3333333 | T5: ='Evaluation-transfer'!AF274 -> 0.5 | U5: ='Evaluation-transfer'!AG274 -> 1.6 | V5: ='Evaluation-transfer'!AH274 -> 1 | W5: ='Evaluation-transfer'!AI274 -> 0.8 | X5: ='Evaluation-transfer'!AJ274 -> 0.5 | ... AA5: ='Evaluation-transfer'!AM274 -> 6.9166667
A6: =machine_learning!C6 -> P4 | B6: =machine_learning!E6 -> Third Tier | C6: ='Evaluation-transfer'!N275 -> 0.33333333 | D6: ='Evaluation-transfer'!O275 -> 0.25 | E6: ='Evaluation-transfer'!P275 -> 0.33333333 | F6: ='Evaluation-transfer'!Q275 -> 0.5 | G6: ='Evaluation-transfer'!R275 -> 0.6 | H6: ='Evaluation-transfer'!S275 -> 1 | I6: ='Evaluation-transfer'!T275 -> 0.2 | J6: ='Evaluation-transfer'!U275 -> 0 | ... M6: ='Evaluation-transfer'!X275 -> 3.8166667 | O6: =A6 -> P4 | P6: =B6 -> Third Tier | Q6: ='Evaluation-transfer'!AC275 -> 0.33333333 | R6: ='Evaluation-transfer'!AD275 -> 0.25 | S6: ='Evaluation-transfer'!AE275 -> 0.33333333 | T6: ='Evaluation-transfer'!AF275 -> 0.5 | U6: ='Evaluation-transfer'!AG275 -> 0.8 | V6: ='Evaluation-transfer'!AH275 -> 1.3333333 | W6: ='Evaluation-transfer'!AI275 -> 0.2 | X6: ='Evaluation-transfer'!AJ275 -> 0 | ... AA6: ='Evaluation-transfer'!AM275 -> 4.35
A7: =machine_learning!C7 -> P5 | B7: =machine_learning!E7 -> Third Tier | C7: ='Evaluation-transfer'!N276 -> 0.33333333 | D7: ='Evaluation-transfer'!O276 -> 0.25 | E7: ='Evaluation-transfer'!P276 -> 0.33333333 | F7: ='Evaluation-transfer'!Q276 -> 0.5 | G7: ='Evaluation-transfer'!R276 -> 0.6 | H7: ='Evaluation-transfer'!S276 -> 0.66666667 | I7: ='Evaluation-transfer'!T276 -> 0.2 | J7: ='Evaluation-transfer'!U276 -> 0 | ... M7: ='Evaluation-transfer'!X276 -> 2.8833333 | O7: =A7 -> P5 | P7: =B7 -> Third Tier | Q7: ='Evaluation-transfer'!AC276 -> 0.33333333 | R7: ='Evaluation-transfer'!AD276 -> 0.25 | S7: ='Evaluation-transfer'!AE276 -> 0.33333333 | T7: ='Evaluation-transfer'!AF276 -> 0.5 | U7: ='Evaluation-transfer'!AG276 -> 0.8 | V7: ='Evaluation-transfer'!AH276 -> 1.3333333 | W7: ='Evaluation-transfer'!AI276 -> 0.2 | X7: ='Evaluation-transfer'!AJ276 -> 0 | ... AA7: ='Evaluation-transfer'!AM276 -> 3.75
A8: =machine_learning!C8 -> P6 | B8: =machine_learning!E8 -> Third Tier | C8: ='Evaluation-transfer'!N277 -> 0.33333333 | D8: ='Evaluation-transfer'!O277 -> 0.25 | E8: ='Evaluation-transfer'!P277 -> 0 | F8: ='Evaluation-transfer'!Q277 -> 0.5 | G8: ='Evaluation-transfer'!R277 -> 0 | H8: ='Evaluation-transfer'!S277 -> 0.33333333 | I8: ='Evaluation-transfer'!T277 -> 0.8 | J8: ='Evaluation-transfer'!U277 -> 0.5 | ... M8: ='Evaluation-transfer'!X277 -> 3.1166667 | O8: =A8 -> P6 | P8: =B8 -> Third Tier | Q8: ='Evaluation-transfer'!AC277 -> 0.33333333 | R8: ='Evaluation-transfer'!AD277 -> 0.25 | S8: ='Evaluation-transfer'!AE277 -> 0 | T8: ='Evaluation-transfer'!AF277 -> 0.5 | U8: ='Evaluation-transfer'!AG277 -> 0 | V8: ='Evaluation-transfer'!AH277 -> 0.66666667 | W8: ='Evaluation-transfer'!AI277 -> 0.8 | X8: ='Evaluation-transfer'!AJ277 -> 0.5 | ... AA8: ='Evaluation-transfer'!AM277 -> 3.45
A9: =machine_learning!C9 -> P7 | B9: =machine_learning!E9 -> Third Tier | C9: ='Evaluation-transfer'!N278 -> 0.33333333 | D9: ='Evaluation-transfer'!O278 -> 0.25 | E9: ='Evaluation-transfer'!P278 -> 0 | F9: ='Evaluation-transfer'!Q278 -> 0.5 | G9: ='Evaluation-transfer'!R278 -> 0.8 | H9: ='Evaluation-transfer'!S278 -> 0.66666667 | I9: ='Evaluation-transfer'!T278 -> 0 | J9: ='Evaluation-transfer'!U278 -> 0 | ... M9: ='Evaluation-transfer'!X278 -> 2.55 | O9: =A9 -> P7 | P9: =B9 -> Third Tier | Q9: ='Evaluation-transfer'!AC278 -> 0.33333333 | R9: ='Evaluation-transfer'!AD278 -> 0.25 | S9: ='Evaluation-transfer'!AE278 -> 0 | T9: ='Evaluation-transfer'!AF278 -> 0.5 | U9: ='Evaluation-transfer'!AG278 -> 1.6 | V9: ='Evaluation-transfer'!AH278 -> 1.3333333 | W9: ='Evaluation-transfer'!AI278 -> 0 | X9: ='Evaluation-transfer'!AJ278 -> 0 | ... AA9: ='Evaluation-transfer'!AM278 -> 4.0166667
A10: =machine_learning!C10 -> P8 | B10: =machine_learning!E10 -> Second Tier | C10: ='Evaluation-transfer'!N279 -> 0.33333333 | D10: ='Evaluation-transfer'!O279 -> 0.25 | E10: ='Evaluation-transfer'!P279 -> 0.66666667 | F10: ='Evaluation-transfer'!Q279 -> 0.5 | G10: ='Evaluation-transfer'!R279 -> 0.8 | H10: ='Evaluation-transfer'!S279 -> 0.66666667 | I10: ='Evaluation-transfer'!T279 -> 1 | J10: ='Evaluation-transfer'!U279 -> 0.5 | ... M10: ='Evaluation-transfer'!X279 -> 6.1166667 | O10: =A10 -> P8 | P10: =B10 -> Second Tier | Q10: ='Evaluation-transfer'!AC279 -> 0.33333333 | R10: ='Evaluation-transfer'!AD279 -> 0.25 | S10: ='Evaluation-transfer'!AE279 -> 1.3333333 | T10: ='Evaluation-transfer'!AF279 -> 0.5 | U10: ='Evaluation-transfer'!AG279 -> 1 | V10: ='Evaluation-transfer'!AH279 -> 2.3333333 | W10: ='Evaluation-transfer'!AI279 -> 1.4 | X10: ='Evaluation-transfer'!AJ279 -> 0.5 | ... AA10: ='Evaluation-transfer'!AM279 -> 9.05
A11: =machine_learning!C11 -> P9 | B11: =machine_learning!E11 -> Third Tier | C11: ='Evaluation-transfer'!N280 -> 0.33333333 | D11: ='Evaluation-transfer'!O280 -> 0.25 | E11: ='Evaluation-transfer'!P280 -> 0.66666667 | F11: ='Evaluation-transfer'!Q280 -> 0.5 | G11: ='Evaluation-transfer'!R280 -> 1 | H11: ='Evaluation-transfer'!S280 -> 0.33333333 | I11: ='Evaluation-transfer'!T280 -> 0.6 | J11: ='Evaluation-transfer'!U280 -> 0.5 | ... M11: ='Evaluation-transfer'!X280 -> 5.1833333 | O11: =A11 -> P9 | P11: =B11 -> Third Tier | Q11: ='Evaluation-transfer'!AC280 -> 0.33333333 | R11: ='Evaluation-transfer'!AD280 -> 0.25 | S11: ='Evaluation-transfer'!AE280 -> 1 | T11: ='Evaluation-transfer'!AF280 -> 0.5 | U11: ='Evaluation-transfer'!AG280 -> 1.8 | V11: ='Evaluation-transfer'!AH280 -> 0.33333333 | W11: ='Evaluation-transfer'!AI280 -> 0.6 | X11: ='Evaluation-transfer'!AJ280 -> 0.5 | ... AA11: ='Evaluation-transfer'!AM280 -> 6.3166667
A12: =machine_learning!C12 -> P10 | B12: =machine_learning!E12 -> Second Tier | C12: ='Evaluation-transfer'!N281 -> 0.33333333 | D12: ='Evaluation-transfer'!O281 -> 0.25 | E12: ='Evaluation-transfer'!P281 -> 0.33333333 | F12: ='Evaluation-transfer'!Q281 -> 0.5 | G12: ='Evaluation-transfer'!R281 -> 1 | H12: ='Evaluation-transfer'!S281 -> 0.66666667 | I12: ='Evaluation-transfer'!T281 -> 0.2 | J12: ='Evaluation-transfer'!U281 -> 0 | ... M12: ='Evaluation-transfer'!X281 -> 4.4833333 | O12: =A12 -> P10 | P12: =B12 -> Second Tier | Q12: ='Evaluation-transfer'!AC281 -> 0.33333333 | R12: ='Evaluation-transfer'!AD281 -> 0.25 | S12: ='Evaluation-transfer'!AE281 -> 0.33333333 | T12: ='Evaluation-transfer'!AF281 -> 1 | U12: ='Evaluation-transfer'!AG281 -> 1.6 | V12: ='Evaluation-transfer'!AH281 -> 0.66666667 | W12: ='Evaluation-transfer'!AI281 -> 0.2 | X12: ='Evaluation-transfer'!AJ281 -> 0 | ... AA12: ='Evaluation-transfer'!AM281 -> 6.5833333
A13: =machine_learning!C13 -> P11 | B13: =machine_learning!E13 -> First Tier | C13: ='Evaluation-transfer'!N282 -> 0.33333333 | D13: ='Evaluation-transfer'!O282 -> 0.25 | E13: ='Evaluation-transfer'!P282 -> 0 | F13: ='Evaluation-transfer'!Q282 -> 0.5 | G13: ='Evaluation-transfer'!R282 -> 0.6 | H13: ='Evaluation-transfer'!S282 -> 0.66666667 | I13: ='Evaluation-transfer'!T282 -> 0.4 | J13: ='Evaluation-transfer'!U282 -> 0 | ... M13: ='Evaluation-transfer'!X282 -> 2.75 | O13: =A13 -> P11 | P13: =B13 -> First Tier | Q13: ='Evaluation-transfer'!AC282 -> 0.33333333 | R13: ='Evaluation-transfer'!AD282 -> 0.25 | S13: ='Evaluation-transfer'!AE282 -> 0 | T13: ='Evaluation-transfer'!AF282 -> 0.5 | U13: ='Evaluation-transfer'!AG282 -> 0.6 | V13: ='Evaluation-transfer'!AH282 -> 1 | W13: ='Evaluation-transfer'!AI282 -> 0.4 | X13: ='Evaluation-transfer'!AJ282 -> 0 | ... AA13: ='Evaluation-transfer'!AM282 -> 3.0833333
... A43: =machine_learning!C43 -> P41 | B43: =machine_learning!E43 -> Third Tier | C43: ='Evaluation-transfer'!N312 -> 0.33333333 | D43: ='Evaluation-transfer'!O312 -> 0.25 | E43: ='Evaluation-transfer'!P312 -> 0.33333333 | F43: ='Evaluation-transfer'!Q312 -> 0.5 | G43: ='Evaluation-transfer'!R312 -> 0.2 | H43: ='Evaluation-transfer'!S312 -> 0.66666667 | I43: ='Evaluation-transfer'!T312 -> 0.6 | J43: ='Evaluation-transfer'!U312 -> 0.5 | ... M43: ='Evaluation-transfer'!X312 -> 3.7833333 | O43: =A43 -> P41 | P43: =B43 -> Third Tier | Q43: ='Evaluation-transfer'!AC312 -> 0.33333333 | R43: ='Evaluation-transfer'!AD312 -> 0.25 | S43: ='Evaluation-transfer'!AE312 -> 0.33333333 | T43: ='Evaluation-transfer'!AF312 -> 0.5 | U43: ='Evaluation-transfer'!AG312 -> 0.2 | V43: ='Evaluation-transfer'!AH312 -> 1.3333333 | W43: ='Evaluation-transfer'!AI312 -> 0.6 | X43: ='Evaluation-transfer'!AJ312 -> 0.5 | ... AA43: ='Evaluation-transfer'!AM312 -> 4.45
B46: 行标签 | C46: 平均值项:X1 | D46: 平均值项:X2 | E46: 平均值项:X3 | F46: 平均值项:X4 | G46: 平均值项:X5 | H46: 平均值项:X6 | I46: 平均值项:X7 | J46: 平均值项:X8 | K46: 平均值项:X9 | L46: 平均值项:X10 | P46: 行标签 | Q46: 平均值项:X1 | R46: 平均值项:X2 | S46: 平均值项:X3 | T46: 平均值项:X4 | U46: 平均值项:X5 | V46: 平均值项:X6 | W46: 平均值项:X7 | X46: 平均值项:X8 | Y46: 平均值项:X9 | Z46: 平均值项:X10
B47: First Tier | C47: 0.33333333 | D47: 0.3125 | E47: 0.16666667 | F47: 0.375 | G47: 0.65 | H47: 0.75 | I47: 0.3 | J47: 0.125 | K47: 0.2 | L47: 0 | P47: First Tier | Q47: 0.33333333 | R47: 0.3125 | S47: 0.33333333 | T47: 0.375 | U47: 0.8 | V47: 0.91666667 | W47: 0.35 | X47: 0.125 | Y47: 0.25 | Z47: 0
B48: Second Tier | C48: 0.30769231 | D48: 0.23076923 | E48: 0.43589744 | F48: 0.42307692 | G48: 0.81538462 | H48: 0.71794872 | I48: 0.36923077 | J48: 0.076923077 | K48: 0.18461538 | L48: 0.38461538 | P48: Second Tier | Q48: 0.30769231 | R48: 0.26923077 | S48: 0.69230769 | T48: 0.5 | U48: 1.1538462 | V48: 1.1794872 | W48: 0.55384615 | X48: 0.076923077 | Y48: 0.18461538 | Z48: 0.46153846
B49: Third Tier | C49: 0.34722222 | D49: 0.22916667 | E49: 0.27777778 | F49: 0.47916667 | G49: 0.58333333 | H49: 0.5 | I49: 0.49166667 | J49: 0.14583333 | K49: 0.24166667 | L49: 0.20833333 | P49: Third Tier | Q49: 0.34722222 | R49: 0.22916667 | S49: 0.38888889 | T49: 0.47916667 | U49: 0.71666667 | V49: 0.80555556 | W49: 0.59166667 | X49: 0.14583333 | Y49: 0.25833333 | Z49: 0.20833333
B50: 总计 | C50: 0.33333333 | D50: 0.23780488 | E50: 0.31707317 | F50: 0.45121951 | G50: 0.66341463 | H50: 0.59349593 | I50: 0.43414634 | J50: 0.12195122 | K50: 0.2195122 | L50: 0.24390244 | P50: 总计 | Q50: 0.33333333 | R50: 0.25 | S50: 0.4796748 | T50: 0.47560976 | U50: 0.86341463 | V50: 0.93495935 | W50: 0.55609756 | X50: 0.12195122 | Y50: 0.23414634 | Z50: 0.26829268

Sheet 房地产销售面积
B3: 指标 | C3: 45413 | D3: 45383 | E3: 45352 | F3: 45323 | G3: 45292 | H3: 45261 | I3: 45231 | J3: 45200 | K3: 45170 | L3: 45139 | M3: 45108 | N3: 45078 | O3: 45047 | P3: 45017 | Q3: 44986 | R3: 44958 | S3: 44927 | T3: 44896 | U3: 44866 | V3: 44835 | W3: 44805 | X3: 44774 | Y3: 44743 | Z3: 44713 | AA3: 44682 | AB3: 44652 | AC3: 44621 | AD3: 44593 | AE3: 44562 | AF3: 44531 | AG3: 44501 | AH3: 44470 | AI3: 44440 | AJ3: 44409 | AK3: 44378 | AL3: 44348
B4: 商品住宅销售面积
B5: 累计值(万平方米) | C5: 30744.16 | D5: 24507.14 | E5: 18941.9 | F5: 9558.82 | H5: 94796.35 | I5: 85964.5 | J5: 79385.98 | K5: 72769.59 | L5: 63811.11 | M5: 57622.54 | N5: 51592.34 | O5: 40663.17 | P5: 32965.87 | Q5: 26251.39 | R5: 13387.18 | T5: 114630.65 | U5: 102726.84 | V5: 94129.37 | W5: 85758.17 | X5: 74402.56 | Y5: 66087.03 | Z5: 58056.89 | AA5: 42902.6 | AB5: 33721.72 | AC5: 26304.59 | AD5: 13462.26 | AF5: 156532.17 | AG5: 139156.19 | AH5: 126419.25 | AI5: 115431.87 | AJ5: 101606.71 | AK5: 90597.93 | AL5: 79081.42
B6: 商品住宅销售面积
B7: 累计增长(%) | C7: -23.6 | D7: -23.8 | E7: -23.4 | F7: -24.8 | H7: -8.2 | I7: -7.3 | J7: -6.8 | K7: -6.3 | L7: -5.5 | M7: -4.3 | N7: -2.8 | O7: 2.3 | P7: 2.7 | Q7: 1.4 | R7: -0.6 | T7: -26.8 | U7: -26.2 | V7: -25.5 | W7: -25.7 | X7: -26.8 | Y7: -27.1 | Z7: -26.6 | AA7: -28.1 | AB7: -25.4 | AC7: -18.6 | AD7: -13.8 | AF7: 1.1 | AG7: 4.4 | AH7: 7.1 | AI7: 11.4 | AJ7: 16.5 | AK7: 22.7 | AL7: 29.4
B8: 商品住宅现房销售面积
B9: 累计值(万平方米) | C9: 8239.06 | D9: 6594.56 | E9: 5095.59 | F9: 2530.27 | H9: 17765.24 | I9: 15643.06 | J9: 14297.21 | K9: 12992.43 | L9: 11105.61 | M9: 9859.96 | N9: 8715.02 | O9: 6729.16 | P9: 5528.71 | Q9: 4455.69 | R9: 2174.7 | T9: 15974.38 | U9: 14010.42 | V9: 12916.77 | W9: 11818.09 | X9: 10284.7 | Y9: 9157.69 | Z9: 8083.33 | AA9: 5699.66 | AB9: 4439.28 | AC9: 3446.67 | AD9: 1812.26 | AF9: 16356.74 | AG9: 13976.18 | AH9: 12452.23 | AI9: 11270.76 | AJ9: 9691.05 | AK9: 8635.87 | AL9: 7502.96
B10: 商品住宅现房销售面积
B11: 累计增长(%) | C11: 23.8 | D11: 22.6 | E11: 21.2 | F11: 22.3 | H11: 22.7 | I11: 23.2 | J11: 21.9 | K11: 21.2 | L11: 18.8 | M11: 17.9 | N11: 17.5 | O11: 26.5 | P11: 30.5 | Q11: 30.3 | R11: 20 | T11: -2.3 | U11: 0.2 | V11: 3.7 | W11: 4.9 | X11: 6.1 | Y11: 6 | Z11: 7.7 | AA11: 4 | AB11: 5.3 | AC11: 13.3 | AD11: 17.1 | AF11: 3.9 | AG11: 4.1 | AH11: 5.4 | AI11: 8.2 | AJ11: 10 | AK11: 13.7 | AL11: 17.5
B12: 商品住宅期房销售面积
B13: 累计值(万平方米) | C13: 22505.1 | D13: 17912.59 | E13: 13846.31 | F13: 7028.55 | H13: 77031.11 | I13: 70321.44 | J13: 65088.77 | K13: 59777.16 | L13: 52705.5 | M13: 47762.57 | N13: 42877.32 | O13: 33934.01 | P13: 27437.16 | Q13: 21795.71 | R13: 11212.48 | T13: 98656.28 | U13: 88716.42 | V13: 81212.6 | W13: 73940.08 | X13: 64117.86 | Y13: 56929.34 | Z13: 49973.56 | AA13: 37202.93 | AB13: 29282.44 | AC13: 22857.92 | AD13: 11650 | AF13: 140175.43 | AG13: 125180.01 | AH13: 113967.02 | AI13: 104161.11 | AJ13: 91915.67 | AK13: 81962.06 | AL13: 71578.46
B14: 商品住宅期房销售面积
B17: 指标 | C17: 45413 | D17: 45383 | E17: 45352 | F17: 45323 | G17: 45261 | H17: 45231 | I17: 45200 | J17: 45170 | K17: 45139 | L17: 45108 | M17: 45078 | N17: 45047 | O17: 45017 | P17: 44986 | Q17: 44958 | R17: 44896 | S17: 44866 | T17: 44835 | U17: 44805 | V17: 44774 | W17: 44743 | X17: 44713 | Y17: 44682 | Z17: 44652 | AA17: 44621 | AB17: 44593 | AC17: 44531 | AD17: 44501 | AE17: 44470 | AF17: 44440 | AG17: 44409 | AH17: 44378 | AI17: 44348
B18: 商品住宅施工面积
B19: 累计值(万平方米) | C19: 481557.1 | D19: 480646.6 | E19: 474580.41 | F19: 466635.99 | G19: 589884.26 | H19: 585309.35 | I19: 579361.46 | J19: 574249.97 | K19: 567791.72 | L19: 563025.82 | M19: 557083.19 | N19: 548474.66 | O19: 542968.14 | P19: 538214.33 | Q19: 527695.21 | R19: 639695.94 | S19: 633915.74 | T19: 628277.72 | U19: 621201.24 | V19: 613604.38 | W19: 607028.94 | X19: 599429.46 | Y19: 586918.32 | Z19: 577691.56 | AA19: 569044.86 | AB19: 553513.53 | AC19: 690319.37 | AD19: 679539.72 | AE19: 667801.09 | AF19: 656884.07 | AG19: 644335.62 | AH19: 631071.97 | AI19: 617479.66
B20: 商品住宅施工面积
B21: 累计增长(%) | C21: -12.2 | D21: -11.4 | E21: -11.7 | F21: -11.4 | G21: -7.7 | H21: -7.6 | I21: -7.7 | J21: -7.4 | K21: -7.3 | L21: -7.1 | M21: -6.9 | N21: -6.5 | O21: -5.9 | P21: -5.4 | Q21: -4.7 | R21: -7.3 | S21: -6.7 | T21: -5.9 | U21: -5.4 | V21: -4.8 | W21: -3.8 | X21: -2.9 | Y21: -1.1 | Z21: -0.1 | AA21: 1.1 | AB21: 2 | AC21: 5.3 | AD21: 6.5 | AE21: 7.4 | AF21: 8.2 | AG21: 8.8 | AH21: 9.4 | AI21: 10.5
B22: 商品住宅新开工施工面积
B23: 累计值(万平方米) | C23: 21759.93 | D23: 17005.67 | E23: 12534.02 | F23: 6795.71 | G23: 69285.61 | H23: 63737.03 | I23: 57658.9 | J23: 52511.64 | K23: 46636.07 | L23: 41546.49 | M23: 36339.64 | N23: 29009.79 | O23: 22899.88 | P23: 17719.09 | Q23: 9891.04 | R23: 88135.08 | S23: 81734.35 | T23: 75934.15 | U23: 69482.75 | V23: 62413.69 | W23: 55918.75 | X23: 48800.48 | Y23: 37782.31 | Z23: 28876.56 | AA23: 21558.38 | AB23: 10835.67 | AC23: 146378.56 | AD23: 135017.36 | AE23: 123480.57 | AF23: 113374.46 | AG23: 100765.33 | AH23: 88473.99 | AI23: 75514.87
B24: 商品住宅新开工施工面积
B25: 累计增长(%) | C25: -25 | D25: -25.6 | E25: -28.7 | F25: -30.6 | G25: -20.9 | H25: -21.5 | I25: -23.6 | J25: -23.9 | K25: -24.7 | L25: -25 | M25: -24.9 | N25: -22.7 | O25: -20.6 | P25: -17.8 | Q25: -8.7 | R25: -39.8 | S25: -39.5 | T25: -38.5 | U25: -38.7 | V25: -38.1 | W25: -36.8 | X25: -35.4 | Y25: -31.9 | Z25: -28.4 | AA25: -20.3 | AB25: -14.9 | AC25: -10.9 | AD25: -8.4 | AE25: -6.8 | AF25: -3.3 | AG25: -1.7 | AH25: 0.4 | AI25: 5.5
B26: 商品住宅竣工面积
B27: 累计值(万平方米) | C27: 16199.37 | D27: 13745.79 | E27: 11147.95 | F27: 7694 | G27: 72432.59 | H27: 47580.71 | I27: 40079.28 | J27: 35319.34 | K27: 31775.39 | L27: 27953.67 | M27: 24603.62 | N27: 20194.33 | O27: 17395.98 | P27: 14395.91 | Q27: 9781.5 | R27: 62539.25 | S27: 40441.54 | T27: 33771.43 | U27: 29595.36 | V27: 26737.46 | W27: 23279.5 | X27: 20858.26 | Y27: 17049.73 | Z27: 14661.72 | AA27: 12322.65 | AB27: 8914.78 | AC27: 73016.2 | AD27: 49582.28 | AE27: 41415.46 | AF27: 36816.18 | AG27: 33771.05 | AH27: 30125.2 | AI27: 26253.82
B28: 商品住宅竣工面积 | C28: =C27 -> 16199.37 | G28: =G27-H27 -> 24851.88 | AA28: =AA27 -> 12322.65
B36: 45413 | C36: 45078 | D36: 竣备 | E36: =C27+N27 -> 36393.7
B37: 44531 | C37: 44896 | D37: 销售 | E37: =T13 -> 98656.28 | F37: =E36/E37 -> 0.3688939

Sheet matrix
B1: 白沙县 | C1: 北海市 | D1: 北京市 | E1: 澄迈县 | F1: 儋州市 | G1: 定安县 | H1: 东方市 | I1: 东莞 | J1: 东营市 | K1: 佛山市 | L1: 广州市 | M1: 海口市 | N1: 合肥市 | O1: 惠州 | P1: 九江市 | Q1: 兰州 | R1: 乐东县 | S1: 乐山市 | T1: 丽水市 | U1: 临高 | V1: 陵水 | W1: 六安 | X1: 清远市 | Y1: 琼海市 | Z1: 琼中县 | AA1: 汕头市2 | AB1: 上海 | AC1: 上饶 | AD1: 韶关 | AE1: 深圳市 | AF1: 万宁市 | AG1: 文昌市 | AH1: 五指山 | AI1: 信阳市 | AJ1: 义乌 | AK1: 肇庆市 | AL1: 中山 | AM1: 中卫 | AN1: 珠海市 | AO1: 屯昌县 | AP1: 昌江县
A2: 1 : code | B2: 10 | C2: 12 | D2: 20 | E2: 14 | F2: 12 | G2: 9 | H2: 15 | I2: 17 | J2: 13 | K2: 15 | L2: 12 | M2: 6 | N2: 10 | O2: 15 | P2: 26 | Q2: 13 | R2: 2 | S2: 15 | T2: 11 | U2: 14 | V2: 10 | W2: 10 | X2: 16 | Y2: 7 | Z2: 18 | AA2: 18 | AB2: 7 | AC2: 14 | AD2: 10 | AE2: 8 | AF2: 15 | AG2: 12 | AH2: 8 | AI2: 9 | AJ2: 12 | AK2: 15 | AL2: 24 | AM2: 18 | AN2: 12 | AO2: 8 | AP2: 8
A3: 2 : X1 Policy issuing agency | B3: 1 | C3: 1 | D3: 1 | E3: 1 | F3: 1 | G3: 1 | H3: 1 | I3: 1 | J3: 1 | K3: 1 | L3: 1 | M3: 0 | N3: 1 | O3: 1 | P3: 1 | Q3: 1 | R3: 1 | S3: 1 | T3: 1 | U3: 1 | V3: 2 | W3: 1 | X3: 1 | Y3: 1 | Z3: 1 | AA3: 1 | AB3: 1 | AC3: 1 | AD3: 1 | AE3: 1 | AF3: 1 | AG3: 1 | AH3: 1 | AI3: 1 | AJ3: 1 | AK3: 1 | AL3: 1 | AM3: 1 | AN3: 1 | AO3: 1 | AP3: 1
A4: 3 : X1.1 Provinces | B4: 0 | C4: 0 | D4: 1 | E4: 0 | F4: 0 | G4: 1 | H4: 0 | I4: 0 | J4: 0 | K4: 0 | L4: 0 | M4: 0 | N4: 0 | O4: 0 | P4: 0 | Q4: 0 | R4: 0 | S4: 0 | T4: 1 | U4: 1 | V4: 1 | W4: 0 | X4: 0 | Y4: 0 | Z4: 0 | AA4: 0 | AB4: 0 | AC4: 0 | AD4: 0 | AE4: 0 | AF4: 0 | AG4: 1 | AH4: 1 | AI4: 0 | AJ4: 1 | AK4: 0 | AL4: 0 | AM4: 0 | AN4: 0 | AO4: 1 | AP4: 1
A5: 4 : X1.2 Cities | B5: 0 | C5: 1 | D5: 0 | E5: 0 | F5: 1 | G5: 0 | H5: 0 | I5: 1 | J5: 1 | K5: 1 | L5: 1 | M5: 0 | N5: 1 | O5: 1 | P5: 1 | Q5: 1 | R5: 0 | S5: 1 | T5: 0 | U5: 0 | V5: 1 | W5: 1 | X5: 1 | Y5: 1 | Z5: 0 | AA5: 1 | AB5: 1 | AC5: 1 | AD5: 1 | AE5: 1 | AF5: 0 | AG5: 0 | AH5: 0 | AI5: 1 | AJ5: 0 | AK5: 1 | AL5: 1 | AM5: 1 | AN5: 1 | AO5: 0 | AP5: 0
A6: 5 : X1.3 Country-level cities | B6: 1 | C6: 0 | D6: 0 | E6: 1 | F6: 0 | G6: 0 | H6: 1 | I6: 0 | J6: 0 | K6: 0 | L6: 0 | M6: 0 | N6: 0 | O6: 0 | P6: 0 | Q6: 0 | R6: 1 | S6: 0 | T6: 0 | U6: 0 | V6: 0 | W6: 0 | X6: 0 | Y6: 0 | Z6: 1 | AA6: 0 | AB6: 0 | AC6: 0 | AD6: 0 | AE6: 0 | AF6: 1 | AG6: 0 | AH6: 0 | AI6: 0 | AJ6: 0 | AK6: 0 | AL6: 0 | AM6: 0 | AN6: 0 | AO6: 0 | AP6: 0
A7: 6 : X1.4 Level unknown | B7: 0 | C7: 0 | D7: 0 | E7: 0 | F7: 0 | G7: 0 | H7: 0 | I7: 0 | J7: 0 | K7: 0 | L7: 0 | M7: 0 | N7: 0 | O7: 0 | P7: 0 | Q7: 0 | R7: 0 | S7: 0 | T7: 0 | U7: 0 | V7: 0 | W7: 0 | X7: 0 | Y7: 0 | Z7: 0 | AA7: 0 | AB7: 0 | AC7: 0 | AD7: 0 | AE7: 0 | AF7: 0 | AG7: 0 | AH7: 0 | AI7: 0 | AJ7: 0 | AK7: 0 | AL7: 0 | AM7: 0 | AN7: 0 | AO7: 0 | AP7: 0
A8: 7 : X10信用等级分类 | B8: 0 | C8: 0 | D8: 0 | E8: 0 | F8: 0 | G8: 0 | H8: 0 | I8: 1 | J8: 1 | K8: 2 | L8: 0 | M8: 0 | N8: 0 | O8: 0 | P8: 0 | Q8: 1 | R8: 0 | S8: 1 | T8: 0 | U8: 0 | V8: 0 | W8: 0 | X8: 1 | Y8: 0 | Z8: 0 | AA8: 0 | AB8: 0 | AC8: 0 | AD8: 1 | AE8: 0 | AF8: 0 | AG8: 0 | AH8: 0 | AI8: 0 | AJ8: 0 | AK8: 1 | AL8: 1 | AM8: 1 | AN8: 0 | AO8: 0 | AP8: 0
A9: 8 : x2 Policy timeliness | B9: 0 | C9: 1 | D9: 1 | E9: 1 | F9: 1 | G9: 1 | H9: 1 | I9: 1 | J9: 1 | K9: 1 | L9: 1 | M9: 0 | N9: 2 | O9: 1 | P9: 1 | Q9: 1 | R9: 1 | S9: 1 | T9: 1 | U9: 1 | V9: 1 | W9: 1 | X9: 1 | Y9: 1 | Z9: 1 | AA9: 1 | AB9: 1 | AC9: 1 | AD9: 0 | AE9: 2 | AF9: 1 | AG9: 1 | AH9: 1 | AI9: 1 | AJ9: 2 | AK9: 1 | AL9: 1 | AM9: 1 | AN9: 1 | AO9: 1 | AP9: 1
A10: 9 : X2.1Short term 1-3years | B10: 0 | C10: 0 | D10: 0 | E10: 0 | F10: 1 | G10: 0 | H10: 0 | I10: 0 | J10: 0 | K10: 0 | L10: 0 | M10: 0 | N10: 2 | O10: 0 | P10: 0 | Q10: 0 | R10: 0 | S10: 0 | T10: 0 | U10: 0 | V10: 0 | W10: 0 | X10: 0 | Y10: 0 | Z10: 1 | AA10: 1 | AB10: 0 | AC10: 0 | AD10: 0 | AE10: 1 | AF10: 0 | AG10: 0 | AH10: 0 | AI10: 0 | AJ10: 0 | AK10: 0 | AL10: 0 | AM10: 0 | AN10: 1 | AO10: 0 | AP10: 0
A11: 10 : X2.2中期3-5年 | B11: 0 | C11: 0 | D11: 0 | E11: 0 | F11: 0 | G11: 0 | H11: 1 | I11: 1 | J11: 1 | K11: 1 | L11: 0 | M11: 0 | N11: 0 | O11: 1 | P11: 0 | Q11: 1 | R11: 0 | S11: 0 | T11: 0 | U11: 0 | V11: 0 | W11: 0 | X11: 1 | Y11: 0 | Z11: 0 | AA11: 0 | AB11: 0 | AC11: 0 | AD11: 0 | AE11: 0 | AF11: 0 | AG11: 0 | AH11: 0 | AI11: 0 | AJ11: 0 | AK11: 0 | AL11: 1 | AM11: 1 | AN11: 0 | AO11: 0 | AP11: 0
A12: 11 : X2.3长期大于5年 | B12: 0 | C12: 0 | D12: 1 | E12: 0 | F12: 0 | G12: 0 | H12: 0 | I12: 0 | J12: 0 | K12: 0 | L12: 0 | M12: 0 | N12: 0 | O12: 0 | P12: 0 | Q12: 0 | R12: 0 | S12: 1 | T12: 0 | U12: 0 | V12: 0 | W12: 0 | X12: 0 | Y12: 0 | Z12: 0 | AA12: 0 | AB12: 1 | AC12: 0 | AD12: 0 | AE12: 1 | AF12: 0 | AG12: 0 | AH12: 0 | AI12: 0 | AJ12: 0 | AK12: 0 | AL12: 0 | AM12: 0 | AN12: 0 | AO12: 0 | AP12: 0
A13: 12 : X2.4无或不详时限 | B13: 0 | C13: 1 | D13: 0 | E13: 1 | F13: 0 | G13: 1 | H13: 0 | I13: 0 | J13: 0 | K13: 0 | L13: 1 | M13: 0 | N13: 0 | O13: 0 | P13: 1 | Q13: 0 | R13: 1 | S13: 0 | T13: 1 | U13: 1 | V13: 1 | W13: 1 | X13: 0 | Y13: 1 | Z13: 0 | AA13: 0 | AB13: 0 | AC13: 1 | AD13: 0 | AE13: 0 | AF13: 1 | AG13: 1 | AH13: 1 | AI13: 1 | AJ13: 2 | AK13: 1 | AL13: 0 | AM13: 0 | AN13: 0 | AO13: 1 | AP13: 1
... A47: 46 : 总包结算款支付保障 | B47: 0 | C47: 0 | D47: 0 | E47: 0 | F47: 0 | G47: 0 | H47: 0 | I47: 0 | J47: 0 | K47: 0 | L47: 0 | M47: 0 | N47: 0 | O47: 0 | P47: 0 | Q47: 0 | R47: 0 | S47: 0 | T47: 0 | U47: 0 | V47: 0 | W47: 0 | X47: 0 | Y47: 0 | Z47: 0 | AA47: 0 | AB47: 0 | AC47: 0 | AD47: 0 | AE47: 0 | AF47: 0 | AG47: 0 | AH47: 0 | AI47: 0 | AJ47: 0 | AK47: 1 | AL47: 0 | AM47: 0 | AN47: 0 | AO47: 0 | AP47: 0

Sheet Previous studies
A1: Estrada,2011 | E1: Wang et al., 2024 | I1: Cheng et al., 2023 | M1: Xiong et al.,2023
A2: Primary variables | C2: Secondary variables | E2: Primary variables | G2: Secondary variables | I2: Primary variables | K2: Secondary variables | M2: Primary variables | O2: Secondary variables
A3: X1: Type of research | B3: X1.1 | C3: Predicting | E3: X1: Policy Nature | F3: X1.1 | G3: Predicting | I3: X1: Policy Nature | J3: X1.1 | K3: Predictive assessment | M3: X1: Policy Nature | N3: X1.1 | O3: Projection
B4: X1.2 | C4: Monitoring | F4: X1.2 | G4: Suggention | J4: X1.2 | K4: Supervisory management | N4: X1.2 | O4: Regulation
B5: X1.3 | C5: Proposal | F5: X1.3 | G5: Supervision | J5: X1.3 | K5: Mandatory requirement | N5: X1.3 | O5: Suggestion
B6: X1.4 | C6: Descriptive | F6: X1.4 | G6: Guidance | J6: X1.4 | K6: Encouraging guidance | N6: X1.4 | O6: Support
B7: X1.5 | C7: Diagnostic | F7: X1.5 | G7: Feedback | N7: X1.5 | O7: Guidance
B8: X1.6 | C8: Simulation
B9: X1.7 | C9: Experimental
A10: X2: Research orientation | B10: X2.1 | C10: Empirical | E10: X2: Policy timeline | F10: X2.1 | G10: Long-term | I10: X2: Policy timeline | J10: X2.1 | K10: Long-term | M10: X2: Policy Issuing Agency | N10: X2.1 | O10: State Council of PRC
B11: X2.2 | C11: Theoretical | F11: X2.2 | G11: Medium-term | J11: X2.2 | K11: Medium-term | N11: X2.2 | O11: Ministries and Commissions of the State Council of the PRC
B12: X2.3 | C12: Technical | F12: X2.3 | G12: Short-term | J12: X2.3 | K12: Short-term | N12: X2.3 | O12: Multi-agency joint issue
B13: X2.4 | C13: Historical
B14: X2.5 | C14: Quantitative
B15: X2.6 | C15: Qualitative
A16: X3: Date source | B16: X3.1 | C16: Primary data | E16: X3: Policy perspective | F16: X3.1 | G16: Macro | I16: X3: Policy area | J16: X3.1 | K16: Economy | M16: X3: Policy Object | N16: X3.1 | O16: Government
B17: X3.2 | C17: Secondary data | F17: X3.2 | G17: Micrio | J17: X3.2 | K17: Society | N17: X3.2 | O17: Emergency management department
B18: X3.3 | C18: Mix data | J18: X3.3 | K18: Technology | N18: X3.3 | O18: Fire rescue agency
B19: X3.4 | C19: Long term | J19: X3.4 | K19: Environment | N19: X3.4 | O19: Social unit and workshop
B20: X3.5 | C20: Medium term
B21: X3.6 | C21: Short term
A22: X4: Applied Econometrics methods | B22: X4.1 | C22: Linear regression analysis | E22: X4: Policy issuing agency | F22: X4.1 | G22: State council | I22: X4: Policy content | J22: X4.1 | K22: Reform and development planning | M22: X4: Policy Timeliness | N22: X4.1 | O22: Long-term (More than 5 years)
B23: X4.2 | C23: Multiple regression analysis | F23: X4.2 | G23: Ministries and Commissions of the State Council | J23: X4.2 | K23: Safety production management | N23: X4.2 | O23: Medium-term(3-5 years)
B24: X4.3 | C24: Time series data | F24: X4.3 | G24: Provinces and cities | J24: X4.3 | K24: Project engineering construction | N24: X4.3 | O24: Short-term(1-3 years)
B25: X4.4 | C25: Cross-sectional data | J25: X4.4 | K25: Supply guarantee mechanism | N25: X4.4 | O25: Within 1years
B26: X4.5 | C26: Panel data | J26: X4.5 | K26: Market trading principle
B27: X4.6 | C27: Multidimensional panel data | J27: X4.6 | K27: Development and utilisation state
A28: X5: Area of research | B28: X5.1 | C28: Economics | E28: X5: Policy focus | F28: X5.1 | G28: Ecological protection | I28: X5: Issuing agency | J28: X5.1 | K28: National People's Congress and its Standing Committee | M28: X5: Policy Function | N28: X5.1 | O28: Improve public fire safety literacy
B29: X5.2 | C29: Social | F29: X5.2 | G29: Pollution control | J29: X5.2 | K29: State Council | N29: X5.2 | O29: Reduce man-made fires
B30: X5.3 | C30: Technological | F30: X5.3 | G30: Water resource management | J30: X5.3 | K30: Ministries and Departments of the State Council | N30: X5.3 | O30: Promote social stability
B31: X5.4 | C31: Political | F31: X5.4 | G31: Biodiversity conservation | J31: X5.4 | K31: Directly under the State Council
B32: X5.5 | C32: Environment | F32: X5.5 | G32: Natural disaster prevention | J32: X5.5 | K32: National bureaus managed by Ministries and Department of the State Council
B33: X5.6 | C33: Institutional | F33: X5.6 | G33: Ecological compensation mechanism
B34: X5.7 | C34: Sciences
B35: X5.8 | C35: Multi-disciplinary
A36: X6: Research theoretical framework | B36: X6.1 | C36: Original theoretical framework | E36: X6: Regulation scope | F36: X6.1 | G36: Overall of the Yangtze River Economic Belt | I36: X6: Policy evaluation | J36: X6.1 | K36: Sufficient basis | M36: X6: Policy Tools | N36: X6.1 | O36: Compulsory type
B37: X6.2 | C37: Traditional theoretical framework | F37: X6.2 | G37: Some areas of the Yangtze River Economic Belt | J37: X6.2 | K37: Clear goals | N37: X6.2 | O37: Voluntary type
B38: X6.3 | C38: Extension of theoretical framework | J38: X6.3 | K38: Scientific planning | N38: X6.3 | O38: Mixed type
J39: X6.4 | K39: Detail content
A40: X7: Policy modeling by sectors | B40: X7.1 | C40: Private sector | E40: X7: Policy Object | F40: X7.1 | G40: Local government | I40: X7: Policy tools | J40: X7.1 | K40: Fiscal, taxation and finance | M40: X7: Policy Content | N40: X7.1 | O40: Fire safety education field
B41: X7.2 | C41: Public sector | F41: X7.2 | G41: Enterprise | J41: X7.2 | K41: Infrastructure construction | N41: X7.2 | O41: Fire safety education group
B42: X7.3 | C42: Public/private sector | F42: X7.3 | G42: Social organisation | J42: X7.3 | K42: Institutional norm | N42: X7.3 | O42: Fire safety education implementation pathway
F43: X7.4 | G43: Relevant department | J43: X7.4 | K43: Convenience service | N43: X7.4 | O43: Fire safety education infrastructure
J44: X7.5 | K44: goal planning | N44: X7.5 | O44: Fire safety education culture
A45: X8: Economics framework | B45: X8.1 | C45: Macroeconomics analysis | E45: X8: Policy tool | F45: X8.1 | G45: Organisational tools | I45: X8: Policy Object | J45: X8.1 | K45: Country | M45: X8: Policy Guarantee | N45: X8.1 | O45: Responsibility breakdown
B46: X8.2 | C46: Microeconomics analysis | F46: X8.2 | G46: Regulatory tools | J46: X8.2 | K46: Region | N46: X8.2 | O46: Financial support
B47: X8.3 | C47: Partial equilibrium | F47: X8.3 | G47: Inducement tools | J47: X8.3 | K47: Industry | N47: X8.3 | O47: Education team building
B48: X8.4 | C48: General equilibrium | F48: X8.4 | G48: Voluntary tools | J48: X8.4 | K48: Enterprise | N48: X8.4 | O48: Supervisor and inspection
B49: X8.5 | C49: Dynamic modeling | N49: X8.5 | O49: Reward and punishment
B50: X8.6 | C50: Static modeling
B51: X8.7 | C51: Perfect competition
B52: X8.8 | C52: Imperfect competition
A53: X9: Geographical analysis | B53: X9.1 | C53: National level | E53: X9: Policy evaluation | F53: X9.1 | G53: Sufficient basis | I53: X9: Policy potency | J53: X9.1 | K53: Laws | M53: X9: Policy Evaluation | N53: X9.1 | O53: Clear objectives
B54: X9.2 | C54: Regional level | F54: X9.2 | G54: Clear objectives | J54: X9.2 | K54: Administrative regulations | N54: X9.2 | O54: Adequate basis
B55: X9.3 | C55: Global level | F55: X9.3 | G55: Scientific program | J55: X9.3 | K55: Departmental rules | N55: X9.3 | O55: Detailed planning
F56: X9.4 | G56: Detail planning | J56: X9.4 | K56: Normative documents
A57: X10: Paper citation | I57: X10: Policy disclosure
A59: =COUNTA(C:C) -> 51 | E59: =COUNTA(G:G)-1 -> 33 | I59: =COUNTA(K:K) -> 40 | M59: =COUNTA(O:O) -> 36
A60: Count | E60: Count | I60: Count | M60: Count

Sheet VIPcric_1
M2: CRIC-万宁-市场监测.商品房市场.项目累计.供求.xlsx
A3: 时间(年) | B3: 供应面积(㎡) | C3: 供应套数(套) | D3: 成交面积(㎡) | E3: 成交套数(套) | F3: 成交均价(元/㎡) | G3: 成交金额(元) | H3: 供求比 | M3: CRIC-万宁-市场监测.商品房市场.项目累计.供求.xlsx
A4: 2024年 | B4: 13274 | C4: 146 | D4: 7451 | E4: 75 | F4: 16623 | G4: 123862588 | H4: 1.78 | M4: CRIC-万宁-市场监测.商品房市场.项目累计.供求.xlsx
A5: 2023年 | B5: 262195 | C5: 2349 | D5: 234882 | E5: 2494 | F5: 16309 | G5: 3830728567 | H5: 1.12 | M5: CRIC-万宁-市场监测.商品房市场.项目累计.供求.xlsx
A6: 2022年 | B6: 218718 | C6: 2268 | D6: 345964 | E6: 3441 | F6: 14794 | G6: 5118298089 | H6: 0.63 | M6: CRIC-万宁-市场监测.商品房市场.项目累计.供求.xlsx
A7: 2021年 | B7: 0 | C7: 0 | D7: 31792 | E7: 375 | F7: 16807 | G7: 534324608 | H7: 0 | M7: CRIC-万宁-市场监测.商品房市场.项目累计.供求.xlsx
A8: 2020年 | B8: 0 | C8: 0 | D8: 0 | E8: 0 | F8: 0 | G8: 0 | H8: 0 | M8: CRIC-万宁-市场监测.商品房市场.项目累计.供求.xlsx
A9: 2019年 | B9: 0 | C9: 0 | D9: 0 | E9: 0 | F9: 0 | G9: 0 | H9: 0 | M9: CRIC-万宁-市场监测.商品房市场.项目累计.供求.xlsx
A10: 汇总 | B10: 494186 | C10: 4763 | D10: 620089 | E10: 6385 | F10: 15493 | G10: 9607213852 | H10: 0.8 | M10: CRIC-万宁-市场监测.商品房市场.项目累计.供求.xlsx
M11: CRIC-万宁-市场监测.商品房市场.项目累计.库存.xlsx
A12: 时间(年) | B12: 库存面积(㎡) | C12: 库存套数(套) | D12: 去化周期12'(月) | M12: CRIC-万宁-市场监测.商品房市场.项目累计.库存.xlsx
A13: 2024年 | B13: 1177236 | C13: 11995 | D13: 65.7 | M13: CRIC-万宁-市场监测.商品房市场.项目累计.库存.xlsx
A14: 2023年 | B14: 1171297 | C14: 11923 | D14: 59.8 | M14: CRIC-万宁-市场监测.商品房市场.项目累计.库存.xlsx
A15: 2022年 | B15: 1141432 | C15: 12041 | D15: 39.6 | M15: CRIC-万宁-市场监测.商品房市场.项目累计.库存.xlsx
A16: 2021年 | B16: 1353015 | C16: 14336 | D16: 510.7 | M16: CRIC-万宁-市场监测.商品房市场.项目累计.库存.xlsx
M18: CRIC-三亚-市场监测.商品房市场.项目累计.供求.xlsx
A19: 时间(年) | B19: 供应面积(㎡) | C19: 供应套数(套) | D19: 成交面积(㎡) | E19: 成交套数(套) | F19: 成交均价(元/㎡) | G19: 成交金额(元) | H19: 供求比 | M19: CRIC-三亚-市场监测.商品房市场.项目累计.供求.xlsx
A20: 2023年 | B20: 0 | C20: 0 | D20: 2128925 | E20: 18654 | F20: 20992 | G20: 44690402503 | H20: 0 | M20: CRIC-三亚-市场监测.商品房市场.项目累计.供求.xlsx
A21: 2022年 | B21: 0 | C21: 0 | D21: 1321697 | E21: 11720 | F21: 27240 | G21: 36002622595 | H21: 0 | M21: CRIC-三亚-市场监测.商品房市场.项目累计.供求.xlsx
A22: 2021年 | B22: 0 | C22: 0 | D22: 1094572 | E22: 10202 | F22: 29547 | G22: 32340981576 | H22: 0 | M22: CRIC-三亚-市场监测.商品房市场.项目累计.供求.xlsx
A23: 2020年 | B23: 0 | C23: 0 | D23: 527705 | E23: 4988 | F23: 28247 | G23: 14906332741 | H23: 0 | M23: CRIC-三亚-市场监测.商品房市场.项目累计.供求.xlsx
A24: 2019年 | B24: 0 | C24: 0 | D24: 889350 | E24: 8434 | F24: 26872 | G24: 23898179823 | H24: 0 | M24: CRIC-三亚-市场监测.商品房市场.项目累计.供求.xlsx
A25: 2018年 | B25: 0 | C25: 0 | D25: 1132113 | E25: 11596 | F25: 28402 | G25: 32153958532 | H25: 0 | M25: CRIC-三亚-市场监测.商品房市场.项目累计.供求.xlsx
A26: 汇总 | B26: 0 | C26: 0 | D26: 7094361 | E26: 65594 | F26: 25935 | G26: 183992477771 | H26: 0 | M26: CRIC-三亚-市场监测.商品房市场.项目累计.供求.xlsx
M28: CRIC-上海-市场监测.商品房市场.项目累计.供求.xlsx
A29: 时间(年) | B29: 供应面积(㎡) | C29: 供应套数(套) | D29: 成交面积(㎡) | E29: 成交套数(套) | F29: 成交均价(元/㎡) | G29: 成交金额(元) | H29: 供求比 | M29: CRIC-上海-市场监测.商品房市场.项目累计.供求.xlsx
A30: 2023年 | B30: 9472869 | C30: 85900 | D30: 8272987 | E30: 75015 | F30: 66494 | G30: 550105561723 | H30: 1.15 | M30: CRIC-上海-市场监测.商品房市场.项目累计.供求.xlsx
A31: 2022年 | B31: 10275105 | C31: 95629 | D31: 8912467 | E31: 81511 | F31: 63623 | G31: 567033669349 | H31: 1.15 | M31: CRIC-上海-市场监测.商品房市场.项目累计.供求.xlsx
A32: 2021年 | B32: 7042950 | C32: 67256 | D32: 8783542 | E32: 82642 | F32: 55386 | G32: 486482020192 | H32: 0.8 | M32: CRIC-上海-市场监测.商品房市场.项目累计.供求.xlsx
A33: 2020年 | B33: 6738974 | C33: 62818 | D33: 7364723 | E33: 67627 | F33: 56134 | G33: 413413433424 | H33: 0.92 | M33: CRIC-上海-市场监测.商品房市场.项目累计.供求.xlsx
A34: 2019年 | B34: 6280488 | C34: 58213 | D34: 5992144 | E34: 54210 | F34: 54761 | G34: 328136667526 | H34: 1.05 | M34: CRIC-上海-市场监测.商品房市场.项目累计.供求.xlsx
A35: 汇总 | B35: 39810387 | C35: 369816 | D35: 39325863 | E35: 361005 | F35: 59634 | G35: 2345171352215 | H35: 1.01 | M35: CRIC-上海-市场监测.商品房市场.项目累计.供求.xlsx
M37: CRIC-上海-市场监测.商品房市场.项目累计.库存.xlsx
A38: 时间(年) | B38: 库存面积(㎡) | C38: 库存套数(套) | D38: 去化周期12'(月) | M38: CRIC-上海-市场监测.商品房市场.项目累计.库存.xlsx
A39: 2023年 | B39: 23926148 | C39: 131579 | D39: 26.4 | M39: CRIC-上海-市场监测.商品房市场.项目累计.库存.xlsx
A40: 2022年 | B40: 21869214 | C40: 116870 | D40: 22.4 | M40: CRIC-上海-市场监测.商品房市场.项目累计.库存.xlsx
A41: 2021年 | B41: 21104930 | C41: 107483 | D41: 20.3 | M41: CRIC-上海-市场监测.商品房市场.项目累计.库存.xlsx
A42: 2020年 | B42: 23237423 | C42: 127581 | D42: 25 | M42: CRIC-上海-市场监测.商品房市场.项目累计.库存.xlsx
A43: 2019年 | B43: 23229057 | C43: 133562 | D43: 29.1 | M43: CRIC-上海-市场监测.商品房市场.项目累计.库存.xlsx
M45: CRIC-上饶-市场监测.商品房市场.项目累计.供求.xlsx
A46: 时间(年) | B46: 供应面积(㎡) | C46: 供应套数(套) | D46: 成交面积(㎡) | E46: 成交套数(套) | F46: 成交均价(元/㎡) | G46: 成交金额(元) | H46: 供求比 | M46: CRIC-上饶-市场监测.商品房市场.项目累计.供求.xlsx
A47: 2023年 | B47: 1124939 | C47: 9104 | D47: 1003867 | E47: 8439 | F47: 7893 | G47: 7923535408 | H47: 1.12 | M47: CRIC-上饶-市场监测.商品房市场.项目累计.供求.xlsx
A48: 2022年 | B48: 1032546 | C48: 8749 | D48: 1101472 | E48: 9333 | F48: 7889 | G48: 8689254980 | H48: 0.94 | M48: CRIC-上饶-市场监测.商品房市场.项目累计.供求.xlsx
A49: 2021年 | B49: 1652918 | C49: 14172 | D49: 1246814 | E49: 10699 | F49: 8021 | G49: 10000357453 | H49: 1.33 | M49: CRIC-上饶-市场监测.商品房市场.项目累计.供求.xlsx
A50: 2020年 | B50: 1455595 | C50: 12333 | D50: 1803798 | E50: 15208 | F50: 7493 | G50: 13515346923 | H50: 0.81 | M50: CRIC-上饶-市场监测.商品房市场.项目累计.供求.xlsx
A51: 2019年 | B51: 1020431 | C51: 8630 | D51: 1284700 | E51: 10753 | F51: 7601 | G51: 9764760848 | H51: 0.79 | M51: CRIC-上饶-市场监测.商品房市场.项目累计.供求.xlsx
A52: 汇总 | B52: 6286429 | C52: 52988 | D52: 6440651 | E52: 54432 | F52: 7747 | G52: 49893255612 | H52: 0.98 | M52: CRIC-上饶-市场监测.商品房市场.项目累计.供求.xlsx
M54: CRIC-上饶-市场监测.商品房市场.项目累计.库存.xlsx
A55: 时间(年) | B55: 库存面积(㎡) | C55: 库存套数(套) | D55: 去化周期12'(月) | M55: CRIC-上饶-市场监测.商品房市场.项目累计.库存.xlsx
A56: 2023年 | B56: 961005 | C56: 7641 | D56: 11.5 | M56: CRIC-上饶-市场监测.商品房市场.项目累计.库存.xlsx
A57: 2022年 | B57: 771389 | C57: 6282 | D57: 8.4 | M57: CRIC-上饶-市场监测.商品房市场.项目累计.库存.xlsx
A58: 2021年 | B58: 982642 | C58: 8181 | D58: 9.5 | M58: CRIC-上饶-市场监测.商品房市场.项目累计.库存.xlsx
A59: 2020年 | B59: 0 | C59: 0 | D59: 0 | M59: CRIC-上饶-市场监测.商品房市场.项目累计.库存.xlsx
A60: 2019年 | B60: 740444 | C60: 5989 | D60: 6.9 | M60: CRIC-上饶-市场监测.商品房市场.项目累计.库存.xlsx
M62: CRIC-东方-市场监测.商品房市场.项目累计.供求.xlsx
A63: 时间(年) | B63: 供应面积(㎡) | C63: 供应套数(套) | D63: 成交面积(㎡) | E63: 成交套数(套) | F63: 成交均价(元/㎡) | G63: 成交金额(元) | H63: 供求比 | M63: CRIC-东方-市场监测.商品房市场.项目累计.供求.xlsx
A64: 2024年 | B64: 0 | C64: 0 | D64: 44837 | E64: 528 | F64: 8110 | G64: 363634868 | H64: 0 | M64: CRIC-东方-市场监测.商品房市场.项目累计.供求.xlsx
A65: 2023年 | B65: 0 | C65: 0 | D65: 92267 | E65: 1221 | F65: 12405 | G65: 1144608667 | H65: 0 | M65: CRIC-东方-市场监测.商品房市场.项目累计.供求.xlsx
A66: 2022年 | B66: 0 | C66: 0 | D66: 51268 | E66: 614 | F66: 12560 | G66: 643910056 | H66: 0 | M66: CRIC-东方-市场监测.商品房市场.项目累计.供求.xlsx
A67: 2021年 | B67: 0 | C67: 0 | D67: 5776 | E67: 67 | F67: 12971 | G67: 74921563 | H67: 0 | M67: CRIC-东方-市场监测.商品房市场.项目累计.供求.xlsx
A68: 汇总 | B68: 0 | C68: 0 | D68: 194147 | E68: 2430 | F68: 11471 | G68: 2227075154 | H68: 0 | M68: CRIC-东方-市场监测.商品房市场.项目累计.供求.xlsx
M70: CRIC-东方-市场监测.商品房市场.项目累计.库存.xlsx
A71: 时间(年) | B71: 库存面积(㎡) | C71: 库存套数(套) | D71: 去化周期12'(月) | M71: CRIC-东方-市场监测.商品房市场.项目累计.库存.xlsx
A72: 2024年 | B72: 585255 | C72: 7723 | D72: 54.1 | M72: CRIC-东方-市场监测.商品房市场.项目累计.库存.xlsx
A73: 2023年 | B73: 474751 | C73: 6677 | D73: 61.7 | M73: CRIC-东方-市场监测.商品房市场.项目累计.库存.xlsx
A74: 2022年 | B74: 296143 | C74: 4638 | D74: 69.3 | M74: CRIC-东方-市场监测.商品房市场.项目累计.库存.xlsx
A75: 2021年 | B75: 318351 | C75: 4925 | D75: 661.4 | M75: CRIC-东方-市场监测.商品房市场.项目累计.库存.xlsx
M77: CRIC-东莞-市场监测.商品房市场.项目累计.供求.xlsx
A78: 时间(年) | B78: 供应面积(㎡) | C78: 供应套数(套) | D78: 成交面积(㎡) | E78: 成交套数(套) | F78: 成交均价(元/㎡) | G78: 成交金额(元) | H78: 供求比 | M78: CRIC-东莞-市场监测.商品房市场.项目累计.供求.xlsx
A79: 2023年 | B79: 2880697 | C79: 23625 | D79: 2272764 | E79: 19003 | F79: 36305 | G79: 82512434318 | H79: 1.27 | M79: CRIC-东莞-市场监测.商品房市场.项目累计.供求.xlsx
A80: 2022年 | B80: 2958412 | C80: 26904 | D80: 2332563 | E80: 20597 | F80: 29692 | G80: 69258212118 | H80: 1.27 | M80: CRIC-东莞-市场监测.商品房市场.项目累计.供求.xlsx
A81: 2021年 | B81: 5523397 | C81: 50060 | D81: 4268996 | E81: 38848 | F81: 28399 | G81: 121235856663 | H81: 1.29 | M81: CRIC-东莞-市场监测.商品房市场.项目累计.供求.xlsx
A82: 2020年 | B82: 5385449 | C82: 51096 | D82: 6226989 | E82: 58107 | F82: 24187 | G82: 150611708672 | H82: 0.86 | M82: CRIC-东莞-市场监测.商品房市场.项目累计.供求.xlsx
A83: 2019年 | B83: 3645459 | C83: 33434 | D83: 4686652 | E83: 43841 | F83: 20826 | G83: 97603153232 | H83: 0.78 | M83: CRIC-东莞-市场监测.商品房市场.项目累计.供求.xlsx
A84: 汇总 | B84: 20393414 | C84: 185119 | D84: 19787963 | E84: 180396 | F84: 26340 | G84: 521221365003 | H84: 1.03 | M84: CRIC-东莞-市场监测.商品房市场.项目累计.供求.xlsx
M86: CRIC-东莞-市场监测.商品房市场.项目累计.库存.xlsx
A87: 时间(年) | B87: 库存面积(㎡) | C87: 库存套数(套) | D87: 去化周期12'(月) | M87: CRIC-东莞-市场监测.商品房市场.项目累计.库存.xlsx
A88: 2023年 | B88: 4845196 | C88: 44151 | D88: 25.6 | M88: CRIC-东莞-市场监测.商品房市场.项目累计.库存.xlsx
A89: 2022年 | B89: 4231605 | C89: 39341 | D89: 21.8 | M89: CRIC-东莞-市场监测.商品房市场.项目累计.库存.xlsx
A90: 2021年 | B90: 4001377 | C90: 36797 | D90: 11.2 | M90: CRIC-东莞-市场监测.商品房市场.项目累计.库存.xlsx
A91: 2020年 | B91: 2927135 | C91: 27034 | D91: 5.6 | M91: CRIC-东莞-市场监测.商品房市场.项目累计.库存.xlsx
A92: 2019年 | B92: 3451129 | C92: 31032 | D92: 8.8 | M92: CRIC-东莞-市场监测.商品房市场.项目累计.库存.xlsx
M94: CRIC-东营-市场监测.商品房市场.项目累计.供求.xlsx
A95: 时间(年) | B95: 供应面积(㎡) | C95: 供应套数(套) | D95: 成交面积(㎡) | E95: 成交套数(套) | F95: 成交均价(元/㎡) | G95: 成交金额(元) | H95: 供求比 | M95: CRIC-东营-市场监测.商品房市场.项目累计.供求.xlsx
A96: 2023年 | B96: 1339611 | C96: 9745 | D96: 963151 | E96: 6744 | F96: 8079 | G96: 7781631469 | H96: 1.39 | M96: CRIC-东营-市场监测.商品房市场.项目累计.供求.xlsx
A97: 2022年 | B97: 977798 | C97: 7142 | D97: 1152393 | E97: 8428 | F97: 8096 | G97: 9329807386 | H97: 0.85 | M97: CRIC-东营-市场监测.商品房市场.项目累计.供求.xlsx
A98: 2021年 | B98: 1526598 | C98: 11671 | D98: 2216393 | E98: 15505 | F98: 7702 | G98: 17070850869 | H98: 0.69 | M98: CRIC-东营-市场监测.商品房市场.项目累计.供求.xlsx
A99: 2020年 | B99: 2515710 | C99: 18238 | D99: 2017135 | E99: 14796 | F99: 7936 | G99: 16007154752 | H99: 1.25 | M99: CRIC-东营-市场监测.商品房市场.项目累计.供求.xlsx
A100: 2019年 | B100: 1880528 | C100: 12687 | D100: 1398216 | E100: 9730 | F100: 8383 | G100: 11721390668 | H100: 1.34 | M100: CRIC-东营-市场监测.商品房市场.项目累计.供求.xlsx
A101: 汇总 | B101: 8240244 | C101: 59483 | D101: 7747287 | E101: 55203 | F101: 7991 | G101: 61910835143 | H101: 1.06 | M101: CRIC-东营-市场监测.商品房市场.项目累计.供求.xlsx
M103: CRIC-东营-市场监测.商品房市场.项目累计.库存.xlsx
A104: 时间(年) | B104: 库存面积(㎡) | C104: 库存套数(套) | D104: 去化周期12'(月) | M104: CRIC-东营-市场监测.商品房市场.项目累计.库存.xlsx
A105: 2024年 | B105: 4176935 | C105: 30101 | D105: 52.6 | M105: CRIC-东营-市场监测.商品房市场.项目累计.库存.xlsx
A106: 2023年 | B106: 4198368 | C106: 30245 | D106: 52.3 | M106: CRIC-东营-市场监测.商品房市场.项目累计.库存.xlsx
A107: 2022年 | B107: 2116339 | C107: 15279 | D107: 22 | M107: CRIC-东营-市场监测.商品房市场.项目累计.库存.xlsx
A108: 2021年 | B108: 2122456 | C108: 15312 | D108: 11.5 | M108: CRIC-东营-市场监测.商品房市场.项目累计.库存.xlsx
M110: CRIC-中卫-市场监测.商品房市场.项目累计.供求.xlsx
A111: 时间(年) | B111: 供应面积(㎡) | C111: 供应套数(套) | D111: 成交面积(㎡) | E111: 成交套数(套) | F111: 成交均价(元/㎡) | G111: 成交金额(元) | H111: 供求比 | M111: CRIC-中卫-市场监测.商品房市场.项目累计.供求.xlsx
A112: 2024年 | B112: 16220 | C112: 126 | D112: 21737 | E112: 170 | F112: 4556 | G112: 99024867 | H112: 0.75 | M112: CRIC-中卫-市场监测.商品房市场.项目累计.供求.xlsx
A113: 2023年 | B113: 393527 | C113: 2945 | D113: 484575 | E113: 3745 | F113: 4898 | G113: 2373608627 | H113: 0.81 | M113: CRIC-中卫-市场监测.商品房市场.项目累计.供求.xlsx
...

Sheet VIPcric_2
A1: =IF(VIPcric_1!A3="","",VIPcric_1!A3) -> 时间(年) | B1: =IF(VIPcric_1!B3="","",VIPcric_1!B3) -> 供应面积(㎡) | C1: =IF(VIPcric_1!C3="","",VIPcric_1!C3) -> 供应套数(套) | D1: =IF(VIPcric_1!D3="","",VIPcric_1!D3) -> 成交面积(㎡) | E1: =IF(VIPcric_1!E3="","",VIPcric_1!E3) -> 成交套数(套) | F1: =IF(VIPcric_1!F3="","",VIPcric_1!F3) -> 成交均价(元/㎡) | G1: =IF(VIPcric_1!G3="","",VIPcric_1!G3) -> 成交金额(元) | H1: =IF(VIPcric_1!H3="","",VIPcric_1!H3) -> 供求比 | I1: 城市
A2: =IF(VIPcric_1!A4="","",VIPcric_1!A4) -> 2024年 | B2: =IF(VIPcric_1!B4="","",VIPcric_1!B4) -> 13274 | C2: =IF(VIPcric_1!C4="","",VIPcric_1!C4) -> 146 | D2: =IF(VIPcric_1!D4="","",VIPcric_1!D4) -> 7451 | E2: =IF(VIPcric_1!E4="","",VIPcric_1!E4) -> 75 | F2: =IF(VIPcric_1!F4="","",VIPcric_1!F4) -> 16623 | G2: =IF(VIPcric_1!G4="","",VIPcric_1!G4) -> 123862588 | H2: =IF(VIPcric_1!H4="","",VIPcric_1!H4) -> 1.78 | I2: =IF(VIPcric_1!M4="","",VIPcric_1!M4) -> CRIC-万宁-市场监测.商品房市场.项目累计.供求.xlsx
A3: =IF(VIPcric_1!A5="","",VIPcric_1!A5) -> 2023年 | B3: =IF(VIPcric_1!B5="","",VIPcric_1!B5) -> 262195 | C3: =IF(VIPcric_1!C5="","",VIPcric_1!C5) -> 2349 | D3: =IF(VIPcric_1!D5="","",VIPcric_1!D5) -> 234882 | E3: =IF(VIPcric_1!E5="","",VIPcric_1!E5) -> 2494 | F3: =IF(VIPcric_1!F5="","",VIPcric_1!F5) -> 16309 | G3: =IF(VIPcric_1!G5="","",VIPcric_1!G5) -> 3830728567 | H3: =IF(VIPcric_1!H5="","",VIPcric_1!H5) -> 1.12 | I3: =IF(VIPcric_1!M5="","",VIPcric_1!M5) -> CRIC-万宁-市场监测.商品房市场.项目累计.供求.xlsx
A4: =IF(VIPcric_1!A6="","",VIPcric_1!A6) -> 2022年 | B4: =IF(VIPcric_1!B6="","",VIPcric_1!B6) -> 218718 | C4: =IF(VIPcric_1!C6="","",VIPcric_1!C6) -> 2268 | D4: =IF(VIPcric_1!D6="","",VIPcric_1!D6) -> 345964 | E4: =IF(VIPcric_1!E6="","",VIPcric_1!E6) -> 3441 | F4: =IF(VIPcric_1!F6="","",VIPcric_1!F6) -> 14794 | G4: =IF(VIPcric_1!G6="","",VIPcric_1!G6) -> 5118298089 | H4: =IF(VIPcric_1!H6="","",VIPcric_1!H6) -> 0.63 | I4: =IF(VIPcric_1!M6="","",VIPcric_1!M6) -> CRIC-万宁-市场监测.商品房市场.项目累计.供求.xlsx
A5: =IF(VIPcric_1!A7="","",VIPcric_1!A7) -> 2021年 | B5: =IF(VIPcric_1!B7="","",VIPcric_1!B7) -> 0 | C5: =IF(VIPcric_1!C7="","",VIPcric_1!C7) -> 0 | D5: =IF(VIPcric_1!D7="","",VIPcric_1!D7) -> 31792 | E5: =IF(VIPcric_1!E7="","",VIPcric_1!E7) -> 375 | F5: =IF(VIPcric_1!F7="","",VIPcric_1!F7) -> 16807 | G5: =IF(VIPcric_1!G7="","",VIPcric_1!G7) -> 534324608 | H5: =IF(VIPcric_1!H7="","",VIPcric_1!H7) -> 0 | I5: =IF(VIPcric_1!M7="","",VIPcric_1!M7) -> CRIC-万宁-市场监测.商品房市场.项目累计.供求.xlsx
A6: =IF(VIPcric_1!A8="","",VIPcric_1!A8) -> 2020年 | B6: =IF(VIPcric_1!B8="","",VIPcric_1!B8) -> 0 | C6: =IF(VIPcric_1!C8="","",VIPcric_1!C8) -> 0 | D6: =IF(VIPcric_1!D8="","",VIPcric_1!D8) -> 0 | E6: =IF(VIPcric_1!E8="","",VIPcric_1!E8) -> 0 | F6: =IF(VIPcric_1!F8="","",VIPcric_1!F8) -> 0 | G6: =IF(VIPcric_1!G8="","",VIPcric_1!G8) -> 0 | H6: =IF(VIPcric_1!H8="","",VIPcric_1!H8) -> 0 | I6: =IF(VIPcric_1!M8="","",VIPcric_1!M8) -> CRIC-万宁-市场监测.商品房市场.项目累计.供求.xlsx
A7: =IF(VIPcric_1!A9="","",VIPcric_1!A9) -> 2019年 | B7: =IF(VIPcric_1!B9="","",VIPcric_1!B9) -> 0 | C7: =IF(VIPcric_1!C9="","",VIPcric_1!C9) -> 0 | D7: =IF(VIPcric_1!D9="","",VIPcric_1!D9) -> 0 | E7: =IF(VIPcric_1!E9="","",VIPcric_1!E9) -> 0 | F7: =IF(VIPcric_1!F9="","",VIPcric_1!F9) -> 0 | G7: =IF(VIPcric_1!G9="","",VIPcric_1!G9) -> 0 | H7: =IF(VIPcric_1!H9="","",VIPcric_1!H9) -> 0 | I7: =IF(VIPcric_1!M9="","",VIPcric_1!M9) -> CRIC-万宁-市场监测.商品房市场.项目累计.供求.xlsx
A8: =IF(VIPcric_1!A10="","",VIPcric_1!A10) -> 汇总 | B8: =IF(VIPcric_1!B10="","",VIPcric_1!B10) -> 494186 | C8: =IF(VIPcric_1!C10="","",VIPcric_1!C10) -> 4763 | D8: =IF(VIPcric_1!D10="","",VIPcric_1!D10) -> 620089 | E8: =IF(VIPcric_1!E10="","",VIPcric_1!E10) -> 6385 | F8: =IF(VIPcric_1!F10="","",VIPcric_1!F10) -> 15493 | G8: =IF(VIPcric_1!G10="","",VIPcric_1!G10) -> 9607213852 | H8: =IF(VIPcric_1!H10="","",VIPcric_1!H10) -> 0.8 | I8: =IF(VIPcric_1!M10="","",VIPcric_1!M10) -> CRIC-万宁-市场监测.商品房市场.项目累计.供求.xlsx
A9: =IF(VIPcric_1!A11="","",VIPcric_1!A11) | B9: =IF(VIPcric_1!B11="","",VIPcric_1!B11) | C9: =IF(VIPcric_1!C11="","",VIPcric_1!C11) | D9: =IF(VIPcric_1!D11="","",VIPcric_1!D11) | E9: =IF(VIPcric_1!E11="","",VIPcric_1!E11) | F9: =IF(VIPcric_1!F11="","",VIPcric_1!F11) | G9: =IF(VIPcric_1!G11="","",VIPcric_1!G11) | H9: =IF(VIPcric_1!H11="","",VIPcric_1!H11) | I9: =IF(VIPcric_1!M11="","",VIPcric_1!M11) -> CRIC-万宁-市场监测.商品房市场.项目累计.库存.xlsx
A10: =IF(VIPcric_1!A12="","",VIPcric_1!A12) -> 时间(年) | B10: =IF(VIPcric_1!B12="","",VIPcric_1!B12) -> 库存面积(㎡) | C10: =IF(VIPcric_1!C12="","",VIPcric_1!C12) -> 库存套数(套) | D10: =IF(VIPcric_1!D12="","",VIPcric_1!D12) -> 去化周期12'(月) | E10: =IF(VIPcric_1!E12="","",VIPcric_1!E12) | F10: =IF(VIPcric_1!F12="","",VIPcric_1!F12) | G10: =IF(VIPcric_1!G12="","",VIPcric_1!G12) | H10: =IF(VIPcric_1!H12="","",VIPcric_1!H12) | I10: =IF(VIPcric_1!M12="","",VIPcric_1!M12) -> CRIC-万宁-市场监测.商品房市场.项目累计.库存.xlsx
A11: =IF(VIPcric_1!A13="","",VIPcric_1!A13) -> 2024年 | B11: =IF(VIPcric_1!B13="","",VIPcric_1!B13) -> 1177236 | C11: =IF(VIPcric_1!C13="","",VIPcric_1!C13) -> 11995 | D11: =IF(VIPcric_1!D13="","",VIPcric_1!D13) -> 65.7 | E11: =IF(VIPcric_1!E13="","",VIPcric_1!E13) | F11: =IF(VIPcric_1!F13="","",VIPcric_1!F13) | G11: =IF(VIPcric_1!G13="","",VIPcric_1!G13) | H11: =IF(VIPcric_1!H13="","",VIPcric_1!H13) | I11: =IF(VIPcric_1!M13="","",VIPcric_1!M13) -> CRIC-万宁-市场监测.商品房市场.项目累计.库存.xlsx
A12: =IF(VIPcric_1!A14="","",VIPcric_1!A14) -> 2023年 | B12: =IF(VIPcric_1!B14="","",VIPcric_1!B14) -> 1171297 | C12: =IF(VIPcric_1!C14="","",VIPcric_1!C14) -> 11923 | D12: =IF(VIPcric_1!D14="","",VIPcric_1!D14) -> 59.8 | E12: =IF(VIPcric_1!E14="","",VIPcric_1!E14) | F12: =IF(VIPcric_1!F14="","",VIPcric_1!F14) | G12: =IF(VIPcric_1!G14="","",VIPcric_1!G14) | H12: =IF(VIPcric_1!H14="","",VIPcric_1!H14) | I12: =IF(VIPcric_1!M14="","",VIPcric_1!M14) -> CRIC-万宁-市场监测.商品房市场.项目累计.库存.xlsx
A13: =IF(VIPcric_1!A15="","",VIPcric_1!A15) -> 2022年 | B13: =IF(VIPcric_1!B15="","",VIPcric_1!B15) -> 1141432 | C13: =IF(VIPcric_1!C15="","",VIPcric_1!C15) -> 12041 | D13: =IF(VIPcric_1!D15="","",VIPcric_1!D15) -> 39.6 | E13: =IF(VIPcric_1!E15="","",VIPcric_1!E15) | F13: =IF(VIPcric_1!F15="","",VIPcric_1!F15) | G13: =IF(VIPcric_1!G15="","",VIPcric_1!G15) | H13: =IF(VIPcric_1!H15="","",VIPcric_1!H15) | I13: =IF(VIPcric_1!M15="","",VIPcric_1!M15) -> CRIC-万宁-市场监测.商品房市场.项目累计.库存.xlsx
... A298: =IF(VIPcric_1!A300="","",VIPcric_1!A300) -> 时间(年) | B298: =IF(VIPcric_1!B300="","",VIPcric_1!B300) -> 供应面积(㎡) | C298: =IF(VIPcric_1!C300="","",VIPcric_1!C300) -> 供应套数(套) | D298: =IF(VIPcric_1!D300="","",VIPcric_1!D300) -> 成交面积(㎡) | E298: =IF(VIPcric_1!E300="","",VIPcric_1!E300) -> 成交套数(套) | F298: =IF(VIPcric_1!F300="","",VIPcric_1!F300) -> 成交均价(元/㎡) | G298: =IF(VIPcric_1!G300="","",VIPcric_1!G300) -> 成交金额(元) | H298: =IF(VIPcric_1!H300="","",VIPcric_1!H300) -> 供求比 | I298: =IF(VIPcric_1!M300="","",VIPcric_1!M300) -> CRIC-信阳-市场监测.商品房市场.项目累计.供求.xlsx
F299: 7100
A300: =IF(VIPcric_1!A301="","",VIPcric_1!A301) -> 2022年 | B300: =IF(VIPcric_1!B301="","",VIPcric_1!B301) -> 298834 | C300: =IF(VIPcric_1!C301="","",VIPcric_1!C301) -> 2309 | D300: =IF(VIPcric_1!D301="","",VIPcric_1!D301) -> 310803 | E300: =IF(VIPcric_1!E301="","",VIPcric_1!E301) -> 2524 | F300: =IF(VIPcric_1!F301="","",VIPcric_1!F301) -> 7373 | G300: =IF(VIPcric_1!G301="","",VIPcric_1!G301) -> 2291474445 | H300: =IF(VIPcric_1!H301="","",VIPcric_1!H301) -> 0.96 | I300: =IF(VIPcric_1!M301="","",VIPcric_1!M301) -> CRIC-信阳-市场监测.商品房市场.项目累计.供求.xlsx
A301: =IF(VIPcric_1!A302="","",VIPcric_1!A302) -> 2021年 | B301: =IF(VIPcric_1!B302="","",VIPcric_1!B302) -> 2575646 | C301: =IF(VIPcric_1!C302="","",VIPcric_1!C302) -> 21050 | D301: =IF(VIPcric_1!D302="","",VIPcric_1!D302) -> 541030 | E301: =IF(VIPcric_1!E302="","",VIPcric_1!E302) -> 4383 | F301: =IF(VIPcric_1!F302="","",VIPcric_1!F302) -> 7336 | G301: =IF(VIPcric_1!G302="","",VIPcric_1!G302) -> 3969153018 | H301: =IF(VIPcric_1!H302="","",VIPcric_1!H302) -> 4.76 | I301: =IF(VIPcric_1!M302="","",VIPcric_1!M302) -> CRIC-信阳-市场监测.商品房市场.项目累计.供求.xlsx
A302: =IF(VIPcric_1!A303="","",VIPcric_1!A303) -> 2020年 | B302: =IF(VIPcric_1!B303="","",VIPcric_1!B303) -> 2559938 | C302: =IF(VIPcric_1!C303="","",VIPcric_1!C303) -> 20524 | D302: =IF(VIPcric_1!D303="","",VIPcric_1!D303) -> 0 | E302: =IF(VIPcric_1!E303="","",VIPcric_1!E303) -> 0 | F302: =IF(VIPcric_1!F303="","",VIPcric_1!F303) -> 0 | G302: =IF(VIPcric_1!G303="","",VIPcric_1!G303) -> 0 | H302: =IF(VIPcric_1!H303="","",VIPcric_1!H303) -> 0 | I302: =IF(VIPcric_1!M303="","",VIPcric_1!M303) -> CRIC-信阳-市场监测.商品房市场.项目累计.供求.xlsx
A303: =IF(VIPcric_1!A304="","",VIPcric_1!A304) -> 2019年 | B303: =IF(VIPcric_1!B304="","",VIPcric_1!B304) -> 1929322 | C303: =IF(VIPcric_1!C304="","",VIPcric_1!C304) -> 15481 | D303: =IF(VIPcric_1!D304="","",VIPcric_1!D304) -> 0 | E303: =IF(VIPcric_1!E304="","",VIPcric_1!E304) -> 0 | F303: =IF(VIPcric_1!F304="","",VIPcric_1!F304) -> 0 | G303: =IF(VIPcric_1!G304="","",VIPcric_1!G304) -> 0 | H303: =IF(VIPcric_1!H304="","",VIPcric_1!H304) -> 0 | I303: =IF(VIPcric_1!M304="","",VIPcric_1!M304) -> CRIC-信阳-市场监测.商品房市场.项目累计.供求.xlsx
A304: =IF(VIPcric_1!A305="","",VIPcric_1!A305) -> 2018年 | B304: =IF(VIPcric_1!B305="","",VIPcric_1!B305) -> 1418421 | C304: =IF(VIPcric_1!C305="","",VIPcric_1!C305) -> 11351 | D304: =IF(VIPcric_1!D305="","",VIPcric_1!D305) -> 0 | E304: =IF(VIPcric_1!E305="","",VIPcric_1!E305) -> 0 | F304: =IF(VIPcric_1!F305="","",VIPcric_1!F305) -> 0 | G304: =IF(VIPcric_1!G305="","",VIPcric_1!G305) -> 0 | H304: =IF(VIPcric_1!H305="","",VIPcric_1!H305) -> 0 | I304: =IF(VIPcric_1!M305="","",VIPcric_1!M305) -> CRIC-信阳-市场监测.商品房市场.项目累计.供求.xlsx
A305: =IF(VIPcric_1!A306="","",VIPcric_1!A306) -> 2017年 | B305: =IF(VIPcric_1!B306="","",VIPcric_1!B306) -> 863981 | C305: =IF(VIPcric_1!C306="","",VIPcric_1!C306) -> 7130 | D305: =IF(VIPcric_1!D306="","",VIPcric_1!D306) -> 0 | E305: =IF(VIPcric_1!E306="","",VIPcric_1!E306) -> 0 | F305: =IF(VIPcric_1!F306="","",VIPcric_1!F306) -> 0 | G305: =IF(VIPcric_1!G306="","",VIPcric_1!G306) -> 0 | H305: =IF(VIPcric_1!H306="","",VIPcric_1!H306) -> 0 | I305: =IF(VIPcric_1!M306="","",VIPcric_1!M306) -> CRIC-信阳-市场监测.商品房市场.项目累计.供求.xlsx
A306: =IF(VIPcric_1!A307="","",VIPcric_1!A307) -> 汇总 | B306: =IF(VIPcric_1!B307="","",VIPcric_1!B307) -> 9646141 | C306: =IF(VIPcric_1!C307="","",VIPcric_1!C307) -> 77845 | D306: =IF(VIPcric_1!D307="","",VIPcric_1!D307) -> 851834 | E306: =IF(VIPcric_1!E307="","",VIPcric_1!E307) -> 6907 | F306: =IF(VIPcric_1!F307="","",VIPcric_1!F307) -> 7350 | G306: =IF(VIPcric_1!G307="","",VIPcric_1!G307) -> 6260627463 | H306: =IF(VIPcric_1!H307="","",VIPcric_1!H307) -> 11.32 | I306: =IF(VIPcric_1!M307="","",VIPcric_1!M307) -> CRIC-信阳-市场监测.商品房市场.项目累计.供求.xlsx
A307: =IF(VIPcric_1!A308="","",VIPcric_1!A308) | B307: =IF(VIPcric_1!B308="","",VIPcric_1!B308) | C307: =IF(VIPcric_1!C308="","",VIPcric_1!C308) | D307: =IF(VIPcric_1!D308="","",VIPcric_1!D308) | E307: =IF(VIPcric_1!E308="","",VIPcric_1!E308) | F307: =IF(VIPcric_1!F308="","",VIPcric_1!F308) | G307: =IF(VIPcric_1!G308="","",VIPcric_1!G308) | H307: =IF(VIPcric_1!H308="","",VIPcric_1!H308) | I307: =IF(VIPcric_1!M308="","",VIPcric_1!M308)
A308: =IF(VIPcric_1!A309="","",VIPcric_1!A309) | B308: =IF(VIPcric_1!B309="","",VIPcric_1!B309) | C308: =IF(VIPcric_1!C309="","",VIPcric_1!C309) | D308: =IF(VIPcric_1!D309="","",VIPcric_1!D309) | E308: =IF(VIPcric_1!E309="","",VIPcric_1!E309) | F308: =IF(VIPcric_1!F309="","",VIPcric_1!F309) | G308: =IF(VIPcric_1!G309="","",VIPcric_1!G309) | H308: =IF(VIPcric_1!H309="","",VIPcric_1!H309) | I308: =IF(VIPcric_1!M309="","",VIPcric_1!M309) -> CRIC-信阳-市场监测.商品房市场.项目累计.库存.xlsx
A309: =IF(VIPcric_1!A310="","",VIPcric_1!A310) -> 时间(年) | B309: =IF(VIPcric_1!B310="","",VIPcric_1!B310) -> 库存面积(㎡) | C309: =IF(VIPcric_1!C310="","",VIPcric_1!C310) -> 库存套数(套) | D309: =IF(VIPcric_1!D310="","",VIPcric_1!D310) -> 去化周期12'(月) | E309: =IF(VIPcric_1!E310="","",VIPcric_1!E310) -> 去化周期24'(月) | F309: =IF(VIPcric_1!F310="","",VIPcric_1!F310) | G309: =IF(VIPcric_1!G310="","",VIPcric_1!G310) | H309: =IF(VIPcric_1!H310="","",VIPcric_1!H310) | I309: =IF(VIPcric_1!M310="","",VIPcric_1!M310) -> CRIC-信阳-市场监测.商品房市场.项目累计.库存.xlsx
E310: 120
A311: =IF(VIPcric_1!A311="","",VIPcric_1!A311) -> 2022年 | B311: =IF(VIPcric_1!B311="","",VIPcric_1!B311) -> 3327761 | C311: =IF(VIPcric_1!C311="","",VIPcric_1!C311) -> 26001 | D311: =IF(VIPcric_1!D311="","",VIPcric_1!D311) -> 47 | E311: =IF(VIPcric_1!E311="","",VIPcric_1!E311) -> 94 | F311: =IF(VIPcric_1!F311="","",VIPcric_1!F311) | G311: =IF(VIPcric_1!G311="","",VIPcric_1!G311) | H311: =IF(VIPcric_1!H311="","",VIPcric_1!H311) | I311: =IF(VIPcric_1!M311="","",VIPcric_1!M311) -> CRIC-信阳-市场监测.商品房市场.项目累计.库存.xlsx
A312: =IF(VIPcric_1!A312="","",VIPcric_1!A312) -> 2021年 | B312: =IF(VIPcric_1!B312="","",VIPcric_1!B312) -> 3501950 | C312: =IF(VIPcric_1!C312="","",VIPcric_1!C312) -> 27539 | D312: =IF(VIPcric_1!D312="","",VIPcric_1!D312) -> 77.7 | E312: =IF(VIPcric_1!E312="","",VIPcric_1!E312) -> 155.3 | F312: =IF(VIPcric_1!F312="","",VIPcric_1!F312) | G312: =IF(VIPcric_1!G312="","",VIPcric_1!G312) | H312: =IF(VIPcric_1!H312="","",VIPcric_1!H312) | I312: =IF(VIPcric_1!M312="","",VIPcric_1!M312) -> CRIC-信阳-市场监测.商品房市场.项目累计.库存.xlsx
A313: =IF(VIPcric_1!A313="","",VIPcric_1!A313) | B313: =IF(VIPcric_1!B313="","",VIPcric_1!B313) | C313: =IF(VIPcric_1!C313="","",VIPcric_1!C313) | D313: =IF(VIPcric_1!D313="","",VIPcric_1!D313) | E313: =IF(VIPcric_1!E313="","",VIPcric_1!E313) | F313: =IF(VIPcric_1!F313="","",VIPcric_1!F313) | G313: =IF(VIPcric_1!G313="","",VIPcric_1!G313) | H313: =IF(VIPcric_1!H313="","",VIPcric_1!H313) | I313: =IF(VIPcric_1!M313="","",VIPcric_1!M313)
A314: =IF(VIPcric_1!A314="","",VIPcric_1!A314) | B314: =IF(VIPcric_1!B314="","",VIPcric_1!B314) | C314: =IF(VIPcric_1!C314="","",VIPcric_1!C314) | D314: =IF(VIPcric_1!D314="","",VIPcric_1!D314) | E314: =IF(VIPcric_1!E314="","",VIPcric_1!E314) | F314: =IF(VIPcric_1!F314="","",VIPcric_1!F314) | G314: =IF(VIPcric_1!G314="","",VIPcric_1!G314) | H314: =IF(VIPcric_1!H314="","",VIPcric_1!H314) | I314: =IF(VIPcric_1!M314="","",VIPcric_1!M314) -> CRIC-儋州-市场监测.商品房市场.项目累计.供求.xlsx
A315: =IF(VIPcric_1!A315="","",VIPcric_1!A315) -> 时间(年) | B315: =IF(VIPcric_1!B315="","",VIPcric_1!B315) -> 供应面积(㎡) | C315: =IF(VIPcric_1!C315="","",VIPcric_1!C315) -> 供应套数(套) | D315: =IF(VIPcric_1!D315="","",VIPcric_1!D315) -> 成交面积(㎡) | E315: =IF(VIPcric_1!E315="","",VIPcric_1!E315) -> 成交套数(套) | F315: =IF(VIPcric_1!F315="","",VIPcric_1!F315) -> 成交均价(元/㎡) | G315: =IF(VIPcric_1!G315="","",VIPcric_1!G315) -> 成交金额(元) | H315: =IF(VIPcric_1!H315="","",VIPcric_1!H315) -> 供求比 | I315: =IF(VIPcric_1!M315="","",VIPcric_1!M315) -> CRIC-儋州-市场监测.商品房市场.项目累计.供求.xlsx
A316: =IF(VIPcric_1!A316="","",VIPcric_1!A316) -> 2023年 | B316: =IF(VIPcric_1!B316="","",VIPcric_1!B316) -> 496085 | C316: =IF(VIPcric_1!C316="","",VIPcric_1!C316) -> 4885 | D316: =IF(VIPcric_1!D316="","",VIPcric_1!D316) -> 489917 | E316: =IF(VIPcric_1!E316="","",VIPcric_1!E316) -> 5068 | F316: =IF(VIPcric_1!F316="","",VIPcric_1!F316) -> 10533 | G316: =IF(VIPcric_1!G316="","",VIPcric_1!G316) -> 5160428862 | H316: =IF(VIPcric_1!H316="","",VIPcric_1!H316) -> 1.01 | I316: =IF(VIPcric_1!M316="","",VIPcric_1!M316) -> CRIC-儋州-市场监测.商品房市场.项目累计.供求.xlsx
A317: =IF(VIPcric_1!A317="","",VIPcric_1!A317) -> 2022年 | B317: =IF(VIPcric_1!B317="","",VIPcric_1!B317) -> 521206 | C317: =IF(VIPcric_1!C317="","",VIPcric_1!C317) -> 5043 | D317: =IF(VIPcric_1!D317="","",VIPcric_1!D317) -> 232217 | E317: =IF(VIPcric_1!E317="","",VIPcric_1!E317) -> 2339 | F317: =IF(VIPcric_1!F317="","",VIPcric_1!F317) -> 10546 | G317: =IF(VIPcric_1!G317="","",VIPcric_1!G317) -> 2448908121 | H317: =IF(VIPcric_1!H317="","",VIPcric_1!H317) -> 2.24 | I317: =IF(VIPcric_1!M317="","",VIPcric_1!M317) -> CRIC-儋州-市场监测.商品房市场.项目累计.供求.xlsx
A318: =IF(VIPcric_1!A318="","",VIPcric_1!A318) -> 2021年 | B318: =IF(VIPcric_1!B318="","",VIPcric_1!B318) -> 90353 | C318: =IF(VIPcric_1!C318="","",VIPcric_1!C318) -> 901 | D318: =IF(VIPcric_1!D318="","",VIPcric_1!D318) -> 50885 | E318: =IF(VIPcric_1!E318="","",VIPcric_1!E318) -> 507 | F318: =IF(VIPcric_1!F318="","",VIPcric_1!F318) -> 9178 | G318: =IF(VIPcric_1!G318="","",VIPcric_1!G318) -> 467005349 | H318: =IF(VIPcric_1!H318="","",VIPcric_1!H318) -> 1.78 | I318: =IF(VIPcric_1!M318="","",VIPcric_1!M318) -> CRIC-儋州-市场监测.商品房市场.项目累计.供求.xlsx
A319: =IF(VIPcric_1!A319="","",VIPcric_1!A319) -> 汇总 | B319: =IF(VIPcric_1!B319="","",VIPcric_1!B319) -> 1107644 | C319: =IF(VIPcric_1!C319="","",VIPcric_1!C319) -> 10829 | D319: =IF(VIPcric_1!D319="","",VIPcric_1!D319) -> 773019 | E319: =IF(VIPcric_1!E319="","",VIPcric_1!E319) -> 7914 | F319: =IF(VIPcric_1!F319="","",VIPcric_1!F319) -> 10448 | G319: =IF(VIPcric_1!G319="","",VIPcric_1!G319) -> 8076342332 | H319: =IF(VIPcric_1!H319="","",VIPcric_1!H319) -> 1.43 | I319: =IF(VIPcric_1!M319="","",VIPcric_1!M319) -> CRIC-儋州-市场监测.商品房市场.项目累计.供求.xlsx
A320: =IF(VIPcric_1!A320="","",VIPcric_1!A320) | B320: =IF(VIPcric_1!B320="","",VIPcric_1!B320) | C320: =IF(VIPcric_1!C320="","",VIPcric_1!C320) | D320: =IF(VIPcric_1!D320="","",VIPcric_1!D320) | E320: =IF(VIPcric_1!E320="","",VIPcric_1!E320) | F320: =IF(VIPcric_1!F320="","",VIPcric_1!F320) | G320: =IF(VIPcric_1!G320="","",VIPcric_1!G320) | H320: =IF(VIPcric_1!H320="","",VIPcric_1!H320) | I320: =IF(VIPcric_1!M320="","",VIPcric_1!M320)
A321: =IF(VIPcric_1!A321="","",VIPcric_1!A321) | B321: =IF(VIPcric_1!B321="","",VIPcric_1!B321) | C321: =IF(VIPcric_1!C321="","",VIPcric_1!C321) | D321: =IF(VIPcric_1!D321="","",VIPcric_1!D321) | E321: =IF(VIPcric_1!E321="","",VIPcric_1!E321) | F321: =IF(VIPcric_1!F321="","",VIPcric_1!F321) | G321: =IF(VIPcric_1!G321="","",VIPcric_1!G321) | H321: =IF(VIPcric_1!H321="","",VIPcric_1!H321) | I321: =IF(VIPcric_1!M321="","",VIPcric_1!M321) -> CRIC-儋州-市场监测.商品房市场.项目累计.库存.xlsx
A322: =IF(VIPcric_1!A322="","",VIPcric_1!A322) -> 时间(年) | B322: =IF(VIPcric_1!B322="","",VIPcric_1!B322) -> 库存面积(㎡) | C322: =IF(VIPcric_1!C322="","",VIPcric_1!C322) -> 库存套数(套) | D322: =IF(VIPcric_1!D322="","",VIPcric_1!D322) -> 去化周期12'(月) | E322: =IF(VIPcric_1!E322="","",VIPcric_1!E322) | F322: =IF(VIPcric_1!F322="","",VIPcric_1!F322) | G322: =IF(VIPcric_1!G322="","",VIPcric_1!G322) | H322: =IF(VIPcric_1!H322="","",VIPcric_1!H322) | I322: =IF(VIPcric_1!M322="","",VIPcric_1!M322) -> CRIC-儋州-市场监测.商品房市场.项目累计.库存.xlsx
... A380: =IF(VIPcric_1!A380="","",VIPcric_1!A380) -> 2019年 | B380: =IF(VIPcric_1!B380="","",VIPcric_1!B380) -> 7426262 | C380: =IF(VIPcric_1!C380="","",VIPcric_1!C380) -> 70610 | D380: =IF(VIPcric_1!D380="","",VIPcric_1!D380) -> 15.9 | E380: =IF(VIPcric_1!E380="","",VIPcric_1!E380) -> 20.4 | F380: =IF(VIPcric_1!F380="","",VIPcric_1!F380) | G380: =IF(VIPcric_1!G380="","",VIPcric_1!G380) | H380: =IF(VIPcric_1!H380="","",VIPcric_1!H380) | I380: =IF(VIPcric_1!M380="","",VIPcric_1!M380) -> CRIC-北京-市场监测.商品房市场.项目累计.库存.xlsx
A388: =IF(VIPcric_1!A381="","",VIPcric_1!A381) | B388: =IF(VIPcric_1!B381="","",VIPcric_1!B381) | C388: =IF(VIPcric_1!C381="","",VIPcric_1!C381) | D388: =IF(VIPcric_1!D381="","",VIPcric_1!D381) | E388: =IF(VIPcric_1!E381="","",VIPcric_1!E381) | F388: =IF(VIPcric_1!F381="","",VIPcric_1!F381) | G388: =IF(VIPcric_1!G381="","",VIPcric_1!G381) | H388: =IF(VIPcric_1!H381="","",VIPcric_1!H381) | I388: =IF(VIPcric_1!M381="","",VIPcric_1!M381)
A389: =IF(VIPcric_1!A382="","",VIPcric_1!A382) | B389: =IF(VIPcric_1!B382="","",VIPcric_1!B382) | C389: =IF(VIPcric_1!C382="","",VIPcric_1!C382) | D389: =IF(VIPcric_1!D382="","",VIPcric_1!D382) | E389: =IF(VIPcric_1!E382="","",VIPcric_1!E382) | F389: =IF(VIPcric_1!F382="","",VIPcric_1!F382) | G389: =IF(VIPcric_1!G382="","",VIPcric_1!G382) | H389: =IF(VIPcric_1!H382="","",VIPcric_1!H382) | I389: =IF(VIPcric_1!M382="","",VIPcric_1!M382) -> CRIC-北海-市场监测.商品房市场.城市总量.xlsx
A390: =IF(VIPcric_1!A383="","",VIPcric_1!A383) -> 时间(年) | B390: =IF(VIPcric_1!B383="","",VIPcric_1!B383) -> 成交面积(㎡) | C390: =IF(VIPcric_1!C383="","",VIPcric_1!C383) -> 成交套数(套) | D390: =IF(VIPcric_1!D383="","",VIPcric_1!D383) | E390: =IF(VIPcric_1!E383="","",VIPcric_1!E383) | F390: =IF(VIPcric_1!F383="","",VIPcric_1!F383) | G390: =IF(VIPcric_1!G383="","",VIPcric_1!G383) | H390: =IF(VIPcric_1!H383="","",VIPcric_1!H383) | I390: =IF(VIPcric_1!M383="","",VIPcric_1!M383) -> CRIC-北海-市场监测.商品房市场.城市总量.xlsx
A391: =IF(VIPcric_1!A384="","",VIPcric_1!A384) -> 2023年 | B391: =IF(VIPcric_1!B384="","",VIPcric_1!B384) -> 1372500 | C391: =IF(VIPcric_1!C384="","",VIPcric_1!C384) -> 18082 | D391: 6800 | E391: =IF(VIPcric_1!E384="","",VIPcric_1!E384) | F391: =IF(VIPcric_1!F384="","",VIPcric_1!F384) | G391: =IF(VIPcric_1!G384="","",VIPcric_1!G384) | H391: =IF(VIPcric_1!H384="","",VIPcric_1!H384) | I391: =IF(VIPcric_1!M384="","",VIPcric_1!M384) -> CRIC-北海-市场监测.商品房市场.城市总量.xlsx
A392: =IF(VIPcric_1!A385="","",VIPcric_1!A385) -> 2022年 | B392: =IF(VIPcric_1!B385="","",VIPcric_1!B385) -> 1037000 | C392: =IF(VIPcric_1!C385="","",VIPcric_1!C385) -> 9545 | D392: =IF(VIPcric_1!D385="","",VIPcric_1!D385) | E392: =IF(VIPcric_1!E385="","",VIPcric_1!E385) | F392: =IF(VIPcric_1!F385="","",VIPcric_1!F385) | G392: =IF(VIPcric_1!G385="","",VIPcric_1!G385) | H392: =IF(VIPcric_1!H385="","",VIPcric_1!H385) | I392: =IF(VIPcric_1!M385="","",VIPcric_1!M385) -> CRIC-北海-市场监测.商品房市场.城市总量.xlsx
A393: =IF(VIPcric_1!A386="","",VIPcric_1!A386) -> 2021年 | B393: =IF(VIPcric_1!B386="","",VIPcric_1!B386) -> 0 | C393: =IF(VIPcric_1!C386="","",VIPcric_1!C386) -> 0 | D393: =IF(VIPcric_1!D386="","",VIPcric_1!D386) | E393: =IF(VIPcric_1!E386="","",VIPcric_1!E386) | F393: =IF(VIPcric_1!F386="","",VIPcric_1!F386) | G393: =IF(VIPcric_1!G386="","",VIPcric_1!G386) | H393: =IF(VIPcric_1!H386="","",VIPcric_1!H386) | I393: =IF(VIPcric_1!M386="","",VIPcric_1!M386) -> CRIC-北海-市场监测.商品房市场.城市总量.xlsx
A394: =IF(VIPcric_1!A387="","",VIPcric_1!A387) -> 2020年 | B394: =IF(VIPcric_1!B387="","",VIPcric_1!B387) -> 0 | C394: =IF(VIPcric_1!C387="","",VIPcric_1!C387) -> 0 | D394: =IF(VIPcric_1!D387="","",VIPcric_1!D387) | E394: =IF(VIPcric_1!E387="","",VIPcric_1!E387) | F394: =IF(VIPcric_1!F387="","",VIPcric_1!F387) | G394: =IF(VIPcric_1!G387="","",VIPcric_1!G387) | H394: =IF(VIPcric_1!H387="","",VIPcric_1!H387) | I394: =IF(VIPcric_1!M387="","",VIPcric_1!M387) -> CRIC-北海-市场监测.商品房市场.城市总量.xlsx
A395: =IF(VIPcric_1!A388="","",VIPcric_1!A388) -> 2019年 | B395: =IF(VIPcric_1!B388="","",VIPcric_1!B388) -> 182500 | C395: =IF(VIPcric_1!C388="","",VIPcric_1!C388) -> 2134 | D395: =IF(VIPcric_1!D388="","",VIPcric_1!D388) | E395: =IF(VIPcric_1!E388="","",VIPcric_1!E388) | F395: =IF(VIPcric_1!F388="","",VIPcric_1!F388) | G395: =IF(VIPcric_1!G388="","",VIPcric_1!G388) | H395: =IF(VIPcric_1!H388="","",VIPcric_1!H388) | I395: =IF(VIPcric_1!M388="","",VIPcric_1!M388) -> CRIC-北海-市场监测.商品房市场.城市总量.xlsx
A396: =IF(VIPcric_1!A389="","",VIPcric_1!A389) -> 汇总 | B396: =IF(VIPcric_1!B389="","",VIPcric_1!B389) -> 2592000 | C396: =IF(VIPcric_1!C389="","",VIPcric_1!C389) -> 29761 | D396: =IF(VIPcric_1!D389="","",VIPcric_1!D389) | E396: =IF(VIPcric_1!E389="","",VIPcric_1!E389) | F396: =IF(VIPcric_1!F389="","",VIPcric_1!F389) | G396: =IF(VIPcric_1!G389="","",VIPcric_1!G389) | H396: =IF(VIPcric_1!H389="","",VIPcric_1!H389) | I396: =IF(VIPcric_1!M389="","",VIPcric_1!M389) -> CRIC-北海-市场监测.商品房市场.城市总量.xlsx
A397: =IF(VIPcric_1!A390="","",VIPcric_1!A390) | B397: =IF(VIPcric_1!B390="","",VIPcric_1!B390) | C397: =IF(VIPcric_1!C390="","",VIPcric_1!C390) | D397: =IF(VIPcric_1!D390="","",VIPcric_1!D390) | E397: =IF(VIPcric_1!E390="","",VIPcric_1!E390) | F397: =IF(VIPcric_1!F390="","",VIPcric_1!F390) | G397: =IF(VIPcric_1!G390="","",VIPcric_1!G390) | H397: =IF(VIPcric_1!H390="","",VIPcric_1!H390) | I397: =IF(VIPcric_1!M390="","",VIPcric_1!M390)
A398: =IF(VIPcric_1!A391="","",VIPcric_1!A391) | B398: =IF(VIPcric_1!B391="","",VIPcric_1!B391) | C398: =IF(VIPcric_1!C391="","",VIPcric_1!C391) | D398: =IF(VIPcric_1!D391="","",VIPcric_1!D391) | E398: =IF(VIPcric_1!E391="","",VIPcric_1!E391) | F398: =IF(VIPcric_1!F391="","",VIPcric_1!F391) | G398: =IF(VIPcric_1!G391="","",VIPcric_1!G391) | H398: =IF(VIPcric_1!H391="","",VIPcric_1!H391) | I398: =IF(VIPcric_1!M391="","",VIPcric_1!M391) -> CRIC-北海-市场监测.广义存量.广义存量.xlsx
A399: =IF(VIPcric_1!A392="","",VIPcric_1!A392) -> 时间(年) | B399: =IF(VIPcric_1!B392="","",VIPcric_1!B392) -> 广义存量面积(㎡) | C399: =IF(VIPcric_1!C392="","",VIPcric_1!C392) -> 去化周期 | D399: =IF(VIPcric_1!D392="","",VIPcric_1!D392) | E399: =IF(VIPcric_1!E392="","",VIPcric_1!E392) | F399: =IF(VIPcric_1!F392="","",VIPcric_1!F392) | G399: =IF(VIPcric_1!G392="","",VIPcric_1!G392) | H399: =IF(VIPcric_1!H392="","",VIPcric_1!H392) | I399: =IF(VIPcric_1!M392="","",VIPcric_1!M392) -> CRIC-北海-市场监测.广义存量.广义存量.xlsx
A400: =IF(VIPcric_1!A393="","",VIPcric_1!A393) -> 2024年 | B400: =IF(VIPcric_1!B393="","",VIPcric_1!B393) -> 12171040 | C400: =IF(VIPcric_1!C393="","",VIPcric_1!C393) -> 8.8677887 | D400: =IF(VIPcric_1!D393="","",VIPcric_1!D393) | E400: =IF(VIPcric_1!E393="","",VIPcric_1!E393) | F400: =IF(VIPcric_1!F393="","",VIPcric_1!F393) | G400: =IF(VIPcric_1!G393="","",VIPcric_1!G393) | H400: =IF(VIPcric_1!H393="","",VIPcric_1!H393) | I400: =IF(VIPcric_1!M393="","",VIPcric_1!M393) -> CRIC-北海-市场监测.广义存量.广义存量.xlsx
A401: =IF(VIPcric_1!A394="","",VIPcric_1!A394) -> 2023年 | B401: =IF(VIPcric_1!B394="","",VIPcric_1!B394) -> 11951318 | C401: =IF(VIPcric_1!C394="","",VIPcric_1!C394) -> 11.524897 | D401: =IF(VIPcric_1!D394="","",VIPcric_1!D394) | E401: =IF(VIPcric_1!E394="","",VIPcric_1!E394) | F401: =IF(VIPcric_1!F394="","",VIPcric_1!F394) | G401: =IF(VIPcric_1!G394="","",VIPcric_1!G394) | H401: =IF(VIPcric_1!H394="","",VIPcric_1!H394) | I401: =IF(VIPcric_1!M394="","",VIPcric_1!M394) -> CRIC-北海-市场监测.广义存量.广义存量.xlsx
A402: =IF(VIPcric_1!A395="","",VIPcric_1!A395) -> 2022年 | B402: =IF(VIPcric_1!B395="","",VIPcric_1!B395) -> 12428136 | C402: =IF(VIPcric_1!C395="","",VIPcric_1!C395) | D402: =IF(VIPcric_1!D395="","",VIPcric_1!D395) | E402: =IF(VIPcric_1!E395="","",VIPcric_1!E395) | F402: =IF(VIPcric_1!F395="","",VIPcric_1!F395) | G402: =IF(VIPcric_1!G395="","",VIPcric_1!G395) | H402: =IF(VIPcric_1!H395="","",VIPcric_1!H395) | I402: =IF(VIPcric_1!M395="","",VIPcric_1!M395) -> CRIC-北海-市场监测.广义存量.广义存量.xlsx
A403: =IF(VIPcric_1!A396="","",VIPcric_1!A396) | B403: =IF(VIPcric_1!B396="","",VIPcric_1!B396) | C403: =IF(VIPcric_1!C396="","",VIPcric_1!C396) | D403: =IF(VIPcric_1!D396="","",VIPcric_1!D396) | E403: =IF(VIPcric_1!E396="","",VIPcric_1!E396) | F403: =IF(VIPcric_1!F396="","",VIPcric_1!F396) | G403: =IF(VIPcric_1!G396="","",VIPcric_1!G396) | H403: =IF(VIPcric_1!H396="","",VIPcric_1!H396) | I403: =IF(VIPcric_1!M396="","",VIPcric_1!M396)
... A466: =IF(VIPcric_1!A459="","",VIPcric_1!A459) -> 2024年 | B466: =IF(VIPcric_1!B459="","",VIPcric_1!B459) -> 0 | C466: =IF(VIPcric_1!C459="","",VIPcric_1!C459) -> 0 | D466: =IF(VIPcric_1!D459="","",VIPcric_1!D459) -> 0 | E466: =IF(VIPcric_1!E459="","",VIPcric_1!E459) -> 0 | F466: =IF(VIPcric_1!F459="","",VIPcric_1!F459) | G466: =IF(VIPcric_1!G459="","",VIPcric_1!G459) | H466: =IF(VIPcric_1!H459="","",VIPcric_1!H459) | I466: =IF(VIPcric_1!M459="","",VIPcric_1!M459) -> CRIC-南通-市场监测.商品房市场.项目累计.库存.xlsx
A467: =IF(VIPcric_1!A460="","",VIPcric_1!A460) -> 2023年 | B467: =IF(VIPcric_1!B460="","",VIPcric_1!B460) -> 0 | C467: =IF(VIPcric_1!C460="","",VIPcric_1!C460) -> 0 | D467: =5*12 -> 60 | E467: =IF(VIPcric_1!E460="","",VIPcric_1!E460) -> 0 | F467: =IF(VIPcric_1!F460="","",VIPcric_1!F460) | G467: =IF(VIPcric_1!G460="","",VIPcric_1!G460) | H467: =IF(VIPcric_1!H460="","",VIPcric_1!H460) | I467: =IF(VIPcric_1!M460="","",VIPcric_1!M460) -> CRIC-南通-市场监测.商品房市场.项目累计.库存.xlsx | N467: 南通房价四连跌,南通市区新房去化周期突破5年 南通楼市在2023年里面,不含通州、海门的话,一共才只有5124套新房卖出去,而当下南通市区的新房库存量却达到了2.1万套,如果说按照这个一年才卖出去5000多套新房的成交量,南通楼市的去化时间需要5年以上。 而且南通可不止新房库存量高,南通楼市的待售二手房数量也同样比较多,南通楼市的待售二手房数量达到了68000多套,这么多的待售二手房,南通楼市的压力可想而知了。 南通的常住人口有774万,看着多,但南通的老龄化也很严重,这也意味着,南通楼市的消费欲望不会太高。 南通房价后期应该还是有下跌的空间,在南通买房的人还是要悠着点,不要太盲目了。 南通每年的外来人口数量也不多,这也意味着南通楼市想要增加需求,就只能靠内部了,之前有棚改拆迁,现在棚改的
A468: =IF(VIPcric_1!A461="","",VIPcric_1!A461) -> 2022年 | B468: =IF(VIPcric_1!B461="","",VIPcric_1!B461) -> 0 | C468: =IF(VIPcric_1!C461="","",VIPcric_1!C461) -> 0 | D468: =IF(VIPcric_1!D461="","",VIPcric_1!D461) -> 0 | E468: =IF(VIPcric_1!E461="","",VIPcric_1!E461) -> 0 | F468: =IF(VIPcric_1!F461="","",VIPcric_1!F461) | G468: =IF(VIPcric_1!G461="","",VIPcric_1!G461) | H468: =IF(VIPcric_1!H461="","",VIPcric_1!H461) | I468: =IF(VIPcric_1!M461="","",VIPcric_1!M461) -> CRIC-南通-市场监测.商品房市场.项目累计.库存.xlsx
A469: =IF(VIPcric_1!A462="","",VIPcric_1!A462) -> 2021年 | B469: =IF(VIPcric_1!B462="","",VIPcric_1!B462) -> 0 | C469: =IF(VIPcric_1!C462="","",VIPcric_1!C462) -> 0 | D469: =IF(VIPcric_1!D462="","",VIPcric_1!D462) -> 0 | E469: =IF(VIPcric_1!E462="","",VIPcric_1!E462) -> 0 | F469: =IF(VIPcric_1!F462="","",VIPcric_1!F462) | G469: =IF(VIPcric_1!G462="","",VIPcric_1!G462) | H469: =IF(VIPcric_1!H462="","",VIPcric_1!H462) | I469: =IF(VIPcric_1!M462="","",VIPcric_1!M462) -> CRIC-南通-市场监测.商品房市场.项目累计.库存.xlsx
A470: =IF(VIPcric_1!A463="","",VIPcric_1!A463) -> 2020年 | B470: =IF(VIPcric_1!B463="","",VIPcric_1!B463) -> 0 | C470: =IF(VIPcric_1!C463="","",VIPcric_1!C463) -> 0 | D470: =IF(VIPcric_1!D463="","",VIPcric_1!D463) -> 0 | E470: =IF(VIPcric_1!E463="","",VIPcric_1!E463) -> 0 | F470: =IF(VIPcric_1!F463="","",VIPcric_1!F463) | G470: =IF(VIPcric_1!G463="","",VIPcric_1!G463) | H470: =IF(VIPcric_1!H463="","",VIPcric_1!H463) | I470: =IF(VIPcric_1!M463="","",VIPcric_1!M463) -> CRIC-南通-市场监测.商品房市场.项目累计.库存.xlsx
A471: =IF(VIPcric_1!A464="","",VIPcric_1!A464) -> 2019年 | B471: =IF(VIPcric_1!B464="","",VIPcric_1!B464) -> 898886 | C471: =IF(VIPcric_1!C464="","",VIPcric_1!C464) -> 7172 | D471: =IF(VIPcric_1!D464="","",VIPcric_1!D464) -> 3.7 | E471: =IF(VIPcric_1!E464="","",VIPcric_1!E464) -> 3.9 | F471: =IF(VIPcric_1!F464="","",VIPcric_1!F464) | G471: =IF(VIPcric_1!G464="","",VIPcric_1!G464) | H471: =IF(VIPcric_1!H464="","",VIPcric_1!H464) | I471: =IF(VIPcric_1!M464="","",VIPcric_1!M464) -> CRIC-南通-市场监测.商品房市场.项目累计.库存.xlsx
A472: =IF(VIPcric_1!A465="","",VIPcric_1!A465) | B472: =IF(VIPcric_1!B465="","",VIPcric_1!B465) | C472: =IF(VIPcric_1!C465="","",VIPcric_1!C465) | D472: =IF(VIPcric_1!D465="","",VIPcric_1!D465) | E472: =IF(VIPcric_1!E465="","",VIPcric_1!E465) | F472: =IF(VIPcric_1!F465="","",VIPcric_1!F465) | G472: =IF(VIPcric_1!G465="","",VIPcric_1!G465) | H472: =IF(VIPcric_1!H465="","",VIPcric_1!H465) | I472: =IF(VIPcric_1!M465="","",VIPcric_1!M465)
A473: =IF(VIPcric_1!A466="","",VIPcric_1!A466) | B473: =IF(VIPcric_1!B466="","",VIPcric_1!B466) | C473: =IF(VIPcric_1!C466="","",VIPcric_1!C466) | D473: =IF(VIPcric_1!D466="","",VIPcric_1!D466) | E473: =IF(VIPcric_1!E466="","",VIPcric_1!E466) | F473: =IF(VIPcric_1!F466="","",VIPcric_1!F466) | G473: =IF(VIPcric_1!G466="","",VIPcric_1!G466) | H473: =IF(VIPcric_1!H466="","",VIPcric_1!H466) | I473: =IF(VIPcric_1!M466="","",VIPcric_1!M466) -> CRIC-厦门-市场监测.商品房市场.项目累计.供求.xlsx
A474: =IF(VIPcric_1!A467="","",VIPcric_1!A467) -> 时间(年) | B474: =IF(VIPcric_1!B467="","",VIPcric_1!B467) -> 供应面积(㎡) | C474: =IF(VIPcric_1!C467="","",VIPcric_1!C467) -> 供应套数(套) | D474: =IF(VIPcric_1!D467="","",VIPcric_1!D467) -> 成交面积(㎡) | E474: =IF(VIPcric_1!E467="","",VIPcric_1!E467) -> 成交套数(套) | F474: =IF(VIPcric_1!F467="","",VIPcric_1!F467) -> 成交均价(元/㎡) | G474: =IF(VIPcric_1!G467="","",VIPcric_1!G467) -> 成交金额(元) | H474: =IF(VIPcric_1!H467="","",VIPcric_1!H467) -> 供求比 | I474: =IF(VIPcric_1!M467="","",VIPcric_1!M467) -> CRIC-厦门-市场监测.商品房市场.项目累计.供求.xlsx
A475: =IF(VIPcric_1!A468="","",VIPcric_1!A468) -> 2023年 | B475: =IF(VIPcric_1!B468="","",VIPcric_1!B468) -> 1867715 | C475: =IF(VIPcric_1!C468="","",VIPcric_1!C468) -> 16742 | D475: =IF(VIPcric_1!D468="","",VIPcric_1!D468) -> 1921051 | E475: =IF(VIPcric_1!E468="","",VIPcric_1!E468) -> 17729 | F475: =IF(VIPcric_1!F468="","",VIPcric_1!F468) -> 43024 | G475: =IF(VIPcric_1!G468="","",VIPcric_1!G468) -> 82651348150 | H475: =IF(VIPcric_1!H468="","",VIPcric_1!H468) -> 0.97 | I475: =IF(VIPcric_1!M468="","",VIPcric_1!M468) -> CRIC-厦门-市场监测.商品房市场.项目累计.供求.xlsx
A476: =IF(VIPcric_1!A469="","",VIPcric_1!A469) -> 2022年 | B476: =IF(VIPcric_1!B469="","",VIPcric_1!B469) -> 1754852 | C476: =IF(VIPcric_1!C469="","",VIPcric_1!C469) -> 16964 | D476: =IF(VIPcric_1!D469="","",VIPcric_1!D469) -> 1705933 | E476: =IF(VIPcric_1!E469="","",VIPcric_1!E469) -> 16273 | F476: =IF(VIPcric_1!F469="","",VIPcric_1!F469) -> 41324 | G476: =IF(VIPcric_1!G469="","",VIPcric_1!G469) -> 70495726312 | H476: =IF(VIPcric_1!H469="","",VIPcric_1!H469) -> 1.03 | I476: =IF(VIPcric_1!M469="","",VIPcric_1!M469) -> CRIC-厦门-市场监测.商品房市场.项目累计.供求.xlsx
A477: =IF(VIPcric_1!A470="","",VIPcric_1!A470) -> 2021年 | B477: =IF(VIPcric_1!B470="","",VIPcric_1!B470) -> 2934300 | C477: =IF(VIPcric_1!C470="","",VIPcric_1!C470) -> 29676 | D477: =IF(VIPcric_1!D470="","",VIPcric_1!D470) -> 3365625 | E477: =IF(VIPcric_1!E470="","",VIPcric_1!E470) -> 32945 | F477: =IF(VIPcric_1!F470="","",VIPcric_1!F470) -> 38208 | G477: =IF(VIPcric_1!G470="","",VIPcric_1!G470) -> 128594055506 | H477: =IF(VIPcric_1!H470="","",VIPcric_1!H470) -> 0.87 | I477: =IF(VIPcric_1!M470="","",VIPcric_1!M470) -> CRIC-厦门-市场监测.商品房市场.项目累计.供求.xlsx
A478: =IF(VIPcric_1!A471="","",VIPcric_1!A471) -> 2020年 | B478: =IF(VIPcric_1!B471="","",VIPcric_1!B471) -> 2594173 | C478: =IF(VIPcric_1!C471="","",VIPcric_1!C471) -> 23621 | D478: =IF(VIPcric_1!D471="","",VIPcric_1!D471) -> 2229551 | E478: =IF(VIPcric_1!E471="","",VIPcric_1!E471) -> 20418 | F478: =IF(VIPcric_1!F471="","",VIPcric_1!F471) -> 40237 | G478: =IF(VIPcric_1!G471="","",VIPcric_1!G471) -> 89710726190 | H478: =IF(VIPcric_1!H471="","",VIPcric_1!H471) -> 1.16 | I478: =IF(VIPcric_1!M471="","",VIPcric_1!M471) -> CRIC-厦门-市场监测.商品房市场.项目累计.供求.xlsx
A479: =IF(VIPcric_1!A472="","",VIPcric_1!A472) -> 2019年 | B479: =IF(VIPcric_1!B472="","",VIPcric_1!B472) -> 2332768 | C479: =IF(VIPcric_1!C472="","",VIPcric_1!C472) -> 22914 | D479: =IF(VIPcric_1!D472="","",VIPcric_1!D472) -> 1286276 | E479: =IF(VIPcric_1!E472="","",VIPcric_1!E472) -> 11860 | F479: =IF(VIPcric_1!F472="","",VIPcric_1!F472) -> 37758 | G479: =IF(VIPcric_1!G472="","",VIPcric_1!G472) -> 48567042983 | H479: =IF(VIPcric_1!H472="","",VIPcric_1!H472) -> 1.81 | I479: =IF(VIPcric_1!M472="","",VIPcric_1!M472) -> CRIC-厦门-市场监测.商品房市场.项目累计.供求.xlsx
... A501: =IF(VIPcric_1!A494="","",VIPcric_1!A494) -> 时间(年) | B501: =IF(VIPcric_1!B494="","",VIPcric_1!B494) -> 库存面积(㎡) | C501: =IF(VIPcric_1!C494="","",VIPcric_1!C494) -> 库存套数(套) | D501: =IF(VIPcric_1!D494="","",VIPcric_1!D494) -> 去化周期12'(月) | E501: =IF(VIPcric_1!E494="","",VIPcric_1!E494) | F501: =IF(VIPcric_1!F494="","",VIPcric_1!F494) | G501: =IF(VIPcric_1!G494="","",VIPcric_1!G494) | H501: =IF(VIPcric_1!H494="","",VIPcric_1!H494) | I501: =IF(VIPcric_1!M494="","",VIPcric_1!M494) -> CRIC-台州-市场监测.商品房市场.项目累计.库存.xlsx
A502: 2023
A503: =IF(VIPcric_1!A495="","",VIPcric_1!A495) -> 2020年 | B503: =IF(VIPcric_1!B495="","",VIPcric_1!B495) -> 5585604 | C503: =IF(VIPcric_1!C495="","",VIPcric_1!C495) -> 44678 | D503: =IF(VIPcric_1!D495="","",VIPcric_1!D495) -> 21.8 | E503: =IF(VIPcric_1!E495="","",VIPcric_1!E495) | F503: =IF(VIPcric_1!F495="","",VIPcric_1!F495) | G503: =IF(VIPcric_1!G495="","",VIPcric_1!G495) | H503: =IF(VIPcric_1!H495="","",VIPcric_1!H495) | I503: =IF(VIPcric_1!M495="","",VIPcric_1!M495) -> CRIC-台州-市场监测.商品房市场.项目累计.库存.xlsx
A504: =IF(VIPcric_1!A496="","",VIPcric_1!A496) -> 2019年 | B504: =IF(VIPcric_1!B496="","",VIPcric_1!B496) -> 4969463 | C504: =IF(VIPcric_1!C496="","",VIPcric_1!C496) -> 40092 | D504: =IF(VIPcric_1!D496="","",VIPcric_1!D496) -> 22.1 | E504: =IF(VIPcric_1!E496="","",VIPcric_1!E496) | F504: =IF(VIPcric_1!F496="","",VIPcric_1!F496) | G504: =IF(VIPcric_1!G496="","",VIPcric_1!G496) | H504: =IF(VIPcric_1!H496="","",VIPcric_1!H496) | I504: =IF(VIPcric_1!M496="","",VIPcric_1!M496) -> CRIC-台州-市场监测.商品房市场.项目累计.库存.xlsx
A505: =IF(VIPcric_1!A497="","",VIPcric_1!A497) -> 2018年 | B505: =IF(VIPcric_1!B497="","",VIPcric_1!B497) -> 3720758 | C505: =IF(VIPcric_1!C497="","",VIPcric_1!C497) -> 29674 | D505: =IF(VIPcric_1!D497="","",VIPcric_1!D497) -> 16.4 | E505: =IF(VIPcric_1!E497="","",VIPcric_1!E497) | F505: =IF(VIPcric_1!F497="","",VIPcric_1!F497) | G505: =IF(VIPcric_1!G497="","",VIPcric_1!G497) | H505: =IF(VIPcric_1!H497="","",VIPcric_1!H497) | I505: =IF(VIPcric_1!M497="","",VIPcric_1!M497) -> CRIC-台州-市场监测.商品房市场.项目累计.库存.xlsx
A506: =IF(VIPcric_1!A498="","",VIPcric_1!A498) | B506: =IF(VIPcric_1!B498="","",VIPcric_1!B498) | C506: =IF(VIPcric_1!C498="","",VIPcric_1!C498) | D506: =IF(VIPcric_1!D498="","",VIPcric_1!D498) | E506: =IF(VIPcric_1!E498="","",VIPcric_1!E498) | F506: =IF(VIPcric_1!F498="","",VIPcric_1!F498) | G506: =IF(VIPcric_1!G498="","",VIPcric_1!G498) | H506: =IF(VIPcric_1!H498="","",VIPcric_1!H498) | I506: =IF(VIPcric_1!M498="","",VIPcric_1!M498)
A507: =IF(VIPcric_1!A499="","",VIPcric_1!A499) | B507: =IF(VIPcric_1!B499="","",VIPcric_1!B499) | C507: =IF(VIPcric_1!C499="","",VIPcric_1!C499) | D507: =IF(VIPcric_1!D499="","",VIPcric_1!D499) | E507: =IF(VIPcric_1!E499="","",VIPcric_1!E499) | F507: =IF(VIPcric_1!F499="","",VIPcric_1!F499) | G507: =IF(VIPcric_1!G499="","",VIPcric_1!G499) | H507: =IF(VIPcric_1!H499="","",VIPcric_1!H499) | I507: =IF(VIPcric_1!M499="","",VIPcric_1!M499) -> CRIC-合肥-市场监测.商品房市场.项目累计.供求.xlsx
A508: =IF(VIPcric_1!A500="","",VIPcric_1!A500) -> 时间(年) | B508: =IF(VIPcric_1!B500="","",VIPcric_1!B500) -> 供应面积(㎡) | C508: =IF(VIPcric_1!C500="","",VIPcric_1!C500) -> 供应套数(套) | D508: =IF(VIPcric_1!D500="","",VIPcric_1!D500) -> 成交面积(㎡) | E508: =IF(VIPcric_1!E500="","",VIPcric_1!E500) -> 成交套数(套) | F508: =IF(VIPcric_1!F500="","",VIPcric_1!F500) -> 成交均价(元/㎡) | G508: =IF(VIPcric_1!G500="","",VIPcric_1!G500) -> 成交金额(元) | H508: =IF(VIPcric_1!H500="","",VIPcric_1!H500) -> 供求比 | I508: =IF(VIPcric_1!M500="","",VIPcric_1!M500) -> CRIC-合肥-市场监测.商品房市场.项目累计.供求.xlsx
A509: =IF(VIPcric_1!A501="","",VIPcric_1!A501) -> 2023年 | B509: =IF(VIPcric_1!B501="","",VIPcric_1!B501) -> 5022525 | C509: =IF(VIPcric_1!C501="","",VIPcric_1!C501) -> 40442 | D509: =IF(VIPcric_1!D501="","",VIPcric_1!D501) -> 4916760 | E509: =IF(VIPcric_1!E501="","",VIPcric_1!E501) -> 39407 | F509: =IF(VIPcric_1!F501="","",VIPcric_1!F501) -> 21353 | G509: =IF(VIPcric_1!G501="","",VIPcric_1!G501) -> 104985463671 | H509: =IF(VIPcric_1!H501="","",VIPcric_1!H501) -> 1.02 | I509: =IF(VIPcric_1!M501="","",VIPcric_1!M501) -> CRIC-合肥-市场监测.商品房市场.项目累计.供求.xlsx
A510: =IF(VIPcric_1!A502="","",VIPcric_1!A502) -> 2022年 | B510: =IF(VIPcric_1!B502="","",VIPcric_1!B502) -> 5843841 | C510: =IF(VIPcric_1!C502="","",VIPcric_1!C502) -> 50076 | D510: =IF(VIPcric_1!D502="","",VIPcric_1!D502) -> 5395120 | E510: =IF(VIPcric_1!E502="","",VIPcric_1!E502) -> 44268 | F510: =IF(VIPcric_1!F502="","",VIPcric_1!F502) -> 19788 | G510: =IF(VIPcric_1!G502="","",VIPcric_1!G502) -> 106758047352 | H510: =IF(VIPcric_1!H502="","",VIPcric_1!H502) -> 1.08 | I510: =IF(VIPcric_1!M502="","",VIPcric_1!M502) -> CRIC-合肥-市场监测.商品房市场.项目累计.供求.xlsx
A511: =IF(VIPcric_1!A503="","",VIPcric_1!A503) -> 2021年 | B511: =IF(VIPcric_1!B503="","",VIPcric_1!B503) -> 6399170 | C511: =IF(VIPcric_1!C503="","",VIPcric_1!C503) -> 53585 | D511: =IF(VIPcric_1!D503="","",VIPcric_1!D503) -> 8118144 | E511: =IF(VIPcric_1!E503="","",VIPcric_1!E503) -> 66655 | F511: =IF(VIPcric_1!F503="","",VIPcric_1!F503) -> 18157 | G511: =IF(VIPcric_1!G503="","",VIPcric_1!G503) -> 147397946000 | H511: =IF(VIPcric_1!H503="","",VIPcric_1!H503) -> 0.79 | I511: =IF(VIPcric_1!M503="","",VIPcric_1!M503) -> CRIC-合肥-市场监测.商品房市场.项目累计.供求.xlsx
A512: =IF(VIPcric_1!A504="","",VIPcric_1!A504) -> 2020年 | B512: =IF(VIPcric_1!B504="","",VIPcric_1!B504) -> 7241576 | C512: =IF(VIPcric_1!C504="","",VIPcric_1!C504) -> 59813 | D512: =IF(VIPcric_1!D504="","",VIPcric_1!D504) -> 8034991 | E512: =IF(VIPcric_1!E504="","",VIPcric_1!E504) -> 67323 | F512: =IF(VIPcric_1!F504="","",VIPcric_1!F504) -> 19584 | G512: =IF(VIPcric_1!G504="","",VIPcric_1!G504) -> 157356393939 | H512: =IF(VIPcric_1!H504="","",VIPcric_1!H504) -> 0.9 | I512: =IF(VIPcric_1!M504="","",VIPcric_1!M504) -> CRIC-合肥-市场监测.商品房市场.项目累计.供求.xlsx
A513: =IF(VIPcric_1!A505="","",VIPcric_1!A505) -> 2019年 | B513: =IF(VIPcric_1!B505="","",VIPcric_1!B505) -> 7300588 | C513: =IF(VIPcric_1!C505="","",VIPcric_1!C505) -> 61225 | D513: =IF(VIPcric_1!D505="","",VIPcric_1!D505) -> 6680407 | E513: =IF(VIPcric_1!E505="","",VIPcric_1!E505) -> 58136 | F513: =IF(VIPcric_1!F505="","",VIPcric_1!F505) -> 17847 | G513: =IF(VIPcric_1!G505="","",VIPcric_1!G505) -> 119228483350 | H513: =IF(VIPcric_1!H505="","",VIPcric_1!H505) -> 1.09 | I513: =IF(VIPcric_1!M505="","",VIPcric_1!M505) -> CRIC-合肥-市场监测.商品房市场.项目累计.供求.xlsx
A514: =IF(VIPcric_1!A506="","",VIPcric_1!A506) -> 汇总 | B514: =IF(VIPcric_1!B506="","",VIPcric_1!B506) -> 31807700 | C514: =IF(VIPcric_1!C506="","",VIPcric_1!C506) -> 265141 | D514: =IF(VIPcric_1!D506="","",VIPcric_1!D506) -> 33145422 | E514: =IF(VIPcric_1!E506="","",VIPcric_1!E506) -> 275789 | F514: =IF(VIPcric_1!F506="","",VIPcric_1!F506) -> 19180 | G514: =IF(VIPcric_1!G506="","",VIPcric_1!G506) -> 635726334311 | H514: =IF(VIPcric_1!H506="","",VIPcric_1!H506) -> 0.96 | I514: =IF(VIPcric_1!M506="","",VIPcric_1!M506) -> CRIC-合肥-市场监测.商品房市场.项目累计.供求.xlsx
... A549: =IF(VIPcric_1!A541="","",VIPcric_1!A541) -> 汇总 | B549: =IF(VIPcric_1!B541="","",VIPcric_1!B541) -> 6801476 | C549: =IF(VIPcric_1!C541="","",VIPcric_1!C541) -> 66086 | D549: =IF(VIPcric_1!D541="","",VIPcric_1!D541) -> 5678861 | E549: =IF(VIPcric_1!E541="","",VIPcric_1!E541) -> 56217 | F549: =IF(VIPcric_1!F541="","",VIPcric_1!F541) -> 12745 | G549: =IF(VIPcric_1!G541="","",VIPcric_1!G541) -> 72377198627 | H549: =IF(VIPcric_1!H541="","",VIPcric_1!H541) -> 1.2 | I549: =IF(VIPcric_1!M541="","",VIPcric_1!M541) -> CRIC-启东-市场监测.商品房市场.项目累计.供求.xlsx
I550: =IF(VIPcric_1!M542="","",VIPcric_1!M542)
A551: =A565 -> 时间(年) | B551: =B565 -> 库存面积(㎡) | C551: =C565 -> 库存套数(套) | D551: =D565 -> 去化周期12'(月) | E551: =E565 -> 去化周期24'(月) | F551: =F565 | I551: =I549 -> CRIC-启东-市场监测.商品房市场.项目累计.供求.xlsx
A552: 2023 | B552: =IF(VIPcric_1!B542="","",VIPcric_1!B542) | C552: =IF(VIPcric_1!C542="","",VIPcric_1!C542) | D552: 59 | E552: =IF(VIPcric_1!E542="","",VIPcric_1!E542) | F552: =IF(VIPcric_1!F542="","",VIPcric_1!F542) | G552: =IF(VIPcric_1!G542="","",VIPcric_1!G542) | H552: =IF(VIPcric_1!H542="","",VIPcric_1!H542) | I552: =I551 -> CRIC-启东-市场监测.商品房市场.项目累计.供求.xlsx
A554: =IF(VIPcric_1!A543="","",VIPcric_1!A543) | B554: =IF(VIPcric_1!B543="","",VIPcric_1!B543) | C554: =IF(VIPcric_1!C543="","",VIPcric_1!C543) | D554: =IF(VIPcric_1!D543="","",VIPcric_1!D543) | E554: =IF(VIPcric_1!E543="","",VIPcric_1!E543) | F554: =IF(VIPcric_1!F543="","",VIPcric_1!F543) | G554: =IF(VIPcric_1!G543="","",VIPcric_1!G543) | H554: =IF(VIPcric_1!H543="","",VIPcric_1!H543) | I554: =IF(VIPcric_1!M543="","",VIPcric_1!M543) -> CRIC-吴忠-市场监测.商品房市场.项目累计.供求.xlsx
A555: =IF(VIPcric_1!A544="","",VIPcric_1!A544) -> 时间(年) | B555: =IF(VIPcric_1!B544="","",VIPcric_1!B544) -> 供应面积(㎡) | C555: =IF(VIPcric_1!C544="","",VIPcric_1!C544) -> 供应套数(套) | D555: =IF(VIPcric_1!D544="","",VIPcric_1!D544) -> 成交面积(㎡) | E555: =IF(VIPcric_1!E544="","",VIPcric_1!E544) -> 成交套数(套) | F555: =IF(VIPcric_1!F544="","",VIPcric_1!F544) -> 成交均价(元/㎡) | G555: =IF(VIPcric_1!G544="","",VIPcric_1!G544) -> 成交金额(元) | H555: =IF(VIPcric_1!H544="","",VIPcric_1!H544) -> 供求比 | I555: =IF(VIPcric_1!M544="","",VIPcric_1!M544) -> CRIC-吴忠-市场监测.商品房市场.项目累计.供求.xlsx
A556: =IF(VIPcric_1!A545="","",VIPcric_1!A545) -> 2024年 | B556: =IF(VIPcric_1!B545="","",VIPcric_1!B545) -> 0 | C556: =IF(VIPcric_1!C545="","",VIPcric_1!C545) -> 0 | D556: =IF(VIPcric_1!D545="","",VIPcric_1!D545) -> 158095 | E556: =IF(VIPcric_1!E545="","",VIPcric_1!E545) -> 1159 | F556: =IF(VIPcric_1!F545="","",VIPcric_1!F545) -> 5658 | G556: =IF(VIPcric_1!G545="","",VIPcric_1!G545) -> 894582036 | H556: =IF(VIPcric_1!H545="","",VIPcric_1!H545) -> 0 | I556: =IF(VIPcric_1!M545="","",VIPcric_1!M545) -> CRIC-吴忠-市场监测.商品房市场.项目累计.供求.xlsx
A557: =IF(VIPcric_1!A546="","",VIPcric_1!A546) -> 2023年 | B557: =IF(VIPcric_1!B546="","",VIPcric_1!B546) -> 1935925 | C557: =IF(VIPcric_1!C546="","",VIPcric_1!C546) -> 14468 | D557: =IF(VIPcric_1!D546="","",VIPcric_1!D546) -> 1541414 | E557: =IF(VIPcric_1!E546="","",VIPcric_1!E546) -> 11701 | F557: =IF(VIPcric_1!F546="","",VIPcric_1!F546) -> 5487 | G557: =IF(VIPcric_1!G546="","",VIPcric_1!G546) -> 8457702142 | H557: =IF(VIPcric_1!H546="","",VIPcric_1!H546) -> 1.26 | I557: =IF(VIPcric_1!M546="","",VIPcric_1!M546) -> CRIC-吴忠-市场监测.商品房市场.项目累计.供求.xlsx
A558: =IF(VIPcric_1!A547="","",VIPcric_1!A547) -> 2022年 | B558: =IF(VIPcric_1!B547="","",VIPcric_1!B547) -> 1560340 | C558: =IF(VIPcric_1!C547="","",VIPcric_1!C547) -> 11842 | D558: =IF(VIPcric_1!D547="","",VIPcric_1!D547) -> 1187728 | E558: =IF(VIPcric_1!E547="","",VIPcric_1!E547) -> 9136 | F558: =IF(VIPcric_1!F547="","",VIPcric_1!F547) -> 5397 | G558: =IF(VIPcric_1!G547="","",VIPcric_1!G547) -> 6410380397 | H558: =IF(VIPcric_1!H547="","",VIPcric_1!H547) -> 1.31 | I558: =IF(VIPcric_1!M547="","",VIPcric_1!M547) -> CRIC-吴忠-市场监测.商品房市场.项目累计.供求.xlsx
A559: =IF(VIPcric_1!A548="","",VIPcric_1!A548) -> 2021年 | B559: =IF(VIPcric_1!B548="","",VIPcric_1!B548) -> 1557321 | C559: =IF(VIPcric_1!C548="","",VIPcric_1!C548) -> 11814 | D559: =IF(VIPcric_1!D548="","",VIPcric_1!D548) -> 691672 | E559: =IF(VIPcric_1!E548="","",VIPcric_1!E548) -> 5334 | F559: =IF(VIPcric_1!F548="","",VIPcric_1!F548) -> 5577 | G559: =IF(VIPcric_1!G548="","",VIPcric_1!G548) -> 3857597890 | H559: =IF(VIPcric_1!H548="","",VIPcric_1!H548) -> 2.25 | I559: =IF(VIPcric_1!M548="","",VIPcric_1!M548) -> CRIC-吴忠-市场监测.商品房市场.项目累计.供求.xlsx
A560: =IF(VIPcric_1!A549="","",VIPcric_1!A549) -> 2020年 | B560: =IF(VIPcric_1!B549="","",VIPcric_1!B549) -> 1218523 | C560: =IF(VIPcric_1!C549="","",VIPcric_1!C549) -> 9306 | D560: =IF(VIPcric_1!D549="","",VIPcric_1!D549) -> 0 | E560: =IF(VIPcric_1!E549="","",VIPcric_1!E549) -> 0 | F560: =IF(VIPcric_1!F549="","",VIPcric_1!F549) -> 0 | G560: =IF(VIPcric_1!G549="","",VIPcric_1!G549) -> 0 | H560: =IF(VIPcric_1!H549="","",VIPcric_1!H549) -> 0 | I560: =IF(VIPcric_1!M549="","",VIPcric_1!M549) -> CRIC-吴忠-市场监测.商品房市场.项目累计.供求.xlsx
A561: =IF(VIPcric_1!A550="","",VIPcric_1!A550) -> 2019年 | B561: =IF(VIPcric_1!B550="","",VIPcric_1!B550) -> 1295055 | C561: =IF(VIPcric_1!C550="","",VIPcric_1!C550) -> 9986 | D561: =IF(VIPcric_1!D550="","",VIPcric_1!D550) -> 0 | E561: =IF(VIPcric_1!E550="","",VIPcric_1!E550) -> 0 | F561: =IF(VIPcric_1!F550="","",VIPcric_1!F550) -> 0 | G561: =IF(VIPcric_1!G550="","",VIPcric_1!G550) -> 0 | H561: =IF(VIPcric_1!H550="","",VIPcric_1!H550) -> 0 | I561: =IF(VIPcric_1!M550="","",VIPcric_1!M550) -> CRIC-吴忠-市场监测.商品房市场.项目累计.供求.xlsx
A562: =IF(VIPcric_1!A551="","",VIPcric_1!A551) -> 汇总 | B562: =IF(VIPcric_1!B551="","",VIPcric_1!B551) -> 7567163 | C562: =IF(VIPcric_1!C551="","",VIPcric_1!C551) -> 57416 | D562: =IF(VIPcric_1!D551="","",VIPcric_1!D551) -> 3578909 | E562: =IF(VIPcric_1!E551="","",VIPcric_1!E551) -> 27330 | F562: =IF(VIPcric_1!F551="","",VIPcric_1!F551) -> 5482 | G562: =IF(VIPcric_1!G551="","",VIPcric_1!G551) -> 19620262465 | H562: =IF(VIPcric_1!H551="","",VIPcric_1!H551) -> 2.11 | I562: =IF(VIPcric_1!M551="","",VIPcric_1!M551) -> CRIC-吴忠-市场监测.商品房市场.项目累计.供求.xlsx
A563: =IF(VIPcric_1!A552="","",VIPcric_1!A552) | B563: =IF(VIPcric_1!B552="","",VIPcric_1!B552) | C563: =IF(VIPcric_1!C552="","",VIPcric_1!C552) | D563: =IF(VIPcric_1!D552="","",VIPcric_1!D552) | E563: =IF(VIPcric_1!E552="","",VIPcric_1!E552) | F563: =IF(VIPcric_1!F552="","",VIPcric_1!F552) | G563: =IF(VIPcric_1!G552="","",VIPcric_1!G552) | H563: =IF(VIPcric_1!H552="","",VIPcric_1!H552) | I563: =IF(VIPcric_1!M552="","",VIPcric_1!M552)
A564: =IF(VIPcric_1!A553="","",VIPcric_1!A553) | B564: =IF(VIPcric_1!B553="","",VIPcric_1!B553) | C564: =IF(VIPcric_1!C553="","",VIPcric_1!C553) | D564: =IF(VIPcric_1!D553="","",VIPcric_1!D553) | E564: =IF(VIPcric_1!E553="","",VIPcric_1!E553) | F564: =IF(VIPcric_1!F553="","",VIPcric_1!F553) | G564: =IF(VIPcric_1!G553="","",VIPcric_1!G553) | H564: =IF(VIPcric_1!H553="","",VIPcric_1!H553) | I564: =IF(VIPcric_1!M553="","",VIPcric_1!M553) -> CRIC-吴忠-市场监测.商品房市场.项目累计.库存.xlsx
A565: =IF(VIPcric_1!A554="","",VIPcric_1!A554) -> 时间(年) | B565: =IF(VIPcric_1!B554="","",VIPcric_1!B554) -> 库存面积(㎡) | C565: =IF(VIPcric_1!C554="","",VIPcric_1!C554) -> 库存套数(套) | D565: =IF(VIPcric_1!D554="","",VIPcric_1!D554) -> 去化周期12'(月) | E565: =IF(VIPcric_1!E554="","",VIPcric_1!E554) -> 去化周期24'(月) | F565: =IF(VIPcric_1!F554="","",VIPcric_1!F554) | G565: =IF(VIPcric_1!G554="","",VIPcric_1!G554) | H565: =IF(VIPcric_1!H554="","",VIPcric_1!H554) | I565: =IF(VIPcric_1!M554="","",VIPcric_1!M554) -> CRIC-吴忠-市场监测.商品房市场.项目累计.库存.xlsx
... A699: =IF(VIPcric_1!A688="","",VIPcric_1!A688) | B699: =IF(VIPcric_1!B688="","",VIPcric_1!B688) | C699: =IF(VIPcric_1!C688="","",VIPcric_1!C688) | D699: =IF(VIPcric_1!D688="","",VIPcric_1!D688) | E699: =IF(VIPcric_1!E688="","",VIPcric_1!E688) | F699: =IF(VIPcric_1!F688="","",VIPcric_1!F688) | G699: =IF(VIPcric_1!G688="","",VIPcric_1!G688) | H699: =IF(VIPcric_1!H688="","",VIPcric_1!H688) | I699: =IF(VIPcric_1!M688="","",VIPcric_1!M688) -> CRIC-大连-市场监测.商品房市场.城市总量.xlsx
...

Sheet VIPcric_3
A1: City | B1: 城市 | C1: Province | D1: 售价 | E1: 去化周期 | F1: 标准工期 | G1: 峰值占用 | H1: 机会成本 | I1: 机会成本占售价比例 | J1: 峰值占用比例
A2: =VIPcric_2!I3 -> CRIC-万宁-市场监测.商品房市场.项目累计.供求.xlsx | B2: =MID(A2,6,2) -> 万宁 | C2: Hainan | D2: =VIPcric_2!F3 -> 16309 | E2: =VIPcric_2!D12 -> 59.8 | F2: =万宁!P4 -> 27.141667 | G2: =万宁!E89 -> 1745.4448 | H2: =万宁!M88 -> 77.859793 | I2: =H2/D2 -> 0.0047740385 | J2: =G2/D2 -> 0.10702341
A3: =VIPcric_2!I28 -> CRIC-上海-市场监测.商品房市场.项目累计.供求.xlsx | B3: =MID(A3,6,2) -> 上海 | C3: Shanghai | D3: =VIPcric_2!F28 -> 66494 | E3: =VIPcric_2!D37 -> 26.4 | F3: =上海!P4 -> 27.141667 | G3: =上海!E89 -> 35261.97 | H3: =上海!M88 -> 2507.4199 | I3: =H3/D3 -> 0.037708965 | J3: =G3/D3 -> 0.53030303
A4: =VIPcric_2!I45 -> CRIC-上饶-市场监测.商品房市场.项目累计.供求.xlsx | B4: =MID(A4,6,2) -> 上饶 | C4: Jiangxi | D4: =VIPcric_2!F45 -> 7893 | E4: =VIPcric_2!D54 -> 11.5 | F4: =上饶!P4 -> 27.141667 | G4: =上饶!E89 -> 1235.4261 | H4: =上饶!M88 -> 165.16102 | I4: =H4/D4 -> 0.020925 | J4: =G4/D4 -> 0.15652174
A5: =VIPcric_2!I62 -> CRIC-东方-市场监测.商品房市场.项目累计.供求.xlsx | B5: =MID(A5,6,2) -> 东方 | C5: Hainan | D5: =VIPcric_2!F63 -> 12405 | E5: =VIPcric_2!D71 -> 61.7 | F5: =东方!Q4 -> 27.141667 | G5: =东方!F89 -> 1256.5843 | H5: =东方!N88 -> 71.444356 | I5: =H5/D5 -> 0.0057593193 | J5: =G5/D5 -> 0.1012966
A6: =VIPcric_2!I77 -> CRIC-东莞-市场监测.商品房市场.项目累计.供求.xlsx | B6: =MID(A6,6,2) -> 东莞 | C6: Guangdong | D6: =VIPcric_2!F77 -> 36305 | E6: =VIPcric_2!D86 -> 25.6 | F6: =东莞!S4 -> 27.141667 | G6: =东莞!F89 -> 14819.814 | H6: =东莞!P88 -> 999.32703 | I6: =H6/D6 -> 0.027525879 | J6: =G6/D6 -> 0.40820312
A7: =VIPcric_2!I94 -> CRIC-东营-市场监测.商品房市场.项目累计.供求.xlsx | B7: =MID(A7,6,2) -> 东营 | C7: Shandong | D7: =VIPcric_2!F94 -> 8079 | E7: =VIPcric_2!D104 -> 52.3 | F7: =东营!S4 -> 28.008333 | G7: =东营!F89 -> 1668.3212 | H7: =东营!P88 -> 133.50045 | I7: =H7/D7 -> 0.016524379 | J7: =G7/D7 -> 0.20650096
A8: =VIPcric_2!I111 -> CRIC-中卫-市场监测.商品房市场.项目累计.供求.xlsx | B8: =MID(A8,6,2) -> 中卫 | C8: Ningxia | D8: =VIPcric_2!F111 -> 4898 | E8: =VIPcric_2!E121 -> 55.1 | F8: =中卫!P4 -> 28.008333 | G8: =中卫!E89 -> 978.71107 | H8: =中卫!M88 -> 70.222186 | I8: =H8/D8 -> 0.01433691 | J8: =G8/D8 -> 0.19981851
A9: =VIPcric_2!I127 -> CRIC-中山-市场监测.商品房市场.项目累计.供求.xlsx | B9: =MID(A9,6,2) -> 中山 | C9: Guangdong | D9: =VIPcric_2!F127 -> 13988 | E9: =VIPcric_2!H137 -> 22.6 | F9: =中山!S4 -> 27.141667 | G9: =中山!F89 -> 3500 | H9: =中山!P88 -> 336.375 | I9: =H9/D9 -> 0.024047398 | J9: =G9/D9 -> 0.25021447
A10: =VIPcric_2!I145 -> CRIC-临高-市场监测.商品房市场.项目累计.供求.xlsx | B10: =MID(A10,6,2) -> 临高 | C10: Hainan | D10: =VIPcric_2!F146 -> 10601 | E10: =VIPcric_2!D154 -> 73.6 | F10: =临高!P4 -> 27.141667 | G10: =临高!E98 -> 965.03668 | H10: =临高!M97 -> 44.474508 | I10: =H10/D10 -> 0.0041953125 | J10: =G10/D10 -> 0.091032609
A11: =VIPcric_2!I160 -> CRIC-丽水-市场监测.商品房市场.项目累计.供求.xlsx | B11: =MID(A11,6,2) -> 丽水 | C11: Zhejiang | D11: =VIPcric_2!F160 -> 12875 | E11: =VIPcric_2!D170 -> 43.7 | F11: =丽水!S4 -> 27.141667 | G11: =丽水!F89 -> 2622.1396 | H11: =丽水!P88 -> 174.956 | I11: =H11/D11 -> 0.013588816 | J11: =G11/D11 -> 0.20366133
A12: =VIPcric_2!I178 -> CRIC-义乌-市场监测.商品房市场.项目累计.供求.xlsx | B12: =MID(A12,6,2) -> 义乌 | C12: Zhejiang | D12: =VIPcric_2!F178 -> 30654 | E12: =VIPcric_2!D189 -> 21.1 | F12: =义乌!S4 -> 27.141667 | G12: =义乌!F89 -> 12929.886 | H12: =义乌!P88 -> 862.71579 | I12: =H12/D12 -> 0.028143661 | J12: =G12/D12 -> 0.42180095
A13: =VIPcric_2!I208 -> CRIC-乐东-市场监测.商品房市场.项目累计.供求.xlsx | B13: =MID(A13,6,2) -> 乐东 | C13: Hainan | D13: =VIPcric_2!F208 -> 11934 | E13: =VIPcric_2!D216 -> 126.4 | F13: =乐东县!P4 -> 27.141667 | G13: =乐东县!E117 -> 604.25316 | H13: =乐东县!M116 -> 26.954176 | I13: =H13/D13 -> 0.0022586036 | J13: =G13/D13 -> 0.050632911
A14: =VIPcric_2!I222 -> CRIC-乐山-市场监测.商品房市场.项目累计.供求.xlsx | B14: =MID(A14,6,2) -> 乐山 | C14: Sichuan | D14: =VIPcric_2!F222 -> 6016 | E14: =VIPcric_2!E232 -> 6.4 | F14: =乐山市!S4 -> 27.141667 | G14: =乐山市!F89 -> 3600 | H14: =乐山市!P88 -> 45.0225 | I14: =H14/D14 -> 0.0074837932 | J14: =G14/D14 -> 0.59840426
A15: =VIPcric_2!I238 -> CRIC-九江-市场监测.商品房市场.项目累计.供求.xlsx | B15: =MID(A15,6,2) -> 九江 | C15: Jiangxi | D15: =VIPcric_2!F238 -> 8624 | E15: =VIPcric_2!E248 -> 22.4 | F15: =九江!Q4 -> 27.141667 | G15: =九江!F89 -> 1724.8 | H15: =九江!N88 -> 100.26694 | I15: =H15/D15 -> 0.0116265 | J15: =G15/D15 -> 0.2
A16: =VIPcric_2!I257 -> CRIC-五指山-市场监测.商品房市场.项目累计.供求.xlsx | B16: =MID(A16,6,3) -> 五指山 | C16: Hainan | D16: =VIPcric_2!F257 -> 13585 | E16: =VIPcric_2!D265 -> 318.7 | F16: =五指山!Q4 -> 27.141667 | G16: =五指山!F89 -> 289.8588 | H16: =五指山!N88 -> 14.889897 | I16: =H16/D16 -> 0.0010960543 | J16: =G16/D16 -> 0.02133668
A17: =VIPcric_2!I271 -> CRIC-佛山-市场监测.商品房市场.项目累计.供求.xlsx | B17: =MID(A17,6,2) -> 佛山 | C17: Guangdong | D17: =VIPcric_2!F271 -> 18333 | E17: =VIPcric_2!D281 -> 19.9 | F17: =佛山!S4 -> 27.141667 | G17: =佛山!F89 -> 1372.6719 | H17: =佛山!P88 -> 66.268267 | I17: =H17/D17 -> 0.0036146985 | J17: =G17/D17 -> 0.074874372
A18: =VIPcric_2!I300 -> CRIC-信阳-市场监测.商品房市场.项目累计.供求.xlsx | B18: =MID(A18,6,2) -> 信阳 | C18: Henan | D18: =VIPcric_2!F299 -> 7100 | E18: =VIPcric_2!E310 -> 120 | F18: =信阳!S4 -> 28.008333 | G18: =信阳!F89 -> 426 | H18: =信阳!P88 -> 34.088875 | I18: =H18/D18 -> 0.00480125 | J18: =G18/D18 -> 0.06
A19: =VIPcric_2!I316 -> CRIC-儋州-市场监测.商品房市场.项目累计.供求.xlsx | B19: =MID(A19,6,2) -> 儋州 | C19: Hainan | D19: =VIPcric_2!F316 -> 10533 | E19: =VIPcric_2!D324 -> 82.5 | F19: =儋州!Q4 -> 27.141667 | G19: =儋州!F89 -> 1798.1091 | H19: =儋州!N88 -> 84.611564 | I19: =H19/D19 -> 0.0080329976 | J19: =G19/D19 -> 0.17071196
A20: =VIPcric_2!I330 -> CRIC-六安-市场监测.商品房市场.项目累计.供求.xlsx | B20: =MID(A20,6,2) -> 六安 | C20: Anhui | D20: =VIPcric_2!F330 -> 8031 | E20: =VIPcric_2!E340 -> 20.7 | F20: =六安!S4 -> 27.141667 | G20: =六安!F69 -> 2400 | H20: =六安!P68 -> 138.15337 | I20: =H20/D20 -> 0.017202512 | J20: =G20/D20 -> 0.29884199
A21: =VIPcric_2!I348 -> CRIC-兰州-市场监测.商品房市场.项目累计.供求.xlsx | B21: =MID(A21,6,2) -> 兰州 | C21: Gansu | D21: =VIPcric_2!F348 -> 10711 | E21: =VIPcric_2!D357 -> 52.1 | F21: =兰州!Q4 -> 28.008333 | G21: =兰州!Q10 -> 3600 | H21: =兰州!N88 -> 139.00073 | I21: =H21/D21 -> 0.012977381 | J21: =G21/D21 -> 0.33610307
A22: =VIPcric_2!I366 -> CRIC-北京-市场监测.商品房市场.项目累计.供求.xlsx | B22: =MID(A22,6,2) -> 北京 | C22: Beijing | D22: =VIPcric_2!F366 -> 40094 | E22: =VIPcric_2!E376 -> 19 | F22: =北京!Q4 -> 28.008333 | G22: =北京!F89 -> 5000 | H22: =北京!N88 -> 1175.8517 | I22: =H22/D22 -> 0.029327373 | J22: =G22/D22 -> 0.12470694
A23: =VIPcric_2!I391 -> CRIC-北海-市场监测.商品房市场.城市总量.xlsx | B23: =MID(A23,6,2) -> 北海 | C23: Guangxi | D23: =VIPcric_2!D391 -> 6800 | E23: =VIPcric_2!C401 -> 11.524897 | F23: =北海!Q4 -> 27.141667 | G23: =北海!F89 -> 2560.1079 | H23: =北海!N88 -> 315.86099 | I23: =H23/D23 -> 0.046450146 | J23: =G23/D23 -> 0.37648646
A24: =VIPcric_2!I406 -> CRIC-南京-市场监测.商品房市场.项目累计.供求.xlsx | B24: =MID(A24,6,2) -> 南京 | C24: Jiangsu | D24: =VIPcric_2!F406 -> 29181 | E24: =VIPcric_2!D415 -> 14.9 | F24: =(10+19+150+605*1.05)/30 -> 27.141667 | I24: =H24/D24 -> 0 | J24: =G24/D24 -> 0
A25: =VIPcric_2!I423 -> CRIC-南宁-市场监测.商品房市场.项目累计.供求.xlsx | B25: =MID(A25,6,2) -> 南宁 | C25: Guangxi | D25: =VIPcric_2!F423 -> 11733 | E25: =VIPcric_2!D432 -> 19.7 | F25: =(10+19+150+605*1.05)/30 -> 27.141667 | I25: =H25/D25 -> 0 | J25: =G25/D25 -> 0
A26: =VIPcric_2!I440 -> CRIC-南昌-市场监测.商品房市场.项目累计.供求.xlsx | B26: =MID(A26,6,2) -> 南昌 | C26: Jiangxi | D26: =VIPcric_2!F440 -> 13287 | E26: =VIPcric_2!D449 -> 7.4 | F26: =(10+19+150+605*1.05)/30 -> 27.141667 | I26: =H26/D26 -> 0 | J26: =G26/D26 -> 0
A27: =VIPcric_2!I457 -> CRIC-南通-市场监测.商品房市场.项目累计.供求.xlsx | B27: =MID(A27,6,2) -> 南通 | C27: Jiangsu | D27: =VIPcric_2!F457 -> 22233 | E27: =VIPcric_2!D467 -> 60 | F27: =(10+19+150+605*1.05)/30 -> 27.141667 | I27: =H27/D27 -> 0 | J27: =G27/D27 -> 0
A28: =VIPcric_2!I475 -> CRIC-厦门-市场监测.商品房市场.项目累计.供求.xlsx | B28: =MID(A28,6,2) -> 厦门 | C28: Fujian | D28: =VIPcric_2!F475 -> 43024 | E28: =VIPcric_2!D484 -> 16.1 | F28: =(10+19+150+605*1.05)/30 -> 27.141667 | I28: =H28/D28 -> 0 | J28: =G28/D28 -> 0
A29: =VIPcric_2!I509 -> CRIC-合肥-市场监测.商品房市场.项目累计.供求.xlsx | B29: =MID(A29,6,2) -> 合肥 | C29: Anhui | D29: =VIPcric_2!F509 -> 21353 | E29: =VIPcric_2!D518 -> 7.1 | F29: =(10+19+150+605*1.05)/30 -> 27.141667 | G29: =合肥!F69 -> 2400 | H29: =合肥!P68 -> 244.26 | I29: =H29/D29 -> 0.011439142 | J29: =G29/D29 -> 0.11239638
A30: =VIPcric_2!I526 -> CRIC-吉林-市场监测.商品房市场.项目累计.供求.xlsx | B30: =MID(A30,6,2) -> 吉林 | C30: Jilin | D30: =VIPcric_2!F526 -> 6593 | E30: =VIPcric_2!E536 -> 33.5 | F30: =(10+19+160+665*1.05)/30 -> 29.575 | I30: =H30/D30 -> 0 | J30: =G30/D30 -> 0
A31: =VIPcric_2!I544 -> CRIC-启东-市场监测.商品房市场.项目累计.供求.xlsx | B31: =MID(A31,6,2) -> 启东 | C31: Jiangsu | D31: =VIPcric_2!F544 -> 13606 | E31: 59 | F31: =(10+19+150+605*1.05)/30 -> 27.141667 | I31: =H31/D31 -> 0 | J31: =G31/D31 -> 0
A32: =VIPcric_2!I557 -> CRIC-吴忠-市场监测.商品房市场.项目累计.供求.xlsx | B32: =MID(A32,6,2) -> 吴忠 | C32: Ningxia | D32: =VIPcric_2!F557 -> 5487 | E32: =VIPcric_2!D566 -> 46.2 | F32: =(10+19+155+625*1.05)/30 -> 28.008333 | I32: =H32/D32 -> 0 | J32: =G32/D32 -> 0
A33: =VIPcric_2!I571 -> CRIC-呼和浩特-市场监测.商品房市场.项目累计.供求.xlsx | B33: =MID(A33,6,4) -> 呼和浩特 | C33: Inner mongolia | D33: =VIPcric_2!F571 -> 10230 | E33: =VIPcric_2!D580 -> 38.1 | F33: =(10+19+160+665*1.05)/30 -> 29.575 | I33: =H33/D33 -> 0 | J33: =G33/D33 -> 0
A34: =VIPcric_2!I588 -> CRIC-哈尔滨-市场监测.商品房市场.项目累计.供求.xlsx | B34: =MID(A34,6,3) -> 哈尔滨 | C34: Heilongjiang | D34: =VIPcric_2!F588 -> 12452 | E34: =VIPcric_2!D597 -> 59.8 | F34: =(10+19+160+665*1.05)/30 -> 29.575 | I34: =H34/D34 -> 0 | J34: =G34/D34 -> 0
A35: =VIPcric_2!I605 -> CRIC-嘉兴-市场监测.商品房市场.项目累计.供求.xlsx | B35: =MID(A35,6,2) -> 嘉兴 | C35: Zhejiang | D35: =VIPcric_2!F606 -> 17448 | E35: =VIPcric_2!D615 -> 14.6 | F35: =(10+19+150+605*1.05)/30 -> 27.141667 | I35: =H35/D35 -> 0 | J35: =G35/D35 -> 0
A36: =VIPcric_2!I622 -> CRIC-嘉善-市场监测.商品房市场.项目累计.供求.xlsx | B36: =MID(A36,6,2) -> 嘉善 | C36: Zhejiang | D36: =VIPcric_2!F622 -> 19253 | E36: =VIPcric_2!D632 -> 19.1 | F36: =(10+19+150+605*1.05)/30 -> 27.141667 | I36: =H36/D36 -> 0 | J36: =G36/D36 -> 0
A37: =VIPcric_2!I640 -> CRIC-嘉峪关-市场监测.商品房市场.项目累计.供求.xlsx | B37: =MID(A37,6,3) -> 嘉峪关 | C37: Gansu | D37: =VIPcric_2!F640 -> 4628 | E37: =VIPcric_2!D650 -> 68.6 | F37: =(10+19+155+625*1.05)/30 -> 28.008333 | I37: =H37/D37 -> 0 | J37: =G37/D37 -> 0
A38: =VIPcric_2!I658 -> CRIC-固原-市场监测.商品房市场.项目累计.供求 (1).xlsx | B38: =MID(A38,6,2) -> 固原 | C38: Ningxia | D38: =VIPcric_2!F658 -> 5329 | E38: =VIPcric_2!D676 -> 37.9 | F38: =(10+19+155+625*1.05)/30 -> 28.008333 | I38: =H38/D38 -> 0 | J38: =G38/D38 -> 0
A39: =VIPcric_2!I701 -> CRIC-大连-市场监测.商品房市场.城市总量.xlsx | B39: =MID(A39,6,2) -> 大连 | C39: Liaoning | D39: =VIPcric_2!F710 -> 13826 | E39: =VIPcric_2!E701 -> 27.831343 | F39: =(10+19+160+665*1.05)/30 -> 29.575 | I39: =H39/D39 -> 0 | J39: =G39/D39 -> 0
A40: =VIPcric_2!I719 -> CRIC-天水-市场监测.商品房市场.项目累计.供求.xlsx | B40: =MID(A40,6,2) -> 天水 | C40: Gansu | D40: =VIPcric_2!F719 -> 8149 | E40: =VIPcric_2!D729 -> 87.4 | F40: =(10+19+155+625*1.05)/30 -> 28.008333 | I40: =H40/D40 -> 0 | J40: =G40/D40 -> 0
A41: =VIPcric_2!I735 -> CRIC-天津-市场监测.商品房市场.项目累计.供求.xlsx | B41: =MID(A41,6,2) -> 天津 | C41: Tianjin | D41: =VIPcric_2!F735 -> 17772 | E41: =VIPcric_2!D744 -> 14.6 | F41: =(10+19+155+625*1.05)/30 -> 28.008333 | I41: =H41/D41 -> 0 | J41: =G41/D41 -> 0
A42: =VIPcric_2!I751 -> CRIC-太仓-市场监测.商品房市场.项目累计.供求.xlsx | B42: =MID(A42,6,2) -> 太仓 | C42: Jiangsu | D42: =VIPcric_2!F751 -> 18644 | E42: =VIPcric_2!D761 -> 16 | F42: =(10+19+150+605*1.05)/30 -> 27.141667 | I42: =H42/D42 -> 0 | J42: =G42/D42 -> 0
A43: =VIPcric_2!I769 -> CRIC-太原-市场监测.商品房市场.项目累计.供求.xlsx | B43: =MID(A43,6,2) -> 太原 | C43: Shanxi | D43: 10664 | E43: =VIPcric_2!D779 -> 14.3 | F43: =(10+19+155+625*1.05)/30 -> 28.008333 | I43: =H43/D43 -> 0 | J43: =G43/D43 -> 0
A44: =VIPcric_2!I783 -> CRIC-宁波-市场监测.商品房市场.项目累计.供求.xlsx | B44: =MID(A44,6,2) -> 宁波 | C44: Zhejiang | D44: =VIPcric_2!F783 -> 35117 | E44: =VIPcric_2!D792 -> 14.4 | F44: =(10+19+150+605*1.05)/30 -> 27.141667 | I44: =H44/D44 -> 0 | J44: =G44/D44 -> 0
A45: =VIPcric_2!I801 -> CRIC-安庆-市场监测.商品房市场.项目累计.供求.xlsx | B45: =MID(A45,6,2) -> 安庆 | C45: Anhui | D45: =VIPcric_2!F801 -> 8639 | E45: =VIPcric_2!D811 -> 13.5 | F45: =(10+19+150+605*1.05)/30 -> 27.141667 | I45: =H45/D45 -> 0 | J45: =G45/D45 -> 0
A46: =VIPcric_2!I819 -> CRIC-安顺-市场监测.商品房市场.项目累计.供求.xlsx | B46: =MID(A46,6,2) -> 安顺 | C46: Guizhou | D46: =VIPcric_2!F819 -> 4902 | E46: =VIPcric_2!D829 -> 54.8 | F46: =(10+19+150+605*1.05)/30 -> 27.141667 | I46: =H46/D46 -> 0 | J46: =G46/D46 -> 0
A47: =VIPcric_2!I836 -> CRIC-定安-市场监测.商品房市场.项目累计.供求.xlsx | B47: =MID(A47,6,2) -> 定安 | C47: Hainan | D47: =VIPcric_2!F836 -> 8030 | E47: =VIPcric_2!D846 -> 41.5 | F47: =(10+19+150+605*1.05)/30 -> 27.141667 | G47: =定安!F89 -> 1315.759 | H47: =定安!N88 -> 67.589864 | I47: =H47/D47 -> 0.0084171687 | J47: =G47/D47 -> 0.16385542
A48: =VIPcric_2!I853 -> CRIC-宜兴-市场监测.商品房市场.项目累计.供求.xlsx | B48: =MID(A48,6,2) -> 宜兴 | C48: Jiangsu | D48: =VIPcric_2!F853 -> 15313 | E48: =VIPcric_2!D863 -> 111.7 | F48: =(10+19+150+605*1.05)/30 -> 27.141667 | I48: =H48/D48 -> 0 | J48: =G48/D48 -> 0
A49: =VIPcric_2!I871 -> CRIC-宜宾-市场监测.商品房市场.项目累计.供求.xlsx | B49: =MID(A49,6,2) -> 宜宾 | C49: Sichuan | D49: =VIPcric_2!F871 -> 8102 | E49: =VIPcric_2!D881 -> 10.5 | F49: =(10+19+150+605*1.05)/30 -> 27.141667 | I49: =H49/D49 -> 0 | J49: =G49/D49 -> 0
A50: =VIPcric_2!I900 -> CRIC-宜春-市场监测.商品房市场.项目累计.供求.xlsx | B50: =MID(A50,6,2) -> 宜春 | C50: Jiangxi | D50: =VIPcric_2!F900 -> 9347 | E50: =VIPcric_2!D909 -> 508.3 | F50: =(10+19+150+605*1.05)/30 -> 27.141667 | I50: =H50/D50 -> 0 | J50: =G50/D50 -> 0
A51: =VIPcric_2!I917 -> CRIC-宝鸡-市场监测.商品房市场.项目累计.供求.xlsx | B51: =MID(A51,6,2) -> 宝鸡 | C51: Shananxi | D51: =VIPcric_2!F917 -> 6367 | E51: =VIPcric_2!D927 -> 138.5 | F51: =(10+19+155+625*1.05)/30 -> 28.008333 | I51: =H51/D51 -> 0 | J51: =G51/D51 -> 0
A52: =VIPcric_2!I949 -> CRIC-屯昌-市场监测.商品房市场.项目累计.供求.xlsx | B52: 屯昌县 | C52: Hainan | D52: =VIPcric_2!F949 -> 8395 | E52: =VIPcric_2!E957 -> 75 | F52: =(10+19+150+605*1.05)/30 -> 27.141667 | G52: =屯昌!F89 -> 761.14667 | H52: =屯昌!N88 -> 39.099713 | I52: =H52/D52 -> 0.0046575 | J52: =G52/D52 -> 0.090666667
A53: =VIPcric_2!I964 -> CRIC-岳阳-市场监测.商品房市场.项目累计.供求.xlsx | B53: =MID(A53,6,2) -> 岳阳 | C53: Hunan | D53: =VIPcric_2!F964 -> 6854 | E53: =VIPcric_2!D974 -> 13.7 | F53: =(10+19+150+605*1.05)/30 -> 27.141667 | I53: =H53/D53 -> 0 | J53: =G53/D53 -> 0
A54: =VIPcric_2!I981 -> CRIC-嵊州-市场监测.商品房市场.项目累计.供求.xlsx | B54: =MID(A54,6,2) -> 嵊州 | C54: Zhejiang | D54: =VIPcric_2!F981 -> 11777 | E54: =VIPcric_2!D991 -> 18 | F54: =(10+19+150+605*1.05)/30 -> 27.141667 | I54: =H54/D54 -> 0 | J54: =G54/D54 -> 0
A55: =VIPcric_2!I1000 -> CRIC-常州-市场监测.商品房市场.项目累计.供求.xlsx | B55: =MID(A55,6,2) -> 常州 | C55: Jiangsu | D55: =VIPcric_2!F1000 -> 16519 | E55: =VIPcric_2!D1011 -> 25.8 | F55: =(10+19+150+605*1.05)/30 -> 27.141667 | I55: =H55/D55 -> 0 | J55: =G55/D55 -> 0
A56: =VIPcric_2!I1020 -> CRIC-常德-市场监测.商品房市场.城市总量.xlsx | B56: =MID(A56,6,2) -> 常德 | C56: Hunan | D56: =VIPcric_2!D1020 -> 6487 | E56: =VIPcric_2!F1020 -> 8.2120028 | F56: =(10+19+150+605*1.05)/30 -> 27.141667 | I56: =H56/D56 -> 0 | J56: =G56/D56 -> 0
A57: =VIPcric_2!I1040 -> CRIC-常熟-市场监测.商品房市场.项目累计.供求.xlsx | B57: =MID(A57,6,2) -> 常熟 | C57: Jiangsu | D57: =VIPcric_2!F1040 -> 15775 | E57: =VIPcric_2!D1049 -> 26.8 | F57: =(10+19+150+605*1.05)/30 -> 27.141667 | I57: =H57/D57 -> 0 | J57: =G57/D57 -> 0
A58: =VIPcric_2!I1058 -> CRIC-平顶山-市场监测.商品房市场.项目累计.供求.xlsx | B58: =MID(A58,6,3) -> 平顶山 | C58: Henan | D58: =VIPcric_2!F1058 -> 7122 | E58: =VIPcric_2!D1067 -> 25 | F58: =(10+19+155+625*1.05)/30 -> 28.008333 | I58: =H58/D58 -> 0 | J58: =G58/D58 -> 0
A59: =VIPcric_2!I1075 -> CRIC-广安-市场监测.商品房市场.项目累计.供求.xlsx | B59: =MID(A59,6,2) -> 广安 | C59: Sichuan | D59: =VIPcric_2!F1075 -> 6184 | E59: =VIPcric_2!D1084 -> 11.7 | F59: =(10+19+150+605*1.05)/30 -> 27.141667 | I59: =H59/D59 -> 0 | J59: =G59/D59 -> 0
A60: =VIPcric_2!I1090 -> CRIC-广州-市场监测.商品房市场.项目累计.供求.xlsx | B60: =MID(A60,6,2) -> 广州 | C60: Guangdong | D60: =VIPcric_2!F1090 -> 37881 | E60: =VIPcric_2!D1100 -> 17.6 | F60: =(10+19+150+605*1.05)/30 -> 27.141667 | G60: =广州!F89 -> 6177.1858 | H60: =广州!P88 -> 809.7548 | I60: =H60/D60 -> 0.021376278 | J60: =G60/D60 -> 0.16306818
A61: =VIPcric_2!I1115 -> CRIC-廊坊-市场监测.商品房市场.项目累计.供求.xlsx | B61: =MID(A61,6,2) -> 廊坊 | C61: Hebei | D61: =VIPcric_2!F1115 -> 9213 | E61: =VIPcric_2!F1112 -> 24 | F61: =(10+19+155+625*1.05)/30 -> 28.008333 | I61: =H61/D61 -> 0 | J61: =G61/D61 -> 0
A62: =VIPcric_2!I1126 -> CRIC-建德-市场监测.商品房市场.项目累计.供求 (1).xlsx | B62: =MID(A62,6,2) -> 建德 | C62: Zhejiang | D62: =VIPcric_2!F1126 -> 16254 | E62: =VIPcric_2!D1136 -> 27.5 | F62: =(10+19+150+605*1.05)/30 -> 27.141667 | I62: =H62/D62 -> 0 | J62: =G62/D62 -> 0
A63: =VIPcric_2!I1145 -> CRIC-张家港-市场监测.商品房市场.项目累计.供求.xlsx | B63: =MID(A63,6,3) -> 张家港 | C63: Jiangsu | D63: =VIPcric_2!F1145 -> 15801 | E63: =VIPcric_2!D1155 -> 27 | F63: =(10+19+150+605*1.05)/30 -> 27.141667 | I63: =H63/D63 -> 0 | J63: =G63/D63 -> 0
A64: =VIPcric_2!I1179 -> CRIC-徐州-市场监测.商品房市场.项目累计.供求.xlsx | B64: =MID(A64,6,2) -> 徐州 | C64: Jiangsu | D64: =VIPcric_2!F1179 -> 9562 | E64: =VIPcric_2!D1189 -> 16.7 | F64: =(10+19+150+605*1.05)/30 -> 27.141667 | I64: =H64/D64 -> 0 | J64: =G64/D64 -> 0
A65: =VIPcric_2!I1198 -> CRIC-德清-市场监测.商品房市场.项目累计.供求.xlsx | B65: =MID(A65,6,2) -> 德清 | C65: Zhejiang | D65: =VIPcric_2!F1198 -> 17132 | E65: =VIPcric_2!D1208 -> 44 | F65: =(10+19+150+605*1.05)/30 -> 27.141667 | I65: =H65/D65 -> 0 | J65: =G65/D65 -> 0
A66: =VIPcric_2!I1216 -> CRIC-德阳-市场监测.商品房市场.项目累计.供求.xlsx | B66: =MID(A66,6,2) -> 德阳 | C66: Sichuan | D66: =VIPcric_2!F1216 -> 9300 | E66: =VIPcric_2!D1225 -> 37.7 | F66: =(10+19+150+605*1.05)/30 -> 27.141667 | I66: =H66/D66 -> 0 | J66: =G66/D66 -> 0
A67: =VIPcric_2!I1232 -> CRIC-惠州-市场监测.商品房市场.项目累计.供求.xlsx | B67: =MID(A67,6,2) -> 惠州 | C67: Guangdong | D67: =VIPcric_2!F1232 -> 12824 | E67: =VIPcric_2!D1242 -> 25.1 | F67: =(10+19+150+605*1.05)/30 -> 27.141667 | G67: =惠州!F89 -> 4281.4789 | H67: =惠州!P88 -> 307.49627 | I67: =H67/D67 -> 0.023978187 | J67: =G67/D67 -> 0.33386454
A68: =VIPcric_2!I1249 -> CRIC-成都-市场监测.商品房市场.项目累计.供求.xlsx | B68: =MID(A68,6,2) -> 成都 | C68: Sichuan | D68: =VIPcric_2!F1249 -> 19262 | E68: =VIPcric_2!D1258 -> 13.7 | F68: =(10+19+150+605*1.05)/30 -> 27.141667 | I68: =H68/D68 -> 0 | J68: =G68/D68 -> 0
A69: =VIPcric_2!I1291 -> CRIC-拉萨-市场监测.商品房市场.项目累计.供求.xlsx | B69: =MID(A69,6,2) -> 拉萨 | C69: Tibet | D69: =VIPcric_2!F1291 -> 7137 | E69: =VIPcric_2!D1301 -> 32.3 | F69: =(10+19+160+665*1.05)/30 -> 29.575 | I69: =H69/D69 -> 0 | J69: =G69/D69 -> 0
A70: =VIPcric_2!I1310 -> CRIC-文昌-市场监测.商品房市场.项目累计.供求.xlsx | B70: =MID(A70,6,2) -> 文昌 | C70: Hainan | D70: =VIPcric_2!F1310 -> 12355 | E70: =VIPcric_2!D1320 -> 111.2 | F70: =(10+19+150+605*1.05)/30 -> 27.141667 | G70: =文昌!F89 -> 755.52158 | H70: =文昌!N88 -> 38.810755 | I70: =H70/D70 -> 0.0031412995 | J70: =G70/D70 -> 0.061151079
A71: =VIPcric_2!I1327 -> CRIC-无锡-市场监测.商品房市场.项目累计.供求.xlsx | B71: =MID(A71,6,2) -> 无锡 | C71: Jiangsu | D71: =VIPcric_2!F1327 -> 22520 | E71: =VIPcric_2!D1337 -> 22.5 | F71: =(10+19+150+605*1.05)/30 -> 27.141667 | I71: =H71/D71 -> 0 | J71: =G71/D71 -> 0
A72: =VIPcric_2!I1345 -> CRIC-日照-市场监测.商品房市场.项目累计.供求.xlsx | B72: =MID(A72,6,2) -> 日照 | C72: Shandong | D72: =VIPcric_2!F1345 -> 9769 | E72: =VIPcric_2!D1355 -> 76 | F72: =(10+19+155+625*1.05)/30 -> 28.008333 | I72: =H72/D72 -> 0 | J72: =G72/D72 -> 0
A73: =VIPcric_2!I1364 -> CRIC-昆山-市场监测.商品房市场.项目累计.供求.xlsx | B73: =MID(A73,6,2) -> 昆山 | C73: Jiangsu | D73: =VIPcric_2!F1364 -> 23023 | E73: =VIPcric_2!D1374 -> 18.2 | F73: =(10+19+150+605*1.05)/30 -> 27.141667 | I73: =H73/D73 -> 0 | J73: =G73/D73 -> 0
A74: =VIPcric_2!I1382 -> CRIC-昆明-市场监测.商品房市场.项目累计.供求 (1).xlsx | B74: =MID(A74,6,2) -> 昆明 | C74: Yunnan | D74: =VIPcric_2!F1382 -> 13533 | E74: =VIPcric_2!D1391 -> 19.3 | F74: =(10+19+150+605*1.05)/30 -> 27.141667 | I74: =H74/D74 -> 0 | J74: =G74/D74 -> 0
A75: =VIPcric_2!I1400 -> CRIC-昌江-市场监测.商品房市场.项目累计.供求.xlsx | B75: =MID(A75,6,2) -> 昌江 | C75: Hainan | D75: =VIPcric_2!F1400 -> 6880 | E75: =VIPcric_2!D1408 -> 18.1 | F75: =(10+19+150+605*1.05)/30 -> 27.141667 | G75: =昌江!F89 -> 2508.7293 | H75: =昌江!N88 -> 131.79381 | I75: =H75/D75 -> 0.019156077 | J75: =G75/D75 -> 0.36464088
A76: =VIPcric_2!I1429 -> CRIC-晋江-市场监测.商品房市场.项目累计.供求.xlsx | B76: =MID(A76,6,2) -> 晋江 | C76: Fujian | D76: =VIPcric_2!F1429 -> 12985 | E76: =VIPcric_2!D1439 -> 25.5 | F76: =(10+19+150+605*1.05)/30 -> 27.141667 | I76: =H76/D76 -> 0 | J76: =G76/D76 -> 0
A77: =VIPcric_2!I1447 -> CRIC-景德镇-市场监测.商品房市场.项目累计.供求.xlsx | B77: =MID(A77,6,3) -> 景德镇 | C77: Jiangxi | D77: =VIPcric_2!F1447 -> 7871 | E77: =VIPcric_2!D1457 -> 35.5 | F77: =(10+19+150+605*1.05)/30 -> 27.141667 | I77: =H77/D77 -> 0 | J77: =G77/D77 -> 0
A78: =VIPcric_2!I1464 -> CRIC-杭州-市场监测.商品房市场.项目累计.供求.xlsx | B78: =MID(A78,6,2) -> 杭州 | C78: Zhejiang | D78: =VIPcric_2!F1464 -> 32322 | E78: =VIPcric_2!D1473 -> 4.5 | F78: =(10+19+150+605*1.05)/30 -> 27.141667 | I78: =H78/D78 -> 0 | J78: =G78/D78 -> 0
A79: =VIPcric_2!I1491 -> CRIC-桐乡-市场监测.商品房市场.项目累计.供求.xlsx | B79: =MID(A79,6,2) -> 桐乡 | C79: Zhejiang | D79: =VIPcric_2!F1491 -> 17669 | E79: =VIPcric_2!D1501 -> 16.3 | F79: =(10+19+150+605*1.05)/30 -> 27.141667 | I79: =H79/D79 -> 0 | J79: =G79/D79 -> 0
A80: =VIPcric_2!I1511 -> CRIC-桐庐-市场监测.商品房市场.项目累计.供求.xlsx | B80: =MID(A80,6,2) -> 桐庐 | C80: Zhejiang | D80: =VIPcric_2!F1511 -> 18035 | E80: =VIPcric_2!D1521 -> 33.8 | F80: =(10+19+150+605*1.05)/30 -> 27.141667 | I80: =H80/D80 -> 0 | J80: =G80/D80 -> 0
A81: =VIPcric_2!I1529 -> CRIC-武汉-市场监测.商品房市场.项目累计.供求.xlsx | B81: =MID(A81,6,2) -> 武汉 | C81: Hubei | D81: =VIPcric_2!F1529 -> 16780 | E81: =VIPcric_2!D1539 -> 17.9 | F81: =(10+19+150+605*1.05)/30 -> 27.141667 | I81: =H81/D81 -> 0 | J81: =G81/D81 -> 0
A82: =VIPcric_2!I1547 -> CRIC-毕节-市场监测.商品房市场.项目累计.供求.xlsx | B82: =MID(A82,6,2) -> 毕节 | C82: Guizhou | D82: =VIPcric_2!F1547 -> 5285 | E82: =VIPcric_2!D1557 -> 35.3 | F82: =(10+19+150+605*1.05)/30 -> 27.141667 | I82: =H82/D82 -> 0 | J82: =G82/D82 -> 0
A83: =VIPcric_2!I1563 -> CRIC-汉中-市场监测.商品房市场.项目累计.供求.xlsx | B83: =MID(A83,6,2) -> 汉中 | C83: Shananxi | D83: =VIPcric_2!F1563 -> 5476 | E83: =VIPcric_2!D1572 -> 38.9 | F83: =(10+19+155+625*1.05)/30 -> 28.008333 | I83: =H83/D83 -> 0 | J83: =G83/D83 -> 0
A84: =VIPcric_2!I1578 -> CRIC-汕头-市场监测.商品房市场.项目累计.供求.xlsx | B84: =MID(A84,6,2) -> 汕头 | C84: Guangdong | D84: =VIPcric_2!F1578 -> 10573 | E84: =VIPcric_2!D1588 -> 34.1 | F84: =(10+19+150+605*1.05)/30 -> 27.141667 | G84: =汕头!F89 -> 3485.5865 | H84: =汕头!P88 -> 380.94829 | I84: =H84/D84 -> 0.036030293 | J84: =G84/D84 -> 0.32966864
A85: =VIPcric_2!I1597 -> CRIC-江阴-市场监测.商品房市场.项目累计.供求.xlsx | B85: =MID(A85,6,2) -> 江阴 | C85: Jiangsu | D85: =VIPcric_2!F1597 -> 13858 | E85: =VIPcric_2!D1607 -> 28 | F85: =(10+19+150+605*1.05)/30 -> 27.141667 | I85: =H85/D85 -> 0 | J85: =G85/D85 -> 0
A86: =VIPcric_2!I1616 -> CRIC-池州-市场监测.商品房市场.项目累计.供求.xlsx | B86: =MID(A86,6,2) -> 池州 | C86: Guangxi | D86: =VIPcric_2!F1616 -> 7825 | E86: =VIPcric_2!D1625 -> 38.3 | F86: =(10+19+150+605*1.05)/30 -> 27.141667 | I86: =H86/D86 -> 0 | J86: =G86/D86 -> 0
A87: =VIPcric_2!I1633 -> CRIC-沈阳-市场监测.商品房市场.项目累计.供求.xlsx | B87: =MID(A87,6,2) -> 沈阳 | C87: Liaoning | D87: =VIPcric_2!F1633 -> 10417 | E87: =VIPcric_2!D1642 -> 35.8 | F87: =(10+19+160+665*1.05)/30 -> 29.575 | I87: =H87/D87 -> 0 | J87: =G87/D87 -> 0
A88: =VIPcric_2!I1651 -> CRIC-泉州-市场监测.商品房市场.项目累计.供求.xlsx | B88: =MID(A88,6,2) -> 泉州 | C88: Fujian | D88: =VIPcric_2!F1651 -> 13023 | E88: =VIPcric_2!D1661 -> 22.3 | F88: =(10+19+150+605*1.05)/30 -> 27.141667 | I88: =H88/D88 -> 0 | J88: =G88/D88 -> 0
A89: =VIPcric_2!I1669 -> CRIC-泰州-市场监测.商品房市场.项目累计.供求.xlsx | B89: =MID(A89,6,2) -> 泰州 | C89: Jiangsu | D89: =VIPcric_2!F1669 -> 16139 | E89: =VIPcric_2!F1667 -> 14.681319 | F89: =(10+19+150+605*1.05)/30 -> 27.141667 | I89: =H89/D89 -> 0 | J89: =G89/D89 -> 0
A90: =VIPcric_2!I1678 -> CRIC-泸州-市场监测.商品房市场.项目累计.供求.xlsx | B90: =MID(A90,6,2) -> 泸州 | C90: Sichuan | D90: =VIPcric_2!F1678 -> 6507 | E90: =VIPcric_2!D1688 -> 43.8 | F90: =(10+19+150+605*1.05)/30 -> 27.141667 | I90: =H90/D90 -> 0 | J90: =G90/D90 -> 0
A91: =VIPcric_2!I1696 -> CRIC-洛阳-市场监测.商品房市场.项目累计.供求.xlsx | B91: =MID(A91,6,2) -> 洛阳 | C91: Henan | D91: =VIPcric_2!F1696 -> 9567 | E91: =VIPcric_2!D1706 -> 25.6 | F91: =(10+19+155+625*1.05)/30 -> 28.008333 | I91: =H91/D91 -> 0 | J91: =G91/D91 -> 0
A92: =VIPcric_2!I1713 -> CRIC-济南-市场监测.商品房市场.项目累计.供求.xlsx | B92: =MID(A92,6,2) -> 济南 | C92: Shandong | D92: =VIPcric_2!F1713 -> 17887 | E92: =VIPcric_2!D1722 -> 12.1 | F92: =(10+19+155+625*1.05)/30 -> 28.008333 | I92: =H92/D92 -> 0 | J92: =G92/D92 -> 0
A93: =VIPcric_2!I1731 -> CRIC-海东地区-市场监测.商品房市场.项目累计.供求.xlsx | B93: =MID(A93,6,2) -> 海东 | C93: Qinghai | D93: =VIPcric_2!F1731 -> 5859 | E93: =VIPcric_2!D1740 -> 38.6 | F93: =(10+19+160+665*1.05)/30 -> 29.575 | I93: =H93/D93 -> 0 | J93: =G93/D93 -> 0
A94: =VIPcric_2!I1746 -> CRIC-海北藏族自治州-市场监测.商品房市场.项目累计.供求.xlsx | B94: =MID(A94,6,4) -> 海北藏族 | C94: Qinghai | D94: =VIPcric_2!F1746 -> 4989 | E94: =VIPcric_2!D1755 -> 22.2 | F94: =(10+19+160+665*1.05)/30 -> 29.575 | I94: =H94/D94 -> 0 | J94: =G94/D94 -> 0
A95: =VIPcric_2!I1760 -> CRIC-海南藏族自治州-市场监测.商品房市场.项目累计.供求.xlsx | B95: =MID(A95,6,4) -> 海南藏族 | C95: Qinghai | D95: =VIPcric_2!F1760 -> 6309 | E95: =VIPcric_2!D1769 -> 28.4 | F95: =(10+19+160+665*1.05)/30 -> 29.575 | I95: =H95/D95 -> 0 | J95: =G95/D95 -> 0
A96: =VIPcric_2!I1774 -> CRIC-海口-市场监测.商品房市场.项目累计.供求.xlsx | B96: =MID(A96,6,2) -> 海口 | C96: Hainan | D96: =VIPcric_2!F1774 -> 18307 | E96: =VIPcric_2!D1783 -> 19.4 | F96: =(10+19+150+605*1.05)/30 -> 27.141667 | G96: =海口!Q10 -> 5000 | H96: =海口!N88 -> 427.89905 | I96: =H96/D96 -> 0.023373521 | J96: =G96/D96 -> 0.27311957
A97: =VIPcric_2!I1789 -> CRIC-海宁-市场监测.商品房市场.项目累计.供求.xlsx | B97: =MID(A97,6,2) -> 海宁 | C97: Zhejiang | D97: =VIPcric_2!F1789 -> 19706 | E97: =VIPcric_2!D1799 -> 39.2 | F97: =(10+19+150+605*1.05)/30 -> 27.141667 | I97: =H97/D97 -> 0 | J97: =G97/D97 -> 0
A98: =VIPcric_2!I1808 -> CRIC-海西蒙古族藏族自治州-市场监测.商品房市场.项目累计.供求.xlsx | B98: =MID(A98,6,5) -> 海西蒙古族 | C98: Qinghai | D98: =VIPcric_2!F1808 -> 5456 | E98: =VIPcric_2!D1817 -> 24.8 | F98: =(10+19+160+665*1.05)/30 -> 29.575 | I98: =H98/D98 -> 0 | J98: =G98/D98 -> 0
A99: =VIPcric_2!I1823 -> CRIC-淄博-市场监测.商品房市场.项目累计.供求.xlsx | B99: =MID(A99,6,2) -> 淄博 | C99: Shandong | D99: =VIPcric_2!F1823 -> 8077 | E99: =VIPcric_2!D1833 -> 31.9 | F99: =(10+19+155+625*1.05)/30 -> 28.008333 | I99: =H99/D99 -> 0 | J99: =G99/D99 -> 0
A100: =VIPcric_2!I1841 -> CRIC-淮北-市场监测.商品房市场.项目累计.供求.xlsx | B100: =MID(A100,6,2) -> 淮北 | C100: Anhui | D100: =VIPcric_2!F1841 -> 8130 | E100: =VIPcric_2!D1850 -> 24.5 | F100: =(10+19+150+605*1.05)/30 -> 27.141667 | I100: =H100/D100 -> 0 | J100: =G100/D100 -> 0
...

Sheet 六安
A1: 月份 | B1: 销售周期 | C1: 施工工期 | D1: 初始登记工期 | E1: 收入 | F1: 封顶前解 | K1: 封顶前占用月 | P1: 机会成本 | R1: 利率 | S1: =3.45%*3/12 -> 0.008625 | T1: =S1*12 -> 0.1035
G2: 封顶解 | L2: 封顶占用 | R2: 2023售价 | S2: =VIPcric_3!D20 -> 8031 | T2: 元/m2
H3: 竣备解 | M3: 竣备占用 | R3: 去化周期 | S3: =VIPcric_3!E20 -> 20.7 | T3: 月
I4: 初始登记 | J4: 风险 | N4: 初登占用 | O4: 风险占用 | R4: 到竣备需要 | S4: =(10+19+150+605*1.05)/30 -> 27.141667 | T4: 个月 | U4: 1.05 | V4: 中级装修
A5: =ROW()-4 -> 1 | C5: 1 | P5: =(F5*K5+G5*L5+H5*M5+I5*N5+J5*O5)*$S$1 -> 0 | R5: 到取证需要 | S5: =(10+19+150)/30 -> 5.9666667 | T5: 个月
A6: =ROW()-4 -> 2 | C6: 1 | P6: =(F6*K6+G6*L6+H6*M6+I6*N6+J6*O6)*$S$1 -> 0 | R6: 封顶需要 | S6: =(10+19+150+605*1.05-S7*30)/30 -> 20.141667 | T6: 个月
A7: =ROW()-4 -> 3 | C7: 1 | P7: =(F7*K7+G7*L7+H7*M7+I7*N7+J7*O7)*$S$1 -> 0 | R7: 装修需要 | S7: 7 | T7: 个月
A8: =ROW()-4 -> 4 | C8: 1 | P8: =(F8*K8+G8*L8+H8*M8+I8*N8+J8*O8)*$S$1 -> 0 | R8: 竣备需要 | S8: 2 | T8: 个月
A9: =ROW()-4 -> 5 | C9: 1 | P9: =(F9*K9+G9*L9+H9*M9+I9*N9+J9*O9)*$S$1 -> 0 | R9: 确权需要 | S9: 12 | T9: 个月
A10: =ROW()-4 -> 6 | C10: 1 | P10: =(F10*K10+G10*L10+H10*M10+I10*N10+J10*O10)*$S$1 -> 0 | R10: 重点监管 | S10: 2400
A11: =ROW()-4 -> 7 | B11: 1 | C11: 1 | E11: =1/$S$3*$S$2 -> 387.97101 | F11: =E11 -> 387.97101 | K11: 6 | P11: =(F11*K11+G11*L11+H11*M11+I11*N11+J11*O11)*$S$1 -> 20.0775
A12: =ROW()-4 -> 8 | B12: 1 | C12: 1 | E12: =1/$S$3*$S$2 -> 387.97101 | F12: =E12 -> 387.97101 | K12: =K11-1 -> 5 | P12: =(F12*K12+G12*L12+H12*M12+I12*N12+J12*O12)*$S$1 -> 16.73125
A13: =ROW()-4 -> 9 | B13: 1 | C13: 1 | E13: =1/$S$3*$S$2 -> 387.97101 | F13: =E13 -> 387.97101 | K13: =K12-1 -> 4 | P13: =(F13*K13+G13*L13+H13*M13+I13*N13+J13*O13)*$S$1 -> 13.385
A14: =ROW()-4 -> 10 | B14: 1 | C14: 1 | E14: =1/$S$3*$S$2 -> 387.97101 | F14: =E14 -> 387.97101 | K14: =K13-1 -> 3 | P14: =(F14*K14+G14*L14+H14*M14+I14*N14+J14*O14)*$S$1 -> 10.03875
A15: =ROW()-4 -> 11 | B15: 1 | C15: 1 | E15: =1/$S$3*$S$2 -> 387.97101 | F15: =E15 -> 387.97101 | K15: =K14-1 -> 2 | P15: =(F15*K15+G15*L15+H15*M15+I15*N15+J15*O15)*$S$1 -> 6.6925
A16: =ROW()-4 -> 12 | B16: 1 | C16: 1 | E16: =1/$S$3*$S$2 -> 387.97101 | F16: =E16 -> 387.97101 | K16: =K15-1 -> 1 | P16: =(F16*K16+G16*L16+H16*M16+I16*N16+J16*O16)*$S$1 -> 3.34625
A17: =ROW()-4 -> 13 | B17: 1 | C17: 1 | E17: =1/$S$3*$S$2 -> 387.97101 | G17: =E17*55% -> 213.38406 | L17: 3 | P17: =(F17*K17+G17*L17+H17*M17+I17*N17+J17*O17)*$S$1 -> 5.5213125
A18: =ROW()-4 -> 14 | B18: 1 | C18: 1 | E18: =1/$S$3*$S$2 -> 387.97101 | G18: =E18*55% -> 213.38406 | L18: 2 | P18: =(F18*K18+G18*L18+H18*M18+I18*N18+J18*O18)*$S$1 -> 3.680875
A19: =ROW()-4 -> 15 | B19: 1 | C19: 1 | E19: =1/$S$3*$S$2 -> 387.97101 | G19: =E19*55% -> 213.38406 | L19: 1 | P19: =(F19*K19+G19*L19+H19*M19+I19*N19+J19*O19)*$S$1 -> 1.8404375
A20: =ROW()-4 -> 16 | B20: 1 | C20: 1 | E20: =1/$S$3*$S$2 -> 387.97101 | H20: =E20*90% -> 349.17391 | M20: 12 | P20: =(F20*K20+G20*L20+H20*M20+I20*N20+J20*O20)*$S$1 -> 36.1395
A21: =ROW()-4 -> 17 | B21: 1 | C21: 1 | E21: =1/$S$3*$S$2 -> 387.97101 | M21: =M20-1 -> 11 | P21: =(F21*K21+G21*L21+H21*M21+I21*N21+J21*O21)*$S$1 -> 0
